Workbook

Sheet QC rev00
M2: Data Solicitação | P2: Início do Serviço | U2: Razão Social
D3: =MAX(C:C) -> 0 | E3: =Insumos!$C$1 -> 0 | P3: Término do Serviço | U3: Fantasia
D4: =MATCH($D$3,$C$10:$C$120,) -> 1 | E4: =Orçamento!$J$2+1 -> 4534 | H4: REV.09-09-2025 | M4: Nome/Nº OBRA | U4: Contato
F5: ="ORÇAMENTO: "&$P$4&" ("&$T$4&")" -> ORÇAMENTO: () | M5: Eng. Responsável | U5: Telefone
F6: ="ORÇAMENTO: "&$P$4&" ("&$T$4&")" -> ORÇAMENTO: () | M6: Suprimentos Responsável | P6: Adriano Carvalho | U6: Email
M7: {=IF(SUM(IF(OR($O$2="",$P$4="",$P$5="",$P$6="",$I$141="",$I$142="",$I$139="",$T2="",$T3=""),1,0))+SUM(IF($Y$2:$BC$2<>"",IF($Y$3:$BC$8="",1)))>0, "Faltam Campos a serem preenchidos",IF('Solic. Contrato'!$P$18="VÍNCULOS NÃO INDICADOS / ERRO NA QUANTIDADE VINCULADA","Falta de vínculos PL",""))} -> Faltam Campos a serem preenchidos | U7: CNPJ/CPF | V7: Melhores Condições
F8: Ordem | G8: Código Insumo | H8: Descrição do Insumo | I8: Unidade | J8: QUANT. | K8: R$ UNIT. | L8: R$ TOTAL | M8: Insumo | N8: ESCOPO DOS SERVIÇOS | Q8: OBS. CONTRATOS | U8: Validade CND
M9: Orçado | N9: Cod. | O9: Descrição | Q9: %Mat. | R9: %Equip. | S9: %Ret. | T9: Unidade | U9: QUANT. | V9: Fornecedor | W9: R$ UNIT. | X9: R$ TOTAL | Y9: R$ UNIT. | Z9: R$ TOTAL | AA9: OBS | AB9: R$ UNIT. | AC9: R$ TOTAL | AD9: OBS | AE9: R$ UNIT. | AF9: R$ TOTAL | AG9: OBS | AH9: R$ UNIT. | AI9: R$ TOTAL | AJ9: OBS | AK9: R$ UNIT. | AL9: R$ TOTAL | AM9: OBS | AN9: R$ UNIT. | AO9: R$ TOTAL | AP9: OBS | AQ9: R$ UNIT. | AR9: R$ TOTAL | AS9: OBS | AT9: R$ UNIT. | AU9: R$ TOTAL | AV9: OBS | AW9: R$ UNIT. | AX9: R$ TOTAL | AY9: OBS | AZ9: R$ UNIT. | BA9: R$ TOTAL | BB9: OBS
B10: =IF(C10=0,"",MATCH(_xlfn.MINIFS(Y10:BC10,Y$9:BC$9,$Y$9,Y10:BC10,"<>0",Y10:BC10,"<>"""),Y10:BC10,)) | C10: =IF(AND(N10<>"",N10<>0),MAX($C$8:$C9)+1,0) -> 0 | D10: =IF($F10>$E$3,"",_xlfn.MAXIFS(OFFSET(Orçamento!$G$5,$E10-5,,$E$4-$E10+5,),OFFSET(Orçamento!$N$5,$E10-5,,$E$4-$E10+5,),$G10)+1-E10+5) | E10: =IF($F10>$E$3,"",_xlfn.IFNA(MATCH($G10,Orçamento!$N:$N,),"")) | F10: 1 | G10: =IF($F10>$E$3,"",INDEX(Insumos!$C:$C,MATCH($F10,Insumos!$B:$B,),1)) | H10: {=IF($E10="","",INDEX(Orçamento!$O:$O,$E10,1))} | I10: {=IF($E10="","",INDEX(Orçamento!$Q:$Q,$E10,1))} | J10: =IF($D10="",0,SUMIF(OFFSET(Orçamento!$N$5,$E10-5,,$D10,),$G10,OFFSET(Orçamento!$I$5,$E10-5,,$D10,))) -> 0 | K10: {=IF($E10="",0,INDEX(Orçamento!$S:$S,$E10,1))} -> 0 | L10: =J10*K10 -> 0 | M10: =N10 | N10: =G10 | V10: {=IF($C10=0,0,INDEX($X$2:$BC$2,1,$B10+1))} -> 0 | W10: {=IF($C10=0,0,INDEX($X10:$BC10,1,$B10+1))} -> 0 | X10: =W10*U10 -> 0 | Z10: =Y10*$U10 -> 0 | AC10: =AB10*$U10 -> 0 | AF10: =AE10*$U10 -> 0 | AI10: =AH10*$U10 -> 0 | AL10: =AK10*$U10 -> 0 | AO10: =AN10*$U10 -> 0 | AR10: =AQ10*$U10 -> 0 | AU10: =AT10*$U10 -> 0 | AX10: =AW10*$U10 -> 0 | BA10: =AZ10*$U10 -> 0
B11: =IF(C11=0,"",MATCH(_xlfn.MINIFS(Y11:BC11,Y$9:BC$9,$Y$9,Y11:BC11,"<>0",Y11:BC11,"<>"""),Y11:BC11,)) | C11: =IF(AND(N11<>"",N11<>0),MAX($C$8:$C10)+1,0) -> 0 | D11: =IF($F11>$E$3,"",_xlfn.MAXIFS(OFFSET(Orçamento!$G$5,$E11-5,,$E$4-$E11+5,),OFFSET(Orçamento!$N$5,$E11-5,,$E$4-$E11+5,),$G11)+1-E11+5) | E11: =IF($F11>$E$3,"",_xlfn.IFNA(MATCH($G11,Orçamento!$N:$N,),"")) | F11: {=OFFSET(F11,-1,,,)+1} -> 2 | G11: =IF($F11>$E$3,"",INDEX(Insumos!$C:$C,MATCH($F11,Insumos!$B:$B,),1)) | H11: {=IF($E11="","",INDEX(Orçamento!$O:$O,$E11,1))} | I11: {=IF($E11="","",INDEX(Orçamento!$Q:$Q,$E11,1))} | J11: =IF($D11="",0,SUMIF(OFFSET(Orçamento!$N$5,$E11-5,,$D11,),$G11,OFFSET(Orçamento!$I$5,$E11-5,,$D11,))) -> 0 | K11: {=IF($E11="",0,INDEX(Orçamento!$S:$S,$E11,1))} -> 0 | L11: =J11*K11 -> 0 | M11: =N11 | N11: =G11 | O11: =H11 | T11: =I11 | U11: =J11 -> 0 | V11: {=IF($C11=0,0,INDEX($X$2:$BC$2,1,$B11+1))} -> 0 | W11: {=IF($C11=0,0,INDEX($X11:$BC11,1,$B11+1))} -> 0 | X11: =W11*U11 -> 0 | Z11: =Y11*$U11 -> 0 | AC11: =AB11*$U11 -> 0 | AF11: =AE11*$U11 -> 0 | AI11: =AH11*$U11 -> 0 | AL11: =AK11*$U11 -> 0 | AO11: =AN11*$U11 -> 0 | AR11: =AQ11*$U11 -> 0 | AU11: =AT11*$U11 -> 0 | AX11: =AW11*$U11 -> 0 | BA11: =AZ11*$U11 -> 0
B12: =IF(C12=0,"",MATCH(_xlfn.MINIFS(Y12:BC12,Y$9:BC$9,$Y$9,Y12:BC12,"<>0",Y12:BC12,"<>"""),Y12:BC12,)) | C12: =IF(AND(N12<>"",N12<>0),MAX($C$8:$C11)+1,0) -> 0 | D12: =IF($F12>$E$3,"",_xlfn.MAXIFS(OFFSET(Orçamento!$G$5,$E12-5,,$E$4-$E12+5,),OFFSET(Orçamento!$N$5,$E12-5,,$E$4-$E12+5,),$G12)+1-E12+5) | E12: =IF($F12>$E$3,"",_xlfn.IFNA(MATCH($G12,Orçamento!$N:$N,),"")) | F12: {=OFFSET(F12,-1,,,)+1} -> 3 | G12: =IF($F12>$E$3,"",INDEX(Insumos!$C:$C,MATCH($F12,Insumos!$B:$B,),1)) | H12: {=IF($E12="","",INDEX(Orçamento!$O:$O,$E12,1))} | I12: {=IF($E12="","",INDEX(Orçamento!$Q:$Q,$E12,1))} | J12: =IF($D12="",0,SUMIF(OFFSET(Orçamento!$N$5,$E12-5,,$D12,),$G12,OFFSET(Orçamento!$I$5,$E12-5,,$D12,))) -> 0 | K12: {=IF($E12="",0,INDEX(Orçamento!$S:$S,$E12,1))} -> 0 | L12: =J12*K12 -> 0 | M12: =N12 | N12: =G12 | O12: =H12 | T12: =I12 | U12: =J12 -> 0 | V12: {=IF($C12=0,0,INDEX($X$2:$BC$2,1,$B12+1))} -> 0 | W12: {=IF($C12=0,0,INDEX($X12:$BC12,1,$B12+1))} -> 0 | X12: =W12*U12 -> 0 | Z12: =Y12*$U12 -> 0 | AC12: =AB12*$U12 -> 0 | AF12: =AE12*$U12 -> 0 | AI12: =AH12*$U12 -> 0 | AL12: =AK12*$U12 -> 0 | AO12: =AN12*$U12 -> 0 | AR12: =AQ12*$U12 -> 0 | AU12: =AT12*$U12 -> 0 | AX12: =AW12*$U12 -> 0 | BA12: =AZ12*$U12 -> 0
B13: =IF(C13=0,"",MATCH(_xlfn.MINIFS(Y13:BC13,Y$9:BC$9,$Y$9,Y13:BC13,"<>0",Y13:BC13,"<>"""),Y13:BC13,)) | C13: =IF(AND(N13<>"",N13<>0),MAX($C$8:$C12)+1,0) -> 0 | D13: =IF($F13>$E$3,"",_xlfn.MAXIFS(OFFSET(Orçamento!$G$5,$E13-5,,$E$4-$E13+5,),OFFSET(Orçamento!$N$5,$E13-5,,$E$4-$E13+5,),$G13)+1-E13+5) | E13: =IF($F13>$E$3,"",_xlfn.IFNA(MATCH($G13,Orçamento!$N:$N,),"")) | F13: {=OFFSET(F13,-1,,,)+1} -> 4 | G13: =IF($F13>$E$3,"",INDEX(Insumos!$C:$C,MATCH($F13,Insumos!$B:$B,),1)) | H13: {=IF($E13="","",INDEX(Orçamento!$O:$O,$E13,1))} | I13: {=IF($E13="","",INDEX(Orçamento!$Q:$Q,$E13,1))} | J13: =IF($D13="",0,SUMIF(OFFSET(Orçamento!$N$5,$E13-5,,$D13,),$G13,OFFSET(Orçamento!$I$5,$E13-5,,$D13,))) -> 0 | K13: {=IF($E13="",0,INDEX(Orçamento!$S:$S,$E13,1))} -> 0 | L13: =J13*K13 -> 0 | M13: =N13 | N13: =G13 | O13: =H13 | T13: =I13 | U13: =J13 -> 0 | V13: {=IF($C13=0,0,INDEX($X$2:$BC$2,1,$B13+1))} -> 0 | W13: {=IF($C13=0,0,INDEX($X13:$BC13,1,$B13+1))} -> 0 | X13: =W13*U13 -> 0 | Z13: =Y13*$U13 -> 0 | AC13: =AB13*$U13 -> 0 | AF13: =AE13*$U13 -> 0 | AI13: =AH13*$U13 -> 0 | AL13: =AK13*$U13 -> 0 | AO13: =AN13*$U13 -> 0 | AR13: =AQ13*$U13 -> 0 | AU13: =AT13*$U13 -> 0 | AX13: =AW13*$U13 -> 0 | BA13: =AZ13*$U13 -> 0
B14: =IF(C14=0,"",MATCH(_xlfn.MINIFS(Y14:BC14,Y$9:BC$9,$Y$9,Y14:BC14,"<>0",Y14:BC14,"<>"""),Y14:BC14,)) | C14: =IF(AND(N14<>"",N14<>0),MAX($C$8:$C13)+1,0) -> 0 | D14: =IF($F14>$E$3,"",_xlfn.MAXIFS(OFFSET(Orçamento!$G$5,$E14-5,,$E$4-$E14+5,),OFFSET(Orçamento!$N$5,$E14-5,,$E$4-$E14+5,),$G14)+1-E14+5) | E14: =IF($F14>$E$3,"",_xlfn.IFNA(MATCH($G14,Orçamento!$N:$N,),"")) | F14: {=OFFSET(F14,-1,,,)+1} -> 5 | G14: =IF($F14>$E$3,"",INDEX(Insumos!$C:$C,MATCH($F14,Insumos!$B:$B,),1)) | H14: {=IF($E14="","",INDEX(Orçamento!$O:$O,$E14,1))} | I14: {=IF($E14="","",INDEX(Orçamento!$Q:$Q,$E14,1))} | J14: =IF($D14="",0,SUMIF(OFFSET(Orçamento!$N$5,$E14-5,,$D14,),$G14,OFFSET(Orçamento!$I$5,$E14-5,,$D14,))) -> 0 | K14: {=IF($E14="",0,INDEX(Orçamento!$S:$S,$E14,1))} -> 0 | L14: =J14*K14 -> 0 | M14: =N14 | N14: =G14 | O14: =H14 | T14: =I14 | U14: =J14 -> 0 | V14: {=IF($C14=0,0,INDEX($X$2:$BC$2,1,$B14+1))} -> 0 | W14: {=IF($C14=0,0,INDEX($X14:$BC14,1,$B14+1))} -> 0 | X14: =W14*U14 -> 0 | Z14: =Y14*$U14 -> 0 | AC14: =AB14*$U14 -> 0 | AF14: =AE14*$U14 -> 0 | AI14: =AH14*$U14 -> 0 | AL14: =AK14*$U14 -> 0 | AO14: =AN14*$U14 -> 0 | AR14: =AQ14*$U14 -> 0 | AU14: =AT14*$U14 -> 0 | AX14: =AW14*$U14 -> 0 | BA14: =AZ14*$U14 -> 0
B15: =IF(C15=0,"",MATCH(_xlfn.MINIFS(Y15:BC15,Y$9:BC$9,$Y$9,Y15:BC15,"<>0",Y15:BC15,"<>"""),Y15:BC15,)) | C15: =IF(AND(N15<>"",N15<>0),MAX($C$8:$C14)+1,0) -> 0 | D15: =IF($F15>$E$3,"",_xlfn.MAXIFS(OFFSET(Orçamento!$G$5,$E15-5,,$E$4-$E15+5,),OFFSET(Orçamento!$N$5,$E15-5,,$E$4-$E15+5,),$G15)+1-E15+5) | E15: =IF($F15>$E$3,"",_xlfn.IFNA(MATCH($G15,Orçamento!$N:$N,),"")) | F15: {=OFFSET(F15,-1,,,)+1} -> 6 | G15: =IF($F15>$E$3,"",INDEX(Insumos!$C:$C,MATCH($F15,Insumos!$B:$B,),1)) | H15: {=IF($E15="","",INDEX(Orçamento!$O:$O,$E15,1))} | I15: {=IF($E15="","",INDEX(Orçamento!$Q:$Q,$E15,1))} | J15: =IF($D15="",0,SUMIF(OFFSET(Orçamento!$N$5,$E15-5,,$D15,),$G15,OFFSET(Orçamento!$I$5,$E15-5,,$D15,))) -> 0 | K15: {=IF($E15="",0,INDEX(Orçamento!$S:$S,$E15,1))} -> 0 | L15: =J15*K15 -> 0 | M15: =N15 | N15: =G15 | O15: =H15 | T15: =I15 | U15: =J15 -> 0 | V15: {=IF($C15=0,0,INDEX($X$2:$BC$2,1,$B15+1))} -> 0 | W15: {=IF($C15=0,0,INDEX($X15:$BC15,1,$B15+1))} -> 0 | X15: =W15*U15 -> 0 | Z15: =Y15*$U15 -> 0 | AC15: =AB15*$U15 -> 0 | AF15: =AE15*$U15 -> 0 | AI15: =AH15*$U15 -> 0 | AL15: =AK15*$U15 -> 0 | AO15: =AN15*$U15 -> 0 | AR15: =AQ15*$U15 -> 0 | AU15: =AT15*$U15 -> 0 | AX15: =AW15*$U15 -> 0 | BA15: =AZ15*$U15 -> 0
B16: =IF(C16=0,"",MATCH(_xlfn.MINIFS(Y16:BC16,Y$9:BC$9,$Y$9,Y16:BC16,"<>0",Y16:BC16,"<>"""),Y16:BC16,)) | C16: =IF(AND(N16<>"",N16<>0),MAX($C$8:$C15)+1,0) -> 0 | D16: =IF($F16>$E$3,"",_xlfn.MAXIFS(OFFSET(Orçamento!$G$5,$E16-5,,$E$4-$E16+5,),OFFSET(Orçamento!$N$5,$E16-5,,$E$4-$E16+5,),$G16)+1-E16+5) | E16: =IF($F16>$E$3,"",_xlfn.IFNA(MATCH($G16,Orçamento!$N:$N,),"")) | F16: {=OFFSET(F16,-1,,,)+1} -> 7 | G16: =IF($F16>$E$3,"",INDEX(Insumos!$C:$C,MATCH($F16,Insumos!$B:$B,),1)) | H16: {=IF($E16="","",INDEX(Orçamento!$O:$O,$E16,1))} | I16: {=IF($E16="","",INDEX(Orçamento!$Q:$Q,$E16,1))} | J16: =IF($D16="",0,SUMIF(OFFSET(Orçamento!$N$5,$E16-5,,$D16,),$G16,OFFSET(Orçamento!$I$5,$E16-5,,$D16,))) -> 0 | K16: {=IF($E16="",0,INDEX(Orçamento!$S:$S,$E16,1))} -> 0 | L16: =J16*K16 -> 0 | M16: =N16 | N16: =G16 | O16: =H16 | T16: =I16 | U16: =J16 -> 0 | V16: {=IF($C16=0,0,INDEX($X$2:$BC$2,1,$B16+1))} -> 0 | W16: {=IF($C16=0,0,INDEX($X16:$BC16,1,$B16+1))} -> 0 | X16: =W16*U16 -> 0 | Z16: =Y16*$U16 -> 0 | AC16: =AB16*$U16 -> 0 | AF16: =AE16*$U16 -> 0 | AI16: =AH16*$U16 -> 0 | AL16: =AK16*$U16 -> 0 | AO16: =AN16*$U16 -> 0 | AR16: =AQ16*$U16 -> 0 | AU16: =AT16*$U16 -> 0 | AX16: =AW16*$U16 -> 0 | BA16: =AZ16*$U16 -> 0
B17: =IF(C17=0,"",MATCH(_xlfn.MINIFS(Y17:BC17,Y$9:BC$9,$Y$9,Y17:BC17,"<>0",Y17:BC17,"<>"""),Y17:BC17,)) | C17: =IF(AND(N17<>"",N17<>0),MAX($C$8:$C16)+1,0) -> 0 | D17: =IF($F17>$E$3,"",_xlfn.MAXIFS(OFFSET(Orçamento!$G$5,$E17-5,,$E$4-$E17+5,),OFFSET(Orçamento!$N$5,$E17-5,,$E$4-$E17+5,),$G17)+1-E17+5) | E17: =IF($F17>$E$3,"",_xlfn.IFNA(MATCH($G17,Orçamento!$N:$N,),"")) | F17: {=OFFSET(F17,-1,,,)+1} -> 8 | G17: =IF($F17>$E$3,"",INDEX(Insumos!$C:$C,MATCH($F17,Insumos!$B:$B,),1)) | H17: {=IF($E17="","",INDEX(Orçamento!$O:$O,$E17,1))} | I17: {=IF($E17="","",INDEX(Orçamento!$Q:$Q,$E17,1))} | J17: =IF($D17="",0,SUMIF(OFFSET(Orçamento!$N$5,$E17-5,,$D17,),$G17,OFFSET(Orçamento!$I$5,$E17-5,,$D17,))) -> 0 | K17: {=IF($E17="",0,INDEX(Orçamento!$S:$S,$E17,1))} -> 0 | L17: =J17*K17 -> 0 | M17: =N17 | N17: =G17 | O17: =H17 | T17: =I17 | U17: =J17 -> 0 | V17: {=IF($C17=0,0,INDEX($X$2:$BC$2,1,$B17+1))} -> 0 | W17: {=IF($C17=0,0,INDEX($X17:$BC17,1,$B17+1))} -> 0 | X17: =W17*U17 -> 0 | Z17: =Y17*$U17 -> 0 | AC17: =AB17*$U17 -> 0 | AF17: =AE17*$U17 -> 0 | AI17: =AH17*$U17 -> 0 | AL17: =AK17*$U17 -> 0 | AO17: =AN17*$U17 -> 0 | AR17: =AQ17*$U17 -> 0 | AU17: =AT17*$U17 -> 0 | AX17: =AW17*$U17 -> 0 | BA17: =AZ17*$U17 -> 0
B18: =IF(C18=0,"",MATCH(_xlfn.MINIFS(Y18:BC18,Y$9:BC$9,$Y$9,Y18:BC18,"<>0",Y18:BC18,"<>"""),Y18:BC18,)) | C18: =IF(AND(N18<>"",N18<>0),MAX($C$8:$C17)+1,0) -> 0 | D18: =IF($F18>$E$3,"",_xlfn.MAXIFS(OFFSET(Orçamento!$G$5,$E18-5,,$E$4-$E18+5,),OFFSET(Orçamento!$N$5,$E18-5,,$E$4-$E18+5,),$G18)+1-E18+5) | E18: =IF($F18>$E$3,"",_xlfn.IFNA(MATCH($G18,Orçamento!$N:$N,),"")) | F18: {=OFFSET(F18,-1,,,)+1} -> 9 | G18: =IF($F18>$E$3,"",INDEX(Insumos!$C:$C,MATCH($F18,Insumos!$B:$B,),1)) | H18: {=IF($E18="","",INDEX(Orçamento!$O:$O,$E18,1))} | I18: {=IF($E18="","",INDEX(Orçamento!$Q:$Q,$E18,1))} | J18: =IF($D18="",0,SUMIF(OFFSET(Orçamento!$N$5,$E18-5,,$D18,),$G18,OFFSET(Orçamento!$I$5,$E18-5,,$D18,))) -> 0 | K18: {=IF($E18="",0,INDEX(Orçamento!$S:$S,$E18,1))} -> 0 | L18: =J18*K18 -> 0 | M18: =N18 | N18: =G18 | O18: =H18 | T18: =I18 | U18: =J18 -> 0 | V18: {=IF($C18=0,0,INDEX($X$2:$BC$2,1,$B18+1))} -> 0 | W18: {=IF($C18=0,0,INDEX($X18:$BC18,1,$B18+1))} -> 0 | X18: =W18*U18 -> 0 | Z18: =Y18*$U18 -> 0 | AC18: =AB18*$U18 -> 0 | AF18: =AE18*$U18 -> 0 | AI18: =AH18*$U18 -> 0 | AL18: =AK18*$U18 -> 0 | AO18: =AN18*$U18 -> 0 | AR18: =AQ18*$U18 -> 0 | AU18: =AT18*$U18 -> 0 | AX18: =AW18*$U18 -> 0 | BA18: =AZ18*$U18 -> 0
B19: =IF(C19=0,"",MATCH(_xlfn.MINIFS(Y19:BC19,Y$9:BC$9,$Y$9,Y19:BC19,"<>0",Y19:BC19,"<>"""),Y19:BC19,)) | C19: =IF(AND(N19<>"",N19<>0),MAX($C$8:$C18)+1,0) -> 0 | D19: =IF($F19>$E$3,"",_xlfn.MAXIFS(OFFSET(Orçamento!$G$5,$E19-5,,$E$4-$E19+5,),OFFSET(Orçamento!$N$5,$E19-5,,$E$4-$E19+5,),$G19)+1-E19+5) | E19: =IF($F19>$E$3,"",_xlfn.IFNA(MATCH($G19,Orçamento!$N:$N,),"")) | F19: {=OFFSET(F19,-1,,,)+1} -> 10 | G19: =IF($F19>$E$3,"",INDEX(Insumos!$C:$C,MATCH($F19,Insumos!$B:$B,),1)) | H19: {=IF($E19="","",INDEX(Orçamento!$O:$O,$E19,1))} | I19: {=IF($E19="","",INDEX(Orçamento!$Q:$Q,$E19,1))} | J19: =IF($D19="",0,SUMIF(OFFSET(Orçamento!$N$5,$E19-5,,$D19,),$G19,OFFSET(Orçamento!$I$5,$E19-5,,$D19,))) -> 0 | K19: {=IF($E19="",0,INDEX(Orçamento!$S:$S,$E19,1))} -> 0 | L19: =J19*K19 -> 0 | M19: =N19 | N19: =G19 | O19: =H19 | T19: =I19 | U19: =J19 -> 0 | V19: {=IF($C19=0,0,INDEX($X$2:$BC$2,1,$B19+1))} -> 0 | W19: {=IF($C19=0,0,INDEX($X19:$BC19,1,$B19+1))} -> 0 | X19: =W19*U19 -> 0 | Z19: =Y19*$U19 -> 0 | AC19: =AB19*$U19 -> 0 | AF19: =AE19*$U19 -> 0 | AI19: =AH19*$U19 -> 0 | AL19: =AK19*$U19 -> 0 | AO19: =AN19*$U19 -> 0 | AR19: =AQ19*$U19 -> 0 | AU19: =AT19*$U19 -> 0 | AX19: =AW19*$U19 -> 0 | BA19: =AZ19*$U19 -> 0
B20: =IF(C20=0,"",MATCH(_xlfn.MINIFS(Y20:BC20,Y$9:BC$9,$Y$9,Y20:BC20,"<>0",Y20:BC20,"<>"""),Y20:BC20,)) | C20: =IF(AND(N20<>"",N20<>0),MAX($C$8:$C19)+1,0) -> 0 | D20: =IF($F20>$E$3,"",_xlfn.MAXIFS(OFFSET(Orçamento!$G$5,$E20-5,,$E$4-$E20+5,),OFFSET(Orçamento!$N$5,$E20-5,,$E$4-$E20+5,),$G20)+1-E20+5) | E20: =IF($F20>$E$3,"",_xlfn.IFNA(MATCH($G20,Orçamento!$N:$N,),"")) | F20: {=OFFSET(F20,-1,,,)+1} -> 11 | G20: =IF($F20>$E$3,"",INDEX(Insumos!$C:$C,MATCH($F20,Insumos!$B:$B,),1)) | H20: {=IF($E20="","",INDEX(Orçamento!$O:$O,$E20,1))} | I20: {=IF($E20="","",INDEX(Orçamento!$Q:$Q,$E20,1))} | J20: =IF($D20="",0,SUMIF(OFFSET(Orçamento!$N$5,$E20-5,,$D20,),$G20,OFFSET(Orçamento!$I$5,$E20-5,,$D20,))) -> 0 | K20: {=IF($E20="",0,INDEX(Orçamento!$S:$S,$E20,1))} -> 0 | L20: =J20*K20 -> 0 | M20: =N20 | N20: =G20 | O20: =H20 | T20: =I20 | U20: =J20 -> 0 | V20: {=IF($C20=0,0,INDEX($X$2:$BC$2,1,$B20+1))} -> 0 | W20: {=IF($C20=0,0,INDEX($X20:$BC20,1,$B20+1))} -> 0 | X20: =W20*U20 -> 0 | Z20: =Y20*$U20 -> 0 | AC20: =AB20*$U20 -> 0 | AF20: =AE20*$U20 -> 0 | AI20: =AH20*$U20 -> 0 | AL20: =AK20*$U20 -> 0 | AO20: =AN20*$U20 -> 0 | AR20: =AQ20*$U20 -> 0 | AU20: =AT20*$U20 -> 0 | AX20: =AW20*$U20 -> 0 | BA20: =AZ20*$U20 -> 0
B21: =IF(C21=0,"",MATCH(_xlfn.MINIFS(Y21:BC21,Y$9:BC$9,$Y$9,Y21:BC21,"<>0",Y21:BC21,"<>"""),Y21:BC21,)) | C21: =IF(AND(N21<>"",N21<>0),MAX($C$8:$C20)+1,0) -> 0 | D21: =IF($F21>$E$3,"",_xlfn.MAXIFS(OFFSET(Orçamento!$G$5,$E21-5,,$E$4-$E21+5,),OFFSET(Orçamento!$N$5,$E21-5,,$E$4-$E21+5,),$G21)+1-E21+5) | E21: =IF($F21>$E$3,"",_xlfn.IFNA(MATCH($G21,Orçamento!$N:$N,),"")) | F21: {=OFFSET(F21,-1,,,)+1} -> 12 | G21: =IF($F21>$E$3,"",INDEX(Insumos!$C:$C,MATCH($F21,Insumos!$B:$B,),1)) | H21: {=IF($E21="","",INDEX(Orçamento!$O:$O,$E21,1))} | I21: {=IF($E21="","",INDEX(Orçamento!$Q:$Q,$E21,1))} | J21: =IF($D21="",0,SUMIF(OFFSET(Orçamento!$N$5,$E21-5,,$D21,),$G21,OFFSET(Orçamento!$I$5,$E21-5,,$D21,))) -> 0 | K21: {=IF($E21="",0,INDEX(Orçamento!$S:$S,$E21,1))} -> 0 | L21: =J21*K21 -> 0 | M21: =N21 | N21: =G21 | O21: =H21 | T21: =I21 | U21: =J21 -> 0 | V21: {=IF($C21=0,0,INDEX($X$2:$BC$2,1,$B21+1))} -> 0 | W21: {=IF($C21=0,0,INDEX($X21:$BC21,1,$B21+1))} -> 0 | X21: =W21*U21 -> 0 | Z21: =Y21*$U21 -> 0 | AC21: =AB21*$U21 -> 0 | AF21: =AE21*$U21 -> 0 | AI21: =AH21*$U21 -> 0 | AL21: =AK21*$U21 -> 0 | AO21: =AN21*$U21 -> 0 | AR21: =AQ21*$U21 -> 0 | AU21: =AT21*$U21 -> 0 | AX21: =AW21*$U21 -> 0 | BA21: =AZ21*$U21 -> 0
B22: =IF(C22=0,"",MATCH(_xlfn.MINIFS(Y22:BC22,Y$9:BC$9,$Y$9,Y22:BC22,"<>0",Y22:BC22,"<>"""),Y22:BC22,)) | C22: =IF(AND(N22<>"",N22<>0),MAX($C$8:$C21)+1,0) -> 0 | D22: =IF($F22>$E$3,"",_xlfn.MAXIFS(OFFSET(Orçamento!$G$5,$E22-5,,$E$4-$E22+5,),OFFSET(Orçamento!$N$5,$E22-5,,$E$4-$E22+5,),$G22)+1-E22+5) | E22: =IF($F22>$E$3,"",_xlfn.IFNA(MATCH($G22,Orçamento!$N:$N,),"")) | F22: {=OFFSET(F22,-1,,,)+1} -> 13 | G22: =IF($F22>$E$3,"",INDEX(Insumos!$C:$C,MATCH($F22,Insumos!$B:$B,),1)) | H22: {=IF($E22="","",INDEX(Orçamento!$O:$O,$E22,1))} | I22: {=IF($E22="","",INDEX(Orçamento!$Q:$Q,$E22,1))} | J22: =IF($D22="",0,SUMIF(OFFSET(Orçamento!$N$5,$E22-5,,$D22,),$G22,OFFSET(Orçamento!$I$5,$E22-5,,$D22,))) -> 0 | K22: {=IF($E22="",0,INDEX(Orçamento!$S:$S,$E22,1))} -> 0 | L22: =J22*K22 -> 0 | M22: =N22 | N22: =G22 | O22: =H22 | T22: =I22 | U22: =J22 -> 0 | V22: {=IF($C22=0,0,INDEX($X$2:$BC$2,1,$B22+1))} -> 0 | W22: {=IF($C22=0,0,INDEX($X22:$BC22,1,$B22+1))} -> 0 | X22: =W22*U22 -> 0 | Z22: =Y22*$U22 -> 0 | AC22: =AB22*$U22 -> 0 | AF22: =AE22*$U22 -> 0 | AI22: =AH22*$U22 -> 0 | AL22: =AK22*$U22 -> 0 | AO22: =AN22*$U22 -> 0 | AR22: =AQ22*$U22 -> 0 | AU22: =AT22*$U22 -> 0 | AX22: =AW22*$U22 -> 0 | BA22: =AZ22*$U22 -> 0
... B119: =IF(C119=0,"",MATCH(_xlfn.MINIFS(Y119:BC119,Y$9:BC$9,$Y$9,Y119:BC119,"<>0",Y119:BC119,"<>"""),Y119:BC119,)) | C119: =IF(AND(N119<>"",N119<>0),MAX($C$8:$C118)+1,0) -> 0 | D119: =IF($F119>$E$3,"",_xlfn.MAXIFS(OFFSET(Orçamento!$G$5,$E119-5,,$E$4-$E119+5,),OFFSET(Orçamento!$N$5,$E119-5,,$E$4-$E119+5,),$G119)+1-E119+5) | E119: =IF($F119>$E$3,"",_xlfn.IFNA(MATCH($G119,Orçamento!$N:$N,),"")) | F119: {=OFFSET(F119,-1,,,)+1} -> 110 | G119: =IF($F119>$E$3,"",INDEX(Insumos!$C:$C,MATCH($F119,Insumos!$B:$B,),1)) | H119: {=IF($E119="","",INDEX(Orçamento!$O:$O,$E119,1))} | I119: {=IF($E119="","",INDEX(Orçamento!$Q:$Q,$E119,1))} | J119: =IF($D119="",0,SUMIF(OFFSET(Orçamento!$N$5,$E119-5,,$D119,),$G119,OFFSET(Orçamento!$I$5,$E119-5,,$D119,))) -> 0 | K119: {=IF($E119="",0,INDEX(Orçamento!$S:$S,$E119,1))} -> 0 | L119: =J119*K119 -> 0 | M119: =N119 | N119: =G119 | O119: =H119 | T119: =I119 | U119: =J119 -> 0 | V119: {=IF($C119=0,0,INDEX($X$2:$BC$2,1,$B119+1))} -> 0 | W119: {=IF($C119=0,0,INDEX($X119:$BC119,1,$B119+1))} -> 0 | X119: =W119*U119 -> 0 | Z119: =Y119*$U119 -> 0 | AC119: =AB119*$U119 -> 0 | AF119: =AE119*$U119 -> 0 | AI119: =AH119*$U119 -> 0 | AL119: =AK119*$U119 -> 0 | AO119: =AN119*$U119 -> 0 | AR119: =AQ119*$U119 -> 0 | AU119: =AT119*$U119 -> 0 | AX119: =AW119*$U119 -> 0 | BA119: =AZ119*$U119 -> 0
M120: Total Orçado: | P120: =SUM(L10:L119) -> 0 | T120: R$ Total Equalizado rev00 | X120: =SUM(X10:X119) -> 0 | Z120: =SUM(Z10:Z119) -> 0 | AC120: =SUM(AC10:AC119) -> 0 | AF120: =SUM(AF10:AF119) -> 0 | AI120: =SUM(AI10:AI119) -> 0 | AL120: =SUM(AL10:AL119) -> 0 | AO120: =SUM(AO10:AO119) -> 0 | AR120: =SUM(AR10:AR119) -> 0 | AU120: =SUM(AU10:AU119) -> 0 | AX120: =SUM(AX10:AX119) -> 0 | BA120: =SUM(BA10:BA119) -> 0
F121: OBSERVAÇÕES DA ENGENHARIA / GERAL | M121: Verba Já Utilizada: | T121: R$ Total Equalizado rev01
M122: Acréscimos/Reduções: | T122: R$ Total Equalizado rev02
M123: Verba Disponível: | P123: =SUM(P120:P122) -> 0 | T123: Resultado QC / Orçamento | X123: =$P$123-X120 -> 0 | Y123: =IFERROR(Z123/$P$120,0) -> 0 | Z123: =$P$123-Z120 -> 0 | AB123: =IFERROR(AC123/$P$120,0) -> 0 | AC123: =$P$123-AC120 -> 0 | AE123: =IFERROR(AF123/$P$120,0) -> 0 | AF123: =$P$123-AF120 -> 0 | AH123: =IFERROR(AI123/$P$120,0) -> 0 | AI123: =$P$123-AI120 -> 0 | AK123: =IFERROR(AL123/$P$120,0) -> 0 | AL123: =$P$123-AL120 -> 0 | AN123: =IFERROR(AO123/$P$120,0) -> 0 | AO123: =$P$123-AO120 -> 0 | AQ123: =IFERROR(AR123/$P$120,0) -> 0 | AR123: =$P$123-AR120 -> 0 | AT123: =IFERROR(AU123/$P$120,0) -> 0 | AU123: =$P$123-AU120 -> 0 | AW123: =IFERROR(AX123/$P$120,0) -> 0 | AX123: =$P$123-AX120 -> 0 | AZ123: =IFERROR(BA123/$P$120,0) -> 0 | BA123: =$P$123-BA120 -> 0
N124: OBSERVAÇÕES SUPRIMENTOS | U124: Prazo de execução /Entrega
U127: Condição Pagamento
U130: Forma de Reajuste
U133: Observações
F139: Tipo de Contrato | U139: Pontos Positivos
F141: Empresa Vencendora | I141: 0
F142: Justificativa
U143: Pontos Negativos
F144: Aprovações
H146: ... | L146: GERENTE / COORDENADOR DE OBRA

Sheet Solic. Contrato
D2: =MAX(Orçamento!C:C) -> 0 | E2: ='QC rev00'!$D$3 -> 0 | F2: =Listas!$K$2 -> #REF! | I2: FORMULÁRIO DE SOLICITAÇÃO PARA GERAR CONTRATO DE SERVIÇOS E LOCAÇÃO DE EQUIPAMENTOS COM OPERAÇÃO | R2: REVISÃO: | T2: 1
D3: =MAX($D$22:$D$353)+10 -> 10 | E3: =Orçamento!J2+5 -> 4538 | F3: =Listas!$L$2 -> #REF! | R3: DATA: | T3: =IF($F$2=1,'QC rev00'!$O$2,IF($F$2=2,#REF!,#REF!)) -> #REF!
E5: =IFERROR(SEARCH("Com Fat Direto",I16,1),"X") -> X | F5: =F6*IF(E5="X",1,$K$17+$N$17) -> #REF! | G5: 1. INFORMAÇÕES GERAIS
E6: IM07922 | F6: {=_xlfn.IFNA(IF($F$2=1,OFFSET('QC rev00'!$U$120,,$F$3+1,,),IF($F$2=2,OFFSET(#REF!,,$F$3+1,,),OFFSET(#REF!,,$F$3+1,,))),0)} -> #REF! | G6: 1.1 DADOS INICIAIS
G7: OBRA: | H7: ='QC rev00'!$P$4 -> 0 | J7: ="Nº da Obra: "&'QC rev00'!$T$4 -> Nº da Obra: | K7: Nº da Solicitação de Cotação: | O7: SOLICITANTE: | P7: ='QC rev00'!$P$5 -> 0 | R7: VERBA ORÇAMENTÁRIA: | T7: =IF($F$2=1,'QC rev00'!$P$120,IF($F$2=2,#REF!,#REF!)) -> #REF!
G8: 1.2 OBJETO DO CONTRATO: | I8: ='QC rev00'!H2 -> 0
G9: 1.3 DADOS DO CONTRATADO
G10: Razão Social: | H10: {=IF($F$2=1,OFFSET('QC rev00'!$U$2,,$F$3,,),IF($F$2=2,OFFSET(#REF!,,$F$3,,),OFFSET(#REF!,,$F$3,,)))} -> #REF!
G11: CNPJ: | H11: {=IF($F$2=1,OFFSET('QC rev00'!$U$7,,$F$3,,),IF($F$2=2,OFFSET(#REF!,,$F$3,,),OFFSET(#REF!,,$F$3,,)))} -> #REF! | J11: TEL/CEL: | K11: {=IF($F$2=1,OFFSET('QC rev00'!$U$5,,$F$3,,),IF($F$2=2,OFFSET(#REF!,,$F$3,,),OFFSET(#REF!,,$F$3,,)))} -> #REF! | N11: E-MAIL: | O11: {=IF($F$2=1,OFFSET('QC rev00'!$U$6,,$F$3,,),IF($F$2=2,OFFSET(#REF!,,$F$3,,),OFFSET(#REF!,,$F$3,,)))} -> #REF! | R11: CONTATO: | S11: {=IF($F$2=1,OFFSET('QC rev00'!$U$4,,$F$3,,),IF($F$2=2,OFFSET(#REF!,,$F$3,,),OFFSET(#REF!,,$F$3,,)))} -> #REF!
G12: 1.4 DADOS DO 2º CONTRATADO (caso tenha faturamento por medição para mais de uma empresa)
G13: Razão Social:
G14: CNPJ: | J14: TEL/CEL: | N14: E-MAIL: | R14: CONTATO:
G16: 1.5 TIPO DE CONTRATO | I16: =IF($F$2=1,'QC rev00'!$I$139,IF($F$2=2,#REF!,#REF!)) -> #REF!
G17: 1.6 DISTRIBUIÇÃO E RETENÇÃO | I17: % DE DISTRIBUIÇÃO DO CONTRATO | J17: Material | K17: =IF($F$2=1,SUMPRODUCT(OFFSET('QC rev00'!$M$10:$M$119,$F25-1,9+$F$3,,),'QC rev00'!$Q$10:$Q$119),IF($F$2=2,SUMPRODUCT(OFFSET(#REF!,$F25-1,9+$F$3,,),#REF!),SUMPRODUCT(OFFSET(#REF!,$F25-1,9+$F$3,,),#REF!)))/$F$6 -> #REF! | L17: Equipamento | N17: =IF($F$2=1,SUMPRODUCT(OFFSET('QC rev00'!$M$10:$M$119,$F25-1,9+$F$3,,),'QC rev00'!$R$10:$R$119),IF($F$2=2,SUMPRODUCT(OFFSET(#REF!,$F25-1,9+$F$3,,),#REF!),SUMPRODUCT(OFFSET(#REF!,$F25-1,9+$F$3,,),#REF!)))/$F$6 -> #REF! | O17: MDO / Serviço | P17: =1-K17-N17 -> #REF!
G18: 1.7 VALIDADE DO CONTRATO | I18: DATA DE INÍCIO DO CONTRATO: | J18: =IF($F$2=1,'QC rev00'!$T$2,IF($F$2=2,#REF!,#REF!)) -> #REF! | K18: DATA DE TÉRMINO: | N18: =IF($F$2=1,'QC rev00'!$T$3,IF($F$2=2,#REF!,#REF!)) -> #REF! | P18: =IF(COUNTIF($C$23:$C$353,"X")>0,"VÍNCULOS NÃO INDICADOS / ERRO NA QUANTIDADE VINCULADA","")
G20: 2. ESPECIFICAÇÃO DOS SERVIÇOS CONTRATADO:
G21: COD. DO INSUMO | H21: DESCRIÇÃO | J21: Especificação | L21: % Retenção | M21: UNID. | N21: QUANT. | O21: R$ UNITÁRIO | P21: R$ TOTAL | Q21: Vínculos | R21: 1 | S21: =R21+1 -> 2 | T21: =S21+1 -> 3 | U21: =T21+1 -> 4 | V21: =U21+1 -> 5 | W21: =V21+1 -> 6 | X21: =W21+1 -> 7 | Y21: =X21+1 -> 8 | Z21: =Y21+1 -> 9 | ... AK21: =AJ21+1 -> 20
B23: =IF($F23>$E$2,0,IF(E23<>"",MATCH(F24&" - Mapa",Orçamento!J:J,),0)) -> 0 | C23: =IF($D23>1,_xlfn.MAXIFS(Orçamento!G:G,Orçamento!J:J,F24&" - Mapa")+6-B23,0) -> 0 | D23: =IF($F23>$E$2,0,IF($G23=$E$6,$D$2,IF(E23<>"",_xlfn.MAXIFS(Orçamento!E:E,Orçamento!J:J,F24&" - Mapa"),0))) -> 0 | E23: =IF(F24="","",_xlfn.IFNA(MATCH($F24,'QC rev00'!$G$10:$G$120,),"")) | F23: {=OFFSET(F23,-3,,,)+1} -> 1 | G23: {=IF($F23>$E$2,"",IF($F$2=1,INDEX('QC rev00'!$M$10:$T$120,$F25,2),IF($F$2=2,INDEX(#REF!,$F25,2),INDEX(#REF!,$F25,2))))} | H23: {=IF($F23>$E$2,"",IF($F$2=1,INDEX('QC rev00'!$M$10:$T$120,$F25,3),IF($F$2=2,INDEX(#REF!,$F25,3),INDEX(#REF!,$F25,3))))} | L23: {=IF($F23>$E$2,"",IF($F$2=1,INDEX('QC rev00'!$M$10:$T$120,$F25,7),IF($F$2=2,INDEX(#REF!,$F25,7),INDEX(#REF!,$F25,7))))} | M23: {=IF($F23>$E$2,"",IF($F$2=1,INDEX('QC rev00'!$M$10:$T$120,$F25,8),IF($F$2=2,INDEX(#REF!,$F25,8),INDEX(#REF!,$F25,8))))} | N23: {=IF($F23>$E$2,0,IF(_xlfn.IFNA(MATCH($G23,Listas!$E$4:$E$206,),0)>0,$F$5,IF($F$2=1,INDEX('QC rev00'!$M$10:$U$120,$F25,9),IF($F$2=2,INDEX(#REF!,$F25,9),INDEX(#REF!,$F25,9)))))} -> 0 | O23: {=IF($F23>$E$2,0,IF(_xlfn.IFNA(MATCH($G23,Listas!$E$4:$E$206,),0)>0,1,IF($H$10=0,0,IF($F$2=1,INDEX('QC rev00'!$M$10:$BC$120,$F25,9+$F$3),IF($F$2=2,INDEX(#REF!,$F25,9+$F$3),INDEX(#REF!,$F25,9+$F$3)))*IF($E$5="X",1,1-$B25-$C25))))} -> 0 | P23: =N23*O23 -> 0 | Q23: IP | R23: {=IF($D23=0,"",IF($G23=$E$6,INDEX(Orçamento!$U:$U,MATCH(R$21,Orçamento!$C:$C,),1),INDEX(Orçamento!$U:$U,$B23,1)))} | S23: =IF(S$21>$D23,"",IF($G23=$E$6,INDEX(Orçamento!$U:$U,MATCH(S$21,Orçamento!$C:$C,),1),INDEX(Orçamento!$U:$U,MATCH(S$21&"-"&$F24,Orçamento!$F:$F,),1))) | T23: =IF(T$21>$D23,"",IF($G23=$E$6,INDEX(Orçamento!$U:$U,MATCH(T$21,Orçamento!$C:$C,),1),INDEX(Orçamento!$U:$U,MATCH(T$21&"-"&$F24,Orçamento!$F:$F,),1))) | U23: =IF(U$21>$D23,"",IF($G23=$E$6,INDEX(Orçamento!$U:$U,MATCH(U$21,Orçamento!$C:$C,),1),INDEX(Orçamento!$U:$U,MATCH(U$21&"-"&$F24,Orçamento!$F:$F,),1))) | V23: =IF(V$21>$D23,"",IF($G23=$E$6,INDEX(Orçamento!$U:$U,MATCH(V$21,Orçamento!$C:$C,),1),INDEX(Orçamento!$U:$U,MATCH(V$21&"-"&$F24,Orçamento!$F:$F,),1))) | W23: =IF(W$21>$D23,"",IF($G23=$E$6,INDEX(Orçamento!$U:$U,MATCH(W$21,Orçamento!$C:$C,),1),INDEX(Orçamento!$U:$U,MATCH(W$21&"-"&$F24,Orçamento!$F:$F,),1))) | X23: =IF(X$21>$D23,"",IF($G23=$E$6,INDEX(Orçamento!$U:$U,MATCH(X$21,Orçamento!$C:$C,),1),INDEX(Orçamento!$U:$U,MATCH(X$21&"-"&$F24,Orçamento!$F:$F,),1))) | Y23: =IF(Y$21>$D23,"",IF($G23=$E$6,INDEX(Orçamento!$U:$U,MATCH(Y$21,Orçamento!$C:$C,),1),INDEX(Orçamento!$U:$U,MATCH(Y$21&"-"&$F24,Orçamento!$F:$F,),1))) | Z23: =IF(Z$21>$D23,"",IF($G23=$E$6,INDEX(Orçamento!$U:$U,MATCH(Z$21,Orçamento!$C:$C,),1),INDEX(Orçamento!$U:$U,MATCH(Z$21&"-"&$F24,Orçamento!$F:$F,),1))) | ... AK23: =IF(AK$21>$D23,"",IF($G23=$E$6,INDEX(Orçamento!$U:$U,MATCH(AK$21,Orçamento!$C:$C,),1),INDEX(Orçamento!$U:$U,MATCH(AK$21&"-"&$F24,Orçamento!$F:$F,),1)))
B24: =IF($F23>$E$2,0,(1/(1-B25-C25))*(B25+C25)) -> 0 | C24: {=IF(ROUND(SUM(IF(R23:AK23<>"",(R24:AK24)))-N23,3)<>0,"X",0)} -> 0 | E24: {=IF($F23>$E$2,"",INDEX('QC rev00'!$J$9:$J$120,1+E23,1))} | F24: {=IF($F23>$E$2,"",IF($F$2=1,INDEX('QC rev00'!$M$10:$T$120,$F25,1),IF($F$2=2,INDEX(#REF!,$F25,1),INDEX(#REF!,$F25,1))))} | Q24: Qtd | R24: {=IF(OR($D23=0,R23="",$N23=0),"", IF($G23=$E$6, SUM(IF(OFFSET($R$23,,,($F23-1)*3-2,$D$3)=R23,OFFSET($R$25,,,($F23-1)*3-2,$D$3)*OFFSET($B$23,1,,($F23-1)*3-2,1))), IF($D23=1,$N23, SUMIF(OFFSET(Orçamento!$D$1,$B23-1,,$C23,),$F24&"-"&R23,OFFSET(Orçamento!$I$1,$B23-1,,$C23,))*$N23/$E24)))} | S24: {=IF(OR($D23=0,S23="",$N23=0),"", IF($G23=$E$6, SUM(IF(OFFSET($R$23,,,($F23-1)*3-2,$D$3)=S23,OFFSET($R$25,,,($F23-1)*3-2,$D$3)*OFFSET($B$23,1,,($F23-1)*3-2,1))), IF($D23=1,$N23, SUMIF(OFFSET(Orçamento!$D$1,$B23-1,,$C23,),$F24&"-"&S23,OFFSET(Orçamento!$I$1,$B23-1,,$C23,))*$N23/$E24)))} | T24: {=IF(OR($D23=0,T23="",$N23=0),"", IF($G23=$E$6, SUM(IF(OFFSET($R$23,,,($F23-1)*3-2,$D$3)=T23,OFFSET($R$25,,,($F23-1)*3-2,$D$3)*OFFSET($B$23,1,,($F23-1)*3-2,1))), IF($D23=1,$N23, SUMIF(OFFSET(Orçamento!$D$1,$B23-1,,$C23,),$F24&"-"&T23,OFFSET(Orçamento!$I$1,$B23-1,,$C23,))*$N23/$E24)))} | U24: {=IF(OR($D23=0,U23="",$N23=0),"", IF($G23=$E$6, SUM(IF(OFFSET($R$23,,,($F23-1)*3-2,$D$3)=U23,OFFSET($R$25,,,($F23-1)*3-2,$D$3)*OFFSET($B$23,1,,($F23-1)*3-2,1))), IF($D23=1,$N23, SUMIF(OFFSET(Orçamento!$D$1,$B23-1,,$C23,),$F24&"-"&U23,OFFSET(Orçamento!$I$1,$B23-1,,$C23,))*$N23/$E24)))} | V24: {=IF(OR($D23=0,V23="",$N23=0),"", IF($G23=$E$6, SUM(IF(OFFSET($R$23,,,($F23-1)*3-2,$D$3)=V23,OFFSET($R$25,,,($F23-1)*3-2,$D$3)*OFFSET($B$23,1,,($F23-1)*3-2,1))), IF($D23=1,$N23, SUMIF(OFFSET(Orçamento!$D$1,$B23-1,,$C23,),$F24&"-"&V23,OFFSET(Orçamento!$I$1,$B23-1,,$C23,))*$N23/$E24)))} | W24: {=IF(OR($D23=0,W23="",$N23=0),"", IF($G23=$E$6, SUM(IF(OFFSET($R$23,,,($F23-1)*3-2,$D$3)=W23,OFFSET($R$25,,,($F23-1)*3-2,$D$3)*OFFSET($B$23,1,,($F23-1)*3-2,1))), IF($D23=1,$N23, SUMIF(OFFSET(Orçamento!$D$1,$B23-1,,$C23,),$F24&"-"&W23,OFFSET(Orçamento!$I$1,$B23-1,,$C23,))*$N23/$E24)))} | X24: {=IF(OR($D23=0,X23="",$N23=0),"", IF($G23=$E$6, SUM(IF(OFFSET($R$23,,,($F23-1)*3-2,$D$3)=X23,OFFSET($R$25,,,($F23-1)*3-2,$D$3)*OFFSET($B$23,1,,($F23-1)*3-2,1))), IF($D23=1,$N23, SUMIF(OFFSET(Orçamento!$D$1,$B23-1,,$C23,),$F24&"-"&X23,OFFSET(Orçamento!$I$1,$B23-1,,$C23,))*$N23/$E24)))} | Y24: {=IF(OR($D23=0,Y23="",$N23=0),"", IF($G23=$E$6, SUM(IF(OFFSET($R$23,,,($F23-1)*3-2,$D$3)=Y23,OFFSET($R$25,,,($F23-1)*3-2,$D$3)*OFFSET($B$23,1,,($F23-1)*3-2,1))), IF($D23=1,$N23, SUMIF(OFFSET(Orçamento!$D$1,$B23-1,,$C23,),$F24&"-"&Y23,OFFSET(Orçamento!$I$1,$B23-1,,$C23,))*$N23/$E24)))} | ... AK24: {=IF(OR($D23=0,AK23="",$N23=0),"", IF($G23=$E$6, SUM(IF(OFFSET($R$23,,,($F23-1)*3-2,$D$3)=AK23,OFFSET($R$25,,,($F23-1)*3-2,$D$3)*OFFSET($B$23,1,,($F23-1)*3-2,1))), IF($D23=1,$N23, SUMIF(OFFSET(Orçamento!$D$1,$B23-1,,$C23,),$F24&"-"&AK23,OFFSET(Orçamento!$I$1,$B23-1,,$C23,))*$N23/$E24)))}
B25: {=IF($F23>$E$2,"",IF($F$2=1,INDEX('QC rev00'!$M$10:$T$120,$F25,5),IF($F$2=2,INDEX(#REF!,$F25,5),INDEX(#REF!,$F25,5))))} | C25: {=IF($F23>$E$2,"",IF($F$2=1,INDEX('QC rev00'!$M$10:$T$120,$F25,6),IF($F$2=2,INDEX(#REF!,$F25,6),INDEX(#REF!,$F25,6))))} | F25: =IF(F23>$E$2,"",MATCH(F23,'QC rev00'!$C$10:$C$120,)) | Q25: Valor | R25: =IFERROR(R24*$O23,0) -> 0 | S25: =IFERROR(S24*$O23,0) -> 0 | T25: =IFERROR(T24*$O23,0) -> 0 | U25: =IFERROR(U24*$O23,0) -> 0 | V25: =IFERROR(V24*$O23,0) -> 0 | W25: =IFERROR(W24*$O23,0) -> 0 | X25: =IFERROR(X24*$O23,0) -> 0 | Y25: =IFERROR(Y24*$O23,0) -> 0 | ... AK25: =IFERROR(AK24*$O23,0) -> 0
B26: =IF($F26>$E$2,0,IF(E26<>"",MATCH(F27&" - Mapa",Orçamento!J:J,),0)) -> 0 | C26: =IF($D26>1,_xlfn.MAXIFS(Orçamento!G:G,Orçamento!J:J,F27&" - Mapa")+6-B26,0) -> 0 | D26: =IF($F26>$E$2,0,IF($G26=$E$6,$D$2,IF(E26<>"",_xlfn.MAXIFS(Orçamento!E:E,Orçamento!J:J,F27&" - Mapa"),0))) -> 0 | E26: =IF(F27="","",_xlfn.IFNA(MATCH($F27,'QC rev00'!$G$10:$G$120,),"")) | F26: {=OFFSET(F26,-3,,,)+1} -> 2 | G26: {=IF($F26>$E$2,"",IF($F$2=1,INDEX('QC rev00'!$M$10:$T$120,$F28,2),IF($F$2=2,INDEX(#REF!,$F28,2),INDEX(#REF!,$F28,2))))} | H26: {=IF($F26>$E$2,"",IF($F$2=1,INDEX('QC rev00'!$M$10:$T$120,$F28,3),IF($F$2=2,INDEX(#REF!,$F28,3),INDEX(#REF!,$F28,3))))} | L26: {=IF($F26>$E$2,"",IF($F$2=1,INDEX('QC rev00'!$M$10:$T$120,$F28,7),IF($F$2=2,INDEX(#REF!,$F28,7),INDEX(#REF!,$F28,7))))} | M26: {=IF($F26>$E$2,"",IF($F$2=1,INDEX('QC rev00'!$M$10:$T$120,$F28,8),IF($F$2=2,INDEX(#REF!,$F28,8),INDEX(#REF!,$F28,8))))} | N26: {=IF($F26>$E$2,0,IF(_xlfn.IFNA(MATCH($G26,Listas!$E$4:$E$206,),0)>0,$F$5,IF($F$2=1,INDEX('QC rev00'!$M$10:$U$120,$F28,9),IF($F$2=2,INDEX(#REF!,$F28,9),INDEX(#REF!,$F28,9)))))} -> 0 | O26: {=IF($F26>$E$2,0,IF(_xlfn.IFNA(MATCH($G26,Listas!$E$4:$E$206,),0)>0,1,IF($H$10=0,0,IF($F$2=1,INDEX('QC rev00'!$M$10:$BC$120,$F28,9+$F$3),IF($F$2=2,INDEX(#REF!,$F28,9+$F$3),INDEX(#REF!,$F28,9+$F$3)))*IF($E$5="X",1,1-$B28-$C28))))} -> 0 | P26: =N26*O26 -> 0 | Q26: IP | R26: {=IF($D26=0,"",IF($G26=$E$6,INDEX(Orçamento!$U:$U,MATCH(R$21,Orçamento!$C:$C,),1),INDEX(Orçamento!$U:$U,$B26,1)))} | S26: =IF(S$21>$D26,"",IF($G26=$E$6,INDEX(Orçamento!$U:$U,MATCH(S$21,Orçamento!$C:$C,),1),INDEX(Orçamento!$U:$U,MATCH(S$21&"-"&$F27,Orçamento!$F:$F,),1))) | T26: =IF(T$21>$D26,"",IF($G26=$E$6,INDEX(Orçamento!$U:$U,MATCH(T$21,Orçamento!$C:$C,),1),INDEX(Orçamento!$U:$U,MATCH(T$21&"-"&$F27,Orçamento!$F:$F,),1))) | U26: =IF(U$21>$D26,"",IF($G26=$E$6,INDEX(Orçamento!$U:$U,MATCH(U$21,Orçamento!$C:$C,),1),INDEX(Orçamento!$U:$U,MATCH(U$21&"-"&$F27,Orçamento!$F:$F,),1))) | V26: =IF(V$21>$D26,"",IF($G26=$E$6,INDEX(Orçamento!$U:$U,MATCH(V$21,Orçamento!$C:$C,),1),INDEX(Orçamento!$U:$U,MATCH(V$21&"-"&$F27,Orçamento!$F:$F,),1))) | W26: =IF(W$21>$D26,"",IF($G26=$E$6,INDEX(Orçamento!$U:$U,MATCH(W$21,Orçamento!$C:$C,),1),INDEX(Orçamento!$U:$U,MATCH(W$21&"-"&$F27,Orçamento!$F:$F,),1))) | X26: =IF(X$21>$D26,"",IF($G26=$E$6,INDEX(Orçamento!$U:$U,MATCH(X$21,Orçamento!$C:$C,),1),INDEX(Orçamento!$U:$U,MATCH(X$21&"-"&$F27,Orçamento!$F:$F,),1))) | Y26: =IF(Y$21>$D26,"",IF($G26=$E$6,INDEX(Orçamento!$U:$U,MATCH(Y$21,Orçamento!$C:$C,),1),INDEX(Orçamento!$U:$U,MATCH(Y$21&"-"&$F27,Orçamento!$F:$F,),1))) | Z26: =IF(Z$21>$D26,"",IF($G26=$E$6,INDEX(Orçamento!$U:$U,MATCH(Z$21,Orçamento!$C:$C,),1),INDEX(Orçamento!$U:$U,MATCH(Z$21&"-"&$F27,Orçamento!$F:$F,),1))) | ... AK26: =IF(AK$21>$D26,"",IF($G26=$E$6,INDEX(Orçamento!$U:$U,MATCH(AK$21,Orçamento!$C:$C,),1),INDEX(Orçamento!$U:$U,MATCH(AK$21&"-"&$F27,Orçamento!$F:$F,),1)))
B27: =IF($F26>$E$2,0,(1/(1-B28-C28))*(B28+C28)) -> 0 | C27: {=IF(ROUND(SUM(IF(R26:AK26<>"",(R27:AK27)))-N26,3)<>0,"X",0)} -> 0 | E27: {=IF($F26>$E$2,"",INDEX('QC rev00'!$J$9:$J$120,1+E26,1))} | F27: {=IF($F26>$E$2,"",IF($F$2=1,INDEX('QC rev00'!$M$10:$T$120,$F28,1),IF($F$2=2,INDEX(#REF!,$F28,1),INDEX(#REF!,$F28,1))))} | Q27: Qtd | R27: {=IF(OR($D26=0,R26="",$N26=0),"", IF($G26=$E$6, SUM(IF(OFFSET($R$23,,,($F26-1)*3-2,$D$3)=R26,OFFSET($R$25,,,($F26-1)*3-2,$D$3)*OFFSET($B$23,1,,($F26-1)*3-2,1))), IF($D26=1,$N26, SUMIF(OFFSET(Orçamento!$D$1,$B26-1,,$C26,),$F27&"-"&R26,OFFSET(Orçamento!$I$1,$B26-1,,$C26,))*$N26/$E27)))} | S27: {=IF(OR($D26=0,S26="",$N26=0),"", IF($G26=$E$6, SUM(IF(OFFSET($R$23,,,($F26-1)*3-2,$D$3)=S26,OFFSET($R$25,,,($F26-1)*3-2,$D$3)*OFFSET($B$23,1,,($F26-1)*3-2,1))), IF($D26=1,$N26, SUMIF(OFFSET(Orçamento!$D$1,$B26-1,,$C26,),$F27&"-"&S26,OFFSET(Orçamento!$I$1,$B26-1,,$C26,))*$N26/$E27)))} | T27: {=IF(OR($D26=0,T26="",$N26=0),"", IF($G26=$E$6, SUM(IF(OFFSET($R$23,,,($F26-1)*3-2,$D$3)=T26,OFFSET($R$25,,,($F26-1)*3-2,$D$3)*OFFSET($B$23,1,,($F26-1)*3-2,1))), IF($D26=1,$N26, SUMIF(OFFSET(Orçamento!$D$1,$B26-1,,$C26,),$F27&"-"&T26,OFFSET(Orçamento!$I$1,$B26-1,,$C26,))*$N26/$E27)))} | U27: {=IF(OR($D26=0,U26="",$N26=0),"", IF($G26=$E$6, SUM(IF(OFFSET($R$23,,,($F26-1)*3-2,$D$3)=U26,OFFSET($R$25,,,($F26-1)*3-2,$D$3)*OFFSET($B$23,1,,($F26-1)*3-2,1))), IF($D26=1,$N26, SUMIF(OFFSET(Orçamento!$D$1,$B26-1,,$C26,),$F27&"-"&U26,OFFSET(Orçamento!$I$1,$B26-1,,$C26,))*$N26/$E27)))} | V27: {=IF(OR($D26=0,V26="",$N26=0),"", IF($G26=$E$6, SUM(IF(OFFSET($R$23,,,($F26-1)*3-2,$D$3)=V26,OFFSET($R$25,,,($F26-1)*3-2,$D$3)*OFFSET($B$23,1,,($F26-1)*3-2,1))), IF($D26=1,$N26, SUMIF(OFFSET(Orçamento!$D$1,$B26-1,,$C26,),$F27&"-"&V26,OFFSET(Orçamento!$I$1,$B26-1,,$C26,))*$N26/$E27)))} | W27: {=IF(OR($D26=0,W26="",$N26=0),"", IF($G26=$E$6, SUM(IF(OFFSET($R$23,,,($F26-1)*3-2,$D$3)=W26,OFFSET($R$25,,,($F26-1)*3-2,$D$3)*OFFSET($B$23,1,,($F26-1)*3-2,1))), IF($D26=1,$N26, SUMIF(OFFSET(Orçamento!$D$1,$B26-1,,$C26,),$F27&"-"&W26,OFFSET(Orçamento!$I$1,$B26-1,,$C26,))*$N26/$E27)))} | X27: {=IF(OR($D26=0,X26="",$N26=0),"", IF($G26=$E$6, SUM(IF(OFFSET($R$23,,,($F26-1)*3-2,$D$3)=X26,OFFSET($R$25,,,($F26-1)*3-2,$D$3)*OFFSET($B$23,1,,($F26-1)*3-2,1))), IF($D26=1,$N26, SUMIF(OFFSET(Orçamento!$D$1,$B26-1,,$C26,),$F27&"-"&X26,OFFSET(Orçamento!$I$1,$B26-1,,$C26,))*$N26/$E27)))} | Y27: {=IF(OR($D26=0,Y26="",$N26=0),"", IF($G26=$E$6, SUM(IF(OFFSET($R$23,,,($F26-1)*3-2,$D$3)=Y26,OFFSET($R$25,,,($F26-1)*3-2,$D$3)*OFFSET($B$23,1,,($F26-1)*3-2,1))), IF($D26=1,$N26, SUMIF(OFFSET(Orçamento!$D$1,$B26-1,,$C26,),$F27&"-"&Y26,OFFSET(Orçamento!$I$1,$B26-1,,$C26,))*$N26/$E27)))} | ... AK27: {=IF(OR($D26=0,AK26="",$N26=0),"", IF($G26=$E$6, SUM(IF(OFFSET($R$23,,,($F26-1)*3-2,$D$3)=AK26,OFFSET($R$25,,,($F26-1)*3-2,$D$3)*OFFSET($B$23,1,,($F26-1)*3-2,1))), IF($D26=1,$N26, SUMIF(OFFSET(Orçamento!$D$1,$B26-1,,$C26,),$F27&"-"&AK26,OFFSET(Orçamento!$I$1,$B26-1,,$C26,))*$N26/$E27)))}
B28: {=IF($F26>$E$2,"",IF($F$2=1,INDEX('QC rev00'!$M$10:$T$120,$F28,5),IF($F$2=2,INDEX(#REF!,$F28,5),INDEX(#REF!,$F28,5))))} | C28: {=IF($F26>$E$2,"",IF($F$2=1,INDEX('QC rev00'!$M$10:$T$120,$F28,6),IF($F$2=2,INDEX(#REF!,$F28,6),INDEX(#REF!,$F28,6))))} | F28: =IF(F26>$E$2,"",MATCH(F26,'QC rev00'!$C$10:$C$120,)) | Q28: Valor | R28: =IFERROR(R27*$O26,0) -> 0 | S28: =IFERROR(S27*$O26,0) -> 0 | T28: =IFERROR(T27*$O26,0) -> 0 | U28: =IFERROR(U27*$O26,0) -> 0 | V28: =IFERROR(V27*$O26,0) -> 0 | W28: =IFERROR(W27*$O26,0) -> 0 | X28: =IFERROR(X27*$O26,0) -> 0 | Y28: =IFERROR(Y27*$O26,0) -> 0 | ... AK28: =IFERROR(AK27*$O26,0) -> 0
B29: =IF($F29>$E$2,0,IF(E29<>"",MATCH(F30&" - Mapa",Orçamento!J:J,),0)) -> 0 | C29: =IF($D29>1,_xlfn.MAXIFS(Orçamento!G:G,Orçamento!J:J,F30&" - Mapa")+6-B29,0) -> 0 | D29: =IF($F29>$E$2,0,IF($G29=$E$6,$D$2,IF(E29<>"",_xlfn.MAXIFS(Orçamento!E:E,Orçamento!J:J,F30&" - Mapa"),0))) -> 0 | E29: =IF(F30="","",_xlfn.IFNA(MATCH($F30,'QC rev00'!$G$10:$G$120,),"")) | F29: {=OFFSET(F29,-3,,,)+1} -> 3 | G29: {=IF($F29>$E$2,"",IF($F$2=1,INDEX('QC rev00'!$M$10:$T$120,$F31,2),IF($F$2=2,INDEX(#REF!,$F31,2),INDEX(#REF!,$F31,2))))} | H29: {=IF($F29>$E$2,"",IF($F$2=1,INDEX('QC rev00'!$M$10:$T$120,$F31,3),IF($F$2=2,INDEX(#REF!,$F31,3),INDEX(#REF!,$F31,3))))} | L29: {=IF($F29>$E$2,"",IF($F$2=1,INDEX('QC rev00'!$M$10:$T$120,$F31,7),IF($F$2=2,INDEX(#REF!,$F31,7),INDEX(#REF!,$F31,7))))} | M29: {=IF($F29>$E$2,"",IF($F$2=1,INDEX('QC rev00'!$M$10:$T$120,$F31,8),IF($F$2=2,INDEX(#REF!,$F31,8),INDEX(#REF!,$F31,8))))} | N29: {=IF($F29>$E$2,0,IF(_xlfn.IFNA(MATCH($G29,Listas!$E$4:$E$206,),0)>0,$F$5,IF($F$2=1,INDEX('QC rev00'!$M$10:$U$120,$F31,9),IF($F$2=2,INDEX(#REF!,$F31,9),INDEX(#REF!,$F31,9)))))} -> 0 | O29: {=IF($F29>$E$2,0,IF(_xlfn.IFNA(MATCH($G29,Listas!$E$4:$E$206,),0)>0,1,IF($H$10=0,0,IF($F$2=1,INDEX('QC rev00'!$M$10:$BC$120,$F31,9+$F$3),IF($F$2=2,INDEX(#REF!,$F31,9+$F$3),INDEX(#REF!,$F31,9+$F$3)))*IF($E$5="X",1,1-$B31-$C31))))} -> 0 | P29: =N29*O29 -> 0 | Q29: IP | R29: {=IF($D29=0,"",IF($G29=$E$6,INDEX(Orçamento!$U:$U,MATCH(R$21,Orçamento!$C:$C,),1),INDEX(Orçamento!$U:$U,$B29,1)))} | S29: =IF(S$21>$D29,"",IF($G29=$E$6,INDEX(Orçamento!$U:$U,MATCH(S$21,Orçamento!$C:$C,),1),INDEX(Orçamento!$U:$U,MATCH(S$21&"-"&$F30,Orçamento!$F:$F,),1))) | T29: =IF(T$21>$D29,"",IF($G29=$E$6,INDEX(Orçamento!$U:$U,MATCH(T$21,Orçamento!$C:$C,),1),INDEX(Orçamento!$U:$U,MATCH(T$21&"-"&$F30,Orçamento!$F:$F,),1))) | U29: =IF(U$21>$D29,"",IF($G29=$E$6,INDEX(Orçamento!$U:$U,MATCH(U$21,Orçamento!$C:$C,),1),INDEX(Orçamento!$U:$U,MATCH(U$21&"-"&$F30,Orçamento!$F:$F,),1))) | V29: =IF(V$21>$D29,"",IF($G29=$E$6,INDEX(Orçamento!$U:$U,MATCH(V$21,Orçamento!$C:$C,),1),INDEX(Orçamento!$U:$U,MATCH(V$21&"-"&$F30,Orçamento!$F:$F,),1))) | W29: =IF(W$21>$D29,"",IF($G29=$E$6,INDEX(Orçamento!$U:$U,MATCH(W$21,Orçamento!$C:$C,),1),INDEX(Orçamento!$U:$U,MATCH(W$21&"-"&$F30,Orçamento!$F:$F,),1))) | X29: =IF(X$21>$D29,"",IF($G29=$E$6,INDEX(Orçamento!$U:$U,MATCH(X$21,Orçamento!$C:$C,),1),INDEX(Orçamento!$U:$U,MATCH(X$21&"-"&$F30,Orçamento!$F:$F,),1))) | Y29: =IF(Y$21>$D29,"",IF($G29=$E$6,INDEX(Orçamento!$U:$U,MATCH(Y$21,Orçamento!$C:$C,),1),INDEX(Orçamento!$U:$U,MATCH(Y$21&"-"&$F30,Orçamento!$F:$F,),1))) | Z29: =IF(Z$21>$D29,"",IF($G29=$E$6,INDEX(Orçamento!$U:$U,MATCH(Z$21,Orçamento!$C:$C,),1),INDEX(Orçamento!$U:$U,MATCH(Z$21&"-"&$F30,Orçamento!$F:$F,),1))) | ... AK29: =IF(AK$21>$D29,"",IF($G29=$E$6,INDEX(Orçamento!$U:$U,MATCH(AK$21,Orçamento!$C:$C,),1),INDEX(Orçamento!$U:$U,MATCH(AK$21&"-"&$F30,Orçamento!$F:$F,),1)))
B30: =IF($F29>$E$2,0,(1/(1-B31-C31))*(B31+C31)) -> 0 | C30: {=IF(ROUND(SUM(IF(R29:AK29<>"",(R30:AK30)))-N29,3)<>0,"X",0)} -> 0 | E30: {=IF($F29>$E$2,"",INDEX('QC rev00'!$J$9:$J$120,1+E29,1))} | F30: {=IF($F29>$E$2,"",IF($F$2=1,INDEX('QC rev00'!$M$10:$T$120,$F31,1),IF($F$2=2,INDEX(#REF!,$F31,1),INDEX(#REF!,$F31,1))))} | Q30: Qtd | R30: {=IF(OR($D29=0,R29="",$N29=0),"", IF($G29=$E$6, SUM(IF(OFFSET($R$23,,,($F29-1)*3-2,$D$3)=R29,OFFSET($R$25,,,($F29-1)*3-2,$D$3)*OFFSET($B$23,1,,($F29-1)*3-2,1))), IF($D29=1,$N29, SUMIF(OFFSET(Orçamento!$D$1,$B29-1,,$C29,),$F30&"-"&R29,OFFSET(Orçamento!$I$1,$B29-1,,$C29,))*$N29/$E30)))} | S30: {=IF(OR($D29=0,S29="",$N29=0),"", IF($G29=$E$6, SUM(IF(OFFSET($R$23,,,($F29-1)*3-2,$D$3)=S29,OFFSET($R$25,,,($F29-1)*3-2,$D$3)*OFFSET($B$23,1,,($F29-1)*3-2,1))), IF($D29=1,$N29, SUMIF(OFFSET(Orçamento!$D$1,$B29-1,,$C29,),$F30&"-"&S29,OFFSET(Orçamento!$I$1,$B29-1,,$C29,))*$N29/$E30)))} | T30: {=IF(OR($D29=0,T29="",$N29=0),"", IF($G29=$E$6, SUM(IF(OFFSET($R$23,,,($F29-1)*3-2,$D$3)=T29,OFFSET($R$25,,,($F29-1)*3-2,$D$3)*OFFSET($B$23,1,,($F29-1)*3-2,1))), IF($D29=1,$N29, SUMIF(OFFSET(Orçamento!$D$1,$B29-1,,$C29,),$F30&"-"&T29,OFFSET(Orçamento!$I$1,$B29-1,,$C29,))*$N29/$E30)))} | U30: {=IF(OR($D29=0,U29="",$N29=0),"", IF($G29=$E$6, SUM(IF(OFFSET($R$23,,,($F29-1)*3-2,$D$3)=U29,OFFSET($R$25,,,($F29-1)*3-2,$D$3)*OFFSET($B$23,1,,($F29-1)*3-2,1))), IF($D29=1,$N29, SUMIF(OFFSET(Orçamento!$D$1,$B29-1,,$C29,),$F30&"-"&U29,OFFSET(Orçamento!$I$1,$B29-1,,$C29,))*$N29/$E30)))} | V30: {=IF(OR($D29=0,V29="",$N29=0),"", IF($G29=$E$6, SUM(IF(OFFSET($R$23,,,($F29-1)*3-2,$D$3)=V29,OFFSET($R$25,,,($F29-1)*3-2,$D$3)*OFFSET($B$23,1,,($F29-1)*3-2,1))), IF($D29=1,$N29, SUMIF(OFFSET(Orçamento!$D$1,$B29-1,,$C29,),$F30&"-"&V29,OFFSET(Orçamento!$I$1,$B29-1,,$C29,))*$N29/$E30)))} | W30: {=IF(OR($D29=0,W29="",$N29=0),"", IF($G29=$E$6, SUM(IF(OFFSET($R$23,,,($F29-1)*3-2,$D$3)=W29,OFFSET($R$25,,,($F29-1)*3-2,$D$3)*OFFSET($B$23,1,,($F29-1)*3-2,1))), IF($D29=1,$N29, SUMIF(OFFSET(Orçamento!$D$1,$B29-1,,$C29,),$F30&"-"&W29,OFFSET(Orçamento!$I$1,$B29-1,,$C29,))*$N29/$E30)))} | X30: {=IF(OR($D29=0,X29="",$N29=0),"", IF($G29=$E$6, SUM(IF(OFFSET($R$23,,,($F29-1)*3-2,$D$3)=X29,OFFSET($R$25,,,($F29-1)*3-2,$D$3)*OFFSET($B$23,1,,($F29-1)*3-2,1))), IF($D29=1,$N29, SUMIF(OFFSET(Orçamento!$D$1,$B29-1,,$C29,),$F30&"-"&X29,OFFSET(Orçamento!$I$1,$B29-1,,$C29,))*$N29/$E30)))} | Y30: {=IF(OR($D29=0,Y29="",$N29=0),"", IF($G29=$E$6, SUM(IF(OFFSET($R$23,,,($F29-1)*3-2,$D$3)=Y29,OFFSET($R$25,,,($F29-1)*3-2,$D$3)*OFFSET($B$23,1,,($F29-1)*3-2,1))), IF($D29=1,$N29, SUMIF(OFFSET(Orçamento!$D$1,$B29-1,,$C29,),$F30&"-"&Y29,OFFSET(Orçamento!$I$1,$B29-1,,$C29,))*$N29/$E30)))} | ... AK30: {=IF(OR($D29=0,AK29="",$N29=0),"", IF($G29=$E$6, SUM(IF(OFFSET($R$23,,,($F29-1)*3-2,$D$3)=AK29,OFFSET($R$25,,,($F29-1)*3-2,$D$3)*OFFSET($B$23,1,,($F29-1)*3-2,1))), IF($D29=1,$N29, SUMIF(OFFSET(Orçamento!$D$1,$B29-1,,$C29,),$F30&"-"&AK29,OFFSET(Orçamento!$I$1,$B29-1,,$C29,))*$N29/$E30)))}
B31: {=IF($F29>$E$2,"",IF($F$2=1,INDEX('QC rev00'!$M$10:$T$120,$F31,5),IF($F$2=2,INDEX(#REF!,$F31,5),INDEX(#REF!,$F31,5))))} | C31: {=IF($F29>$E$2,"",IF($F$2=1,INDEX('QC rev00'!$M$10:$T$120,$F31,6),IF($F$2=2,INDEX(#REF!,$F31,6),INDEX(#REF!,$F31,6))))} | F31: =IF(F29>$E$2,"",MATCH(F29,'QC rev00'!$C$10:$C$120,)) | Q31: Valor | R31: =IFERROR(R30*$O29,0) -> 0 | S31: =IFERROR(S30*$O29,0) -> 0 | T31: =IFERROR(T30*$O29,0) -> 0 | U31: =IFERROR(U30*$O29,0) -> 0 | V31: =IFERROR(V30*$O29,0) -> 0 | W31: =IFERROR(W30*$O29,0) -> 0 | X31: =IFERROR(X30*$O29,0) -> 0 | Y31: =IFERROR(Y30*$O29,0) -> 0 | ... AK31: =IFERROR(AK30*$O29,0) -> 0
B32: =IF($F32>$E$2,0,IF(E32<>"",MATCH(F33&" - Mapa",Orçamento!J:J,),0)) -> 0 | C32: =IF($D32>1,_xlfn.MAXIFS(Orçamento!G:G,Orçamento!J:J,F33&" - Mapa")+6-B32,0) -> 0 | D32: =IF($F32>$E$2,0,IF($G32=$E$6,$D$2,IF(E32<>"",_xlfn.MAXIFS(Orçamento!E:E,Orçamento!J:J,F33&" - Mapa"),0))) -> 0 | E32: =IF(F33="","",_xlfn.IFNA(MATCH($F33,'QC rev00'!$G$10:$G$120,),"")) | F32: {=OFFSET(F32,-3,,,)+1} -> 4 | G32: {=IF($F32>$E$2,"",IF($F$2=1,INDEX('QC rev00'!$M$10:$T$120,$F34,2),IF($F$2=2,INDEX(#REF!,$F34,2),INDEX(#REF!,$F34,2))))} | H32: {=IF($F32>$E$2,"",IF($F$2=1,INDEX('QC rev00'!$M$10:$T$120,$F34,3),IF($F$2=2,INDEX(#REF!,$F34,3),INDEX(#REF!,$F34,3))))} | L32: {=IF($F32>$E$2,"",IF($F$2=1,INDEX('QC rev00'!$M$10:$T$120,$F34,7),IF($F$2=2,INDEX(#REF!,$F34,7),INDEX(#REF!,$F34,7))))} | M32: {=IF($F32>$E$2,"",IF($F$2=1,INDEX('QC rev00'!$M$10:$T$120,$F34,8),IF($F$2=2,INDEX(#REF!,$F34,8),INDEX(#REF!,$F34,8))))} | N32: {=IF($F32>$E$2,0,IF(_xlfn.IFNA(MATCH($G32,Listas!$E$4:$E$206,),0)>0,$F$5,IF($F$2=1,INDEX('QC rev00'!$M$10:$U$120,$F34,9),IF($F$2=2,INDEX(#REF!,$F34,9),INDEX(#REF!,$F34,9)))))} -> 0 | O32: {=IF($F32>$E$2,0,IF(_xlfn.IFNA(MATCH($G32,Listas!$E$4:$E$206,),0)>0,1,IF($H$10=0,0,IF($F$2=1,INDEX('QC rev00'!$M$10:$BC$120,$F34,9+$F$3),IF($F$2=2,INDEX(#REF!,$F34,9+$F$3),INDEX(#REF!,$F34,9+$F$3)))*IF($E$5="X",1,1-$B34-$C34))))} -> 0 | P32: =N32*O32 -> 0 | Q32: IP | R32: {=IF($D32=0,"",IF($G32=$E$6,INDEX(Orçamento!$U:$U,MATCH(R$21,Orçamento!$C:$C,),1),INDEX(Orçamento!$U:$U,$B32,1)))} | S32: =IF(S$21>$D32,"",IF($G32=$E$6,INDEX(Orçamento!$U:$U,MATCH(S$21,Orçamento!$C:$C,),1),INDEX(Orçamento!$U:$U,MATCH(S$21&"-"&$F33,Orçamento!$F:$F,),1))) | T32: =IF(T$21>$D32,"",IF($G32=$E$6,INDEX(Orçamento!$U:$U,MATCH(T$21,Orçamento!$C:$C,),1),INDEX(Orçamento!$U:$U,MATCH(T$21&"-"&$F33,Orçamento!$F:$F,),1))) | U32: =IF(U$21>$D32,"",IF($G32=$E$6,INDEX(Orçamento!$U:$U,MATCH(U$21,Orçamento!$C:$C,),1),INDEX(Orçamento!$U:$U,MATCH(U$21&"-"&$F33,Orçamento!$F:$F,),1))) | V32: =IF(V$21>$D32,"",IF($G32=$E$6,INDEX(Orçamento!$U:$U,MATCH(V$21,Orçamento!$C:$C,),1),INDEX(Orçamento!$U:$U,MATCH(V$21&"-"&$F33,Orçamento!$F:$F,),1))) | W32: =IF(W$21>$D32,"",IF($G32=$E$6,INDEX(Orçamento!$U:$U,MATCH(W$21,Orçamento!$C:$C,),1),INDEX(Orçamento!$U:$U,MATCH(W$21&"-"&$F33,Orçamento!$F:$F,),1))) | X32: =IF(X$21>$D32,"",IF($G32=$E$6,INDEX(Orçamento!$U:$U,MATCH(X$21,Orçamento!$C:$C,),1),INDEX(Orçamento!$U:$U,MATCH(X$21&"-"&$F33,Orçamento!$F:$F,),1))) | Y32: =IF(Y$21>$D32,"",IF($G32=$E$6,INDEX(Orçamento!$U:$U,MATCH(Y$21,Orçamento!$C:$C,),1),INDEX(Orçamento!$U:$U,MATCH(Y$21&"-"&$F33,Orçamento!$F:$F,),1))) | Z32: =IF(Z$21>$D32,"",IF($G32=$E$6,INDEX(Orçamento!$U:$U,MATCH(Z$21,Orçamento!$C:$C,),1),INDEX(Orçamento!$U:$U,MATCH(Z$21&"-"&$F33,Orçamento!$F:$F,),1))) | ... AK32: =IF(AK$21>$D32,"",IF($G32=$E$6,INDEX(Orçamento!$U:$U,MATCH(AK$21,Orçamento!$C:$C,),1),INDEX(Orçamento!$U:$U,MATCH(AK$21&"-"&$F33,Orçamento!$F:$F,),1)))
B33: =IF($F32>$E$2,0,(1/(1-B34-C34))*(B34+C34)) -> 0 | C33: {=IF(ROUND(SUM(IF(R32:AK32<>"",(R33:AK33)))-N32,3)<>0,"X",0)} -> 0 | E33: {=IF($F32>$E$2,"",INDEX('QC rev00'!$J$9:$J$120,1+E32,1))} | F33: {=IF($F32>$E$2,"",IF($F$2=1,INDEX('QC rev00'!$M$10:$T$120,$F34,1),IF($F$2=2,INDEX(#REF!,$F34,1),INDEX(#REF!,$F34,1))))} | Q33: Qtd | R33: {=IF(OR($D32=0,R32="",$N32=0),"", IF($G32=$E$6, SUM(IF(OFFSET($R$23,,,($F32-1)*3-2,$D$3)=R32,OFFSET($R$25,,,($F32-1)*3-2,$D$3)*OFFSET($B$23,1,,($F32-1)*3-2,1))), IF($D32=1,$N32, SUMIF(OFFSET(Orçamento!$D$1,$B32-1,,$C32,),$F33&"-"&R32,OFFSET(Orçamento!$I$1,$B32-1,,$C32,))*$N32/$E33)))} | S33: {=IF(OR($D32=0,S32="",$N32=0),"", IF($G32=$E$6, SUM(IF(OFFSET($R$23,,,($F32-1)*3-2,$D$3)=S32,OFFSET($R$25,,,($F32-1)*3-2,$D$3)*OFFSET($B$23,1,,($F32-1)*3-2,1))), IF($D32=1,$N32, SUMIF(OFFSET(Orçamento!$D$1,$B32-1,,$C32,),$F33&"-"&S32,OFFSET(Orçamento!$I$1,$B32-1,,$C32,))*$N32/$E33)))} | T33: {=IF(OR($D32=0,T32="",$N32=0),"", IF($G32=$E$6, SUM(IF(OFFSET($R$23,,,($F32-1)*3-2,$D$3)=T32,OFFSET($R$25,,,($F32-1)*3-2,$D$3)*OFFSET($B$23,1,,($F32-1)*3-2,1))), IF($D32=1,$N32, SUMIF(OFFSET(Orçamento!$D$1,$B32-1,,$C32,),$F33&"-"&T32,OFFSET(Orçamento!$I$1,$B32-1,,$C32,))*$N32/$E33)))} | U33: {=IF(OR($D32=0,U32="",$N32=0),"", IF($G32=$E$6, SUM(IF(OFFSET($R$23,,,($F32-1)*3-2,$D$3)=U32,OFFSET($R$25,,,($F32-1)*3-2,$D$3)*OFFSET($B$23,1,,($F32-1)*3-2,1))), IF($D32=1,$N32, SUMIF(OFFSET(Orçamento!$D$1,$B32-1,,$C32,),$F33&"-"&U32,OFFSET(Orçamento!$I$1,$B32-1,,$C32,))*$N32/$E33)))} | V33: {=IF(OR($D32=0,V32="",$N32=0),"", IF($G32=$E$6, SUM(IF(OFFSET($R$23,,,($F32-1)*3-2,$D$3)=V32,OFFSET($R$25,,,($F32-1)*3-2,$D$3)*OFFSET($B$23,1,,($F32-1)*3-2,1))), IF($D32=1,$N32, SUMIF(OFFSET(Orçamento!$D$1,$B32-1,,$C32,),$F33&"-"&V32,OFFSET(Orçamento!$I$1,$B32-1,,$C32,))*$N32/$E33)))} | W33: {=IF(OR($D32=0,W32="",$N32=0),"", IF($G32=$E$6, SUM(IF(OFFSET($R$23,,,($F32-1)*3-2,$D$3)=W32,OFFSET($R$25,,,($F32-1)*3-2,$D$3)*OFFSET($B$23,1,,($F32-1)*3-2,1))), IF($D32=1,$N32, SUMIF(OFFSET(Orçamento!$D$1,$B32-1,,$C32,),$F33&"-"&W32,OFFSET(Orçamento!$I$1,$B32-1,,$C32,))*$N32/$E33)))} | X33: {=IF(OR($D32=0,X32="",$N32=0),"", IF($G32=$E$6, SUM(IF(OFFSET($R$23,,,($F32-1)*3-2,$D$3)=X32,OFFSET($R$25,,,($F32-1)*3-2,$D$3)*OFFSET($B$23,1,,($F32-1)*3-2,1))), IF($D32=1,$N32, SUMIF(OFFSET(Orçamento!$D$1,$B32-1,,$C32,),$F33&"-"&X32,OFFSET(Orçamento!$I$1,$B32-1,,$C32,))*$N32/$E33)))} | Y33: {=IF(OR($D32=0,Y32="",$N32=0),"", IF($G32=$E$6, SUM(IF(OFFSET($R$23,,,($F32-1)*3-2,$D$3)=Y32,OFFSET($R$25,,,($F32-1)*3-2,$D$3)*OFFSET($B$23,1,,($F32-1)*3-2,1))), IF($D32=1,$N32, SUMIF(OFFSET(Orçamento!$D$1,$B32-1,,$C32,),$F33&"-"&Y32,OFFSET(Orçamento!$I$1,$B32-1,,$C32,))*$N32/$E33)))} | ... AK33: {=IF(OR($D32=0,AK32="",$N32=0),"", IF($G32=$E$6, SUM(IF(OFFSET($R$23,,,($F32-1)*3-2,$D$3)=AK32,OFFSET($R$25,,,($F32-1)*3-2,$D$3)*OFFSET($B$23,1,,($F32-1)*3-2,1))), IF($D32=1,$N32, SUMIF(OFFSET(Orçamento!$D$1,$B32-1,,$C32,),$F33&"-"&AK32,OFFSET(Orçamento!$I$1,$B32-1,,$C32,))*$N32/$E33)))}
B34: {=IF($F32>$E$2,"",IF($F$2=1,INDEX('QC rev00'!$M$10:$T$120,$F34,5),IF($F$2=2,INDEX(#REF!,$F34,5),INDEX(#REF!,$F34,5))))} | C34: {=IF($F32>$E$2,"",IF($F$2=1,INDEX('QC rev00'!$M$10:$T$120,$F34,6),IF($F$2=2,INDEX(#REF!,$F34,6),INDEX(#REF!,$F34,6))))} | F34: =IF(F32>$E$2,"",MATCH(F32,'QC rev00'!$C$10:$C$120,)) | Q34: Valor | R34: =IFERROR(R33*$O32,0) -> 0 | S34: =IFERROR(S33*$O32,0) -> 0 | T34: =IFERROR(T33*$O32,0) -> 0 | U34: =IFERROR(U33*$O32,0) -> 0 | V34: =IFERROR(V33*$O32,0) -> 0 | W34: =IFERROR(W33*$O32,0) -> 0 | X34: =IFERROR(X33*$O32,0) -> 0 | Y34: =IFERROR(Y33*$O32,0) -> 0 | ... AK34: =IFERROR(AK33*$O32,0) -> 0
B35: =IF($F35>$E$2,0,IF(E35<>"",MATCH(F36&" - Mapa",Orçamento!J:J,),0)) -> 0 | C35: =IF($D35>1,_xlfn.MAXIFS(Orçamento!G:G,Orçamento!J:J,F36&" - Mapa")+6-B35,0) -> 0 | D35: =IF($F35>$E$2,0,IF($G35=$E$6,$D$2,IF(E35<>"",_xlfn.MAXIFS(Orçamento!E:E,Orçamento!J:J,F36&" - Mapa"),0))) -> 0 | E35: =IF(F36="","",_xlfn.IFNA(MATCH($F36,'QC rev00'!$G$10:$G$120,),"")) | F35: {=OFFSET(F35,-3,,,)+1} -> 5 | G35: {=IF($F35>$E$2,"",IF($F$2=1,INDEX('QC rev00'!$M$10:$T$120,$F37,2),IF($F$2=2,INDEX(#REF!,$F37,2),INDEX(#REF!,$F37,2))))} | H35: {=IF($F35>$E$2,"",IF($F$2=1,INDEX('QC rev00'!$M$10:$T$120,$F37,3),IF($F$2=2,INDEX(#REF!,$F37,3),INDEX(#REF!,$F37,3))))} | L35: {=IF($F35>$E$2,"",IF($F$2=1,INDEX('QC rev00'!$M$10:$T$120,$F37,7),IF($F$2=2,INDEX(#REF!,$F37,7),INDEX(#REF!,$F37,7))))} | M35: {=IF($F35>$E$2,"",IF($F$2=1,INDEX('QC rev00'!$M$10:$T$120,$F37,8),IF($F$2=2,INDEX(#REF!,$F37,8),INDEX(#REF!,$F37,8))))} | N35: {=IF($F35>$E$2,0,IF(_xlfn.IFNA(MATCH($G35,Listas!$E$4:$E$206,),0)>0,$F$5,IF($F$2=1,INDEX('QC rev00'!$M$10:$U$120,$F37,9),IF($F$2=2,INDEX(#REF!,$F37,9),INDEX(#REF!,$F37,9)))))} -> 0 | O35: {=IF($F35>$E$2,0,IF(_xlfn.IFNA(MATCH($G35,Listas!$E$4:$E$206,),0)>0,1,IF($H$10=0,0,IF($F$2=1,INDEX('QC rev00'!$M$10:$BC$120,$F37,9+$F$3),IF($F$2=2,INDEX(#REF!,$F37,9+$F$3),INDEX(#REF!,$F37,9+$F$3)))*IF($E$5="X",1,1-$B37-$C37))))} -> 0 | P35: =N35*O35 -> 0 | Q35: IP | R35: {=IF($D35=0,"",IF($G35=$E$6,INDEX(Orçamento!$U:$U,MATCH(R$21,Orçamento!$C:$C,),1),INDEX(Orçamento!$U:$U,$B35,1)))} | S35: =IF(S$21>$D35,"",IF($G35=$E$6,INDEX(Orçamento!$U:$U,MATCH(S$21,Orçamento!$C:$C,),1),INDEX(Orçamento!$U:$U,MATCH(S$21&"-"&$F36,Orçamento!$F:$F,),1))) | T35: =IF(T$21>$D35,"",IF($G35=$E$6,INDEX(Orçamento!$U:$U,MATCH(T$21,Orçamento!$C:$C,),1),INDEX(Orçamento!$U:$U,MATCH(T$21&"-"&$F36,Orçamento!$F:$F,),1))) | U35: =IF(U$21>$D35,"",IF($G35=$E$6,INDEX(Orçamento!$U:$U,MATCH(U$21,Orçamento!$C:$C,),1),INDEX(Orçamento!$U:$U,MATCH(U$21&"-"&$F36,Orçamento!$F:$F,),1))) | V35: =IF(V$21>$D35,"",IF($G35=$E$6,INDEX(Orçamento!$U:$U,MATCH(V$21,Orçamento!$C:$C,),1),INDEX(Orçamento!$U:$U,MATCH(V$21&"-"&$F36,Orçamento!$F:$F,),1))) | W35: =IF(W$21>$D35,"",IF($G35=$E$6,INDEX(Orçamento!$U:$U,MATCH(W$21,Orçamento!$C:$C,),1),INDEX(Orçamento!$U:$U,MATCH(W$21&"-"&$F36,Orçamento!$F:$F,),1))) | X35: =IF(X$21>$D35,"",IF($G35=$E$6,INDEX(Orçamento!$U:$U,MATCH(X$21,Orçamento!$C:$C,),1),INDEX(Orçamento!$U:$U,MATCH(X$21&"-"&$F36,Orçamento!$F:$F,),1))) | Y35: =IF(Y$21>$D35,"",IF($G35=$E$6,INDEX(Orçamento!$U:$U,MATCH(Y$21,Orçamento!$C:$C,),1),INDEX(Orçamento!$U:$U,MATCH(Y$21&"-"&$F36,Orçamento!$F:$F,),1))) | Z35: =IF(Z$21>$D35,"",IF($G35=$E$6,INDEX(Orçamento!$U:$U,MATCH(Z$21,Orçamento!$C:$C,),1),INDEX(Orçamento!$U:$U,MATCH(Z$21&"-"&$F36,Orçamento!$F:$F,),1))) | ... AK35: =IF(AK$21>$D35,"",IF($G35=$E$6,INDEX(Orçamento!$U:$U,MATCH(AK$21,Orçamento!$C:$C,),1),INDEX(Orçamento!$U:$U,MATCH(AK$21&"-"&$F36,Orçamento!$F:$F,),1)))
B36: =IF($F35>$E$2,0,(1/(1-B37-C37))*(B37+C37)) -> 0 | C36: {=IF(ROUND(SUM(IF(R35:AK35<>"",(R36:AK36)))-N35,3)<>0,"X",0)} -> 0 | E36: {=IF($F35>$E$2,"",INDEX('QC rev00'!$J$9:$J$120,1+E35,1))} | F36: {=IF($F35>$E$2,"",IF($F$2=1,INDEX('QC rev00'!$M$10:$T$120,$F37,1),IF($F$2=2,INDEX(#REF!,$F37,1),INDEX(#REF!,$F37,1))))} | Q36: Qtd | R36: {=IF(OR($D35=0,R35="",$N35=0),"", IF($G35=$E$6, SUM(IF(OFFSET($R$23,,,($F35-1)*3-2,$D$3)=R35,OFFSET($R$25,,,($F35-1)*3-2,$D$3)*OFFSET($B$23,1,,($F35-1)*3-2,1))), IF($D35=1,$N35, SUMIF(OFFSET(Orçamento!$D$1,$B35-1,,$C35,),$F36&"-"&R35,OFFSET(Orçamento!$I$1,$B35-1,,$C35,))*$N35/$E36)))} | S36: {=IF(OR($D35=0,S35="",$N35=0),"", IF($G35=$E$6, SUM(IF(OFFSET($R$23,,,($F35-1)*3-2,$D$3)=S35,OFFSET($R$25,,,($F35-1)*3-2,$D$3)*OFFSET($B$23,1,,($F35-1)*3-2,1))), IF($D35=1,$N35, SUMIF(OFFSET(Orçamento!$D$1,$B35-1,,$C35,),$F36&"-"&S35,OFFSET(Orçamento!$I$1,$B35-1,,$C35,))*$N35/$E36)))} | T36: {=IF(OR($D35=0,T35="",$N35=0),"", IF($G35=$E$6, SUM(IF(OFFSET($R$23,,,($F35-1)*3-2,$D$3)=T35,OFFSET($R$25,,,($F35-1)*3-2,$D$3)*OFFSET($B$23,1,,($F35-1)*3-2,1))), IF($D35=1,$N35, SUMIF(OFFSET(Orçamento!$D$1,$B35-1,,$C35,),$F36&"-"&T35,OFFSET(Orçamento!$I$1,$B35-1,,$C35,))*$N35/$E36)))} | U36: {=IF(OR($D35=0,U35="",$N35=0),"", IF($G35=$E$6, SUM(IF(OFFSET($R$23,,,($F35-1)*3-2,$D$3)=U35,OFFSET($R$25,,,($F35-1)*3-2,$D$3)*OFFSET($B$23,1,,($F35-1)*3-2,1))), IF($D35=1,$N35, SUMIF(OFFSET(Orçamento!$D$1,$B35-1,,$C35,),$F36&"-"&U35,OFFSET(Orçamento!$I$1,$B35-1,,$C35,))*$N35/$E36)))} | V36: {=IF(OR($D35=0,V35="",$N35=0),"", IF($G35=$E$6, SUM(IF(OFFSET($R$23,,,($F35-1)*3-2,$D$3)=V35,OFFSET($R$25,,,($F35-1)*3-2,$D$3)*OFFSET($B$23,1,,($F35-1)*3-2,1))), IF($D35=1,$N35, SUMIF(OFFSET(Orçamento!$D$1,$B35-1,,$C35,),$F36&"-"&V35,OFFSET(Orçamento!$I$1,$B35-1,,$C35,))*$N35/$E36)))} | W36: {=IF(OR($D35=0,W35="",$N35=0),"", IF($G35=$E$6, SUM(IF(OFFSET($R$23,,,($F35-1)*3-2,$D$3)=W35,OFFSET($R$25,,,($F35-1)*3-2,$D$3)*OFFSET($B$23,1,,($F35-1)*3-2,1))), IF($D35=1,$N35, SUMIF(OFFSET(Orçamento!$D$1,$B35-1,,$C35,),$F36&"-"&W35,OFFSET(Orçamento!$I$1,$B35-1,,$C35,))*$N35/$E36)))} | X36: {=IF(OR($D35=0,X35="",$N35=0),"", IF($G35=$E$6, SUM(IF(OFFSET($R$23,,,($F35-1)*3-2,$D$3)=X35,OFFSET($R$25,,,($F35-1)*3-2,$D$3)*OFFSET($B$23,1,,($F35-1)*3-2,1))), IF($D35=1,$N35, SUMIF(OFFSET(Orçamento!$D$1,$B35-1,,$C35,),$F36&"-"&X35,OFFSET(Orçamento!$I$1,$B35-1,,$C35,))*$N35/$E36)))} | Y36: {=IF(OR($D35=0,Y35="",$N35=0),"", IF($G35=$E$6, SUM(IF(OFFSET($R$23,,,($F35-1)*3-2,$D$3)=Y35,OFFSET($R$25,,,($F35-1)*3-2,$D$3)*OFFSET($B$23,1,,($F35-1)*3-2,1))), IF($D35=1,$N35, SUMIF(OFFSET(Orçamento!$D$1,$B35-1,,$C35,),$F36&"-"&Y35,OFFSET(Orçamento!$I$1,$B35-1,,$C35,))*$N35/$E36)))} | ... AK36: {=IF(OR($D35=0,AK35="",$N35=0),"", IF($G35=$E$6, SUM(IF(OFFSET($R$23,,,($F35-1)*3-2,$D$3)=AK35,OFFSET($R$25,,,($F35-1)*3-2,$D$3)*OFFSET($B$23,1,,($F35-1)*3-2,1))), IF($D35=1,$N35, SUMIF(OFFSET(Orçamento!$D$1,$B35-1,,$C35,),$F36&"-"&AK35,OFFSET(Orçamento!$I$1,$B35-1,,$C35,))*$N35/$E36)))}
B37: {=IF($F35>$E$2,"",IF($F$2=1,INDEX('QC rev00'!$M$10:$T$120,$F37,5),IF($F$2=2,INDEX(#REF!,$F37,5),INDEX(#REF!,$F37,5))))} | C37: {=IF($F35>$E$2,"",IF($F$2=1,INDEX('QC rev00'!$M$10:$T$120,$F37,6),IF($F$2=2,INDEX(#REF!,$F37,6),INDEX(#REF!,$F37,6))))} | F37: =IF(F35>$E$2,"",MATCH(F35,'QC rev00'!$C$10:$C$120,)) | Q37: Valor | R37: =IFERROR(R36*$O35,0) -> 0 | S37: =IFERROR(S36*$O35,0) -> 0 | T37: =IFERROR(T36*$O35,0) -> 0 | U37: =IFERROR(U36*$O35,0) -> 0 | V37: =IFERROR(V36*$O35,0) -> 0 | W37: =IFERROR(W36*$O35,0) -> 0 | X37: =IFERROR(X36*$O35,0) -> 0 | Y37: =IFERROR(Y36*$O35,0) -> 0 | ... AK37: =IFERROR(AK36*$O35,0) -> 0
B38: =IF($F38>$E$2,0,IF(E38<>"",MATCH(F39&" - Mapa",Orçamento!J:J,),0)) -> 0 | C38: =IF($D38>1,_xlfn.MAXIFS(Orçamento!G:G,Orçamento!J:J,F39&" - Mapa")+6-B38,0) -> 0 | D38: =IF($F38>$E$2,0,IF($G38=$E$6,$D$2,IF(E38<>"",_xlfn.MAXIFS(Orçamento!E:E,Orçamento!J:J,F39&" - Mapa"),0))) -> 0 | E38: =IF(F39="","",_xlfn.IFNA(MATCH($F39,'QC rev00'!$G$10:$G$120,),"")) | F38: {=OFFSET(F38,-3,,,)+1} -> 6 | G38: {=IF($F38>$E$2,"",IF($F$2=1,INDEX('QC rev00'!$M$10:$T$120,$F40,2),IF($F$2=2,INDEX(#REF!,$F40,2),INDEX(#REF!,$F40,2))))} | H38: {=IF($F38>$E$2,"",IF($F$2=1,INDEX('QC rev00'!$M$10:$T$120,$F40,3),IF($F$2=2,INDEX(#REF!,$F40,3),INDEX(#REF!,$F40,3))))} | L38: {=IF($F38>$E$2,"",IF($F$2=1,INDEX('QC rev00'!$M$10:$T$120,$F40,7),IF($F$2=2,INDEX(#REF!,$F40,7),INDEX(#REF!,$F40,7))))} | M38: {=IF($F38>$E$2,"",IF($F$2=1,INDEX('QC rev00'!$M$10:$T$120,$F40,8),IF($F$2=2,INDEX(#REF!,$F40,8),INDEX(#REF!,$F40,8))))} | N38: {=IF($F38>$E$2,0,IF(_xlfn.IFNA(MATCH($G38,Listas!$E$4:$E$206,),0)>0,$F$5,IF($F$2=1,INDEX('QC rev00'!$M$10:$U$120,$F40,9),IF($F$2=2,INDEX(#REF!,$F40,9),INDEX(#REF!,$F40,9)))))} -> 0 | O38: {=IF($F38>$E$2,0,IF(_xlfn.IFNA(MATCH($G38,Listas!$E$4:$E$206,),0)>0,1,IF($H$10=0,0,IF($F$2=1,INDEX('QC rev00'!$M$10:$BC$120,$F40,9+$F$3),IF($F$2=2,INDEX(#REF!,$F40,9+$F$3),INDEX(#REF!,$F40,9+$F$3)))*IF($E$5="X",1,1-$B40-$C40))))} -> 0 | P38: =N38*O38 -> 0 | Q38: IP | R38: {=IF($D38=0,"",IF($G38=$E$6,INDEX(Orçamento!$U:$U,MATCH(R$21,Orçamento!$C:$C,),1),INDEX(Orçamento!$U:$U,$B38,1)))} | S38: =IF(S$21>$D38,"",IF($G38=$E$6,INDEX(Orçamento!$U:$U,MATCH(S$21,Orçamento!$C:$C,),1),INDEX(Orçamento!$U:$U,MATCH(S$21&"-"&$F39,Orçamento!$F:$F,),1))) | T38: =IF(T$21>$D38,"",IF($G38=$E$6,INDEX(Orçamento!$U:$U,MATCH(T$21,Orçamento!$C:$C,),1),INDEX(Orçamento!$U:$U,MATCH(T$21&"-"&$F39,Orçamento!$F:$F,),1))) | U38: =IF(U$21>$D38,"",IF($G38=$E$6,INDEX(Orçamento!$U:$U,MATCH(U$21,Orçamento!$C:$C,),1),INDEX(Orçamento!$U:$U,MATCH(U$21&"-"&$F39,Orçamento!$F:$F,),1))) | V38: =IF(V$21>$D38,"",IF($G38=$E$6,INDEX(Orçamento!$U:$U,MATCH(V$21,Orçamento!$C:$C,),1),INDEX(Orçamento!$U:$U,MATCH(V$21&"-"&$F39,Orçamento!$F:$F,),1))) | W38: =IF(W$21>$D38,"",IF($G38=$E$6,INDEX(Orçamento!$U:$U,MATCH(W$21,Orçamento!$C:$C,),1),INDEX(Orçamento!$U:$U,MATCH(W$21&"-"&$F39,Orçamento!$F:$F,),1))) | X38: =IF(X$21>$D38,"",IF($G38=$E$6,INDEX(Orçamento!$U:$U,MATCH(X$21,Orçamento!$C:$C,),1),INDEX(Orçamento!$U:$U,MATCH(X$21&"-"&$F39,Orçamento!$F:$F,),1))) | Y38: =IF(Y$21>$D38,"",IF($G38=$E$6,INDEX(Orçamento!$U:$U,MATCH(Y$21,Orçamento!$C:$C,),1),INDEX(Orçamento!$U:$U,MATCH(Y$21&"-"&$F39,Orçamento!$F:$F,),1))) | Z38: =IF(Z$21>$D38,"",IF($G38=$E$6,INDEX(Orçamento!$U:$U,MATCH(Z$21,Orçamento!$C:$C,),1),INDEX(Orçamento!$U:$U,MATCH(Z$21&"-"&$F39,Orçamento!$F:$F,),1))) | ... AK38: =IF(AK$21>$D38,"",IF($G38=$E$6,INDEX(Orçamento!$U:$U,MATCH(AK$21,Orçamento!$C:$C,),1),INDEX(Orçamento!$U:$U,MATCH(AK$21&"-"&$F39,Orçamento!$F:$F,),1)))
B39: =IF($F38>$E$2,0,(1/(1-B40-C40))*(B40+C40)) -> 0 | C39: {=IF(ROUND(SUM(IF(R38:AK38<>"",(R39:AK39)))-N38,3)<>0,"X",0)} -> 0 | E39: {=IF($F38>$E$2,"",INDEX('QC rev00'!$J$9:$J$120,1+E38,1))} | F39: {=IF($F38>$E$2,"",IF($F$2=1,INDEX('QC rev00'!$M$10:$T$120,$F40,1),IF($F$2=2,INDEX(#REF!,$F40,1),INDEX(#REF!,$F40,1))))} | Q39: Qtd | R39: {=IF(OR($D38=0,R38="",$N38=0),"", IF($G38=$E$6, SUM(IF(OFFSET($R$23,,,($F38-1)*3-2,$D$3)=R38,OFFSET($R$25,,,($F38-1)*3-2,$D$3)*OFFSET($B$23,1,,($F38-1)*3-2,1))), IF($D38=1,$N38, SUMIF(OFFSET(Orçamento!$D$1,$B38-1,,$C38,),$F39&"-"&R38,OFFSET(Orçamento!$I$1,$B38-1,,$C38,))*$N38/$E39)))} | S39: {=IF(OR($D38=0,S38="",$N38=0),"", IF($G38=$E$6, SUM(IF(OFFSET($R$23,,,($F38-1)*3-2,$D$3)=S38,OFFSET($R$25,,,($F38-1)*3-2,$D$3)*OFFSET($B$23,1,,($F38-1)*3-2,1))), IF($D38=1,$N38, SUMIF(OFFSET(Orçamento!$D$1,$B38-1,,$C38,),$F39&"-"&S38,OFFSET(Orçamento!$I$1,$B38-1,,$C38,))*$N38/$E39)))} | T39: {=IF(OR($D38=0,T38="",$N38=0),"", IF($G38=$E$6, SUM(IF(OFFSET($R$23,,,($F38-1)*3-2,$D$3)=T38,OFFSET($R$25,,,($F38-1)*3-2,$D$3)*OFFSET($B$23,1,,($F38-1)*3-2,1))), IF($D38=1,$N38, SUMIF(OFFSET(Orçamento!$D$1,$B38-1,,$C38,),$F39&"-"&T38,OFFSET(Orçamento!$I$1,$B38-1,,$C38,))*$N38/$E39)))} | U39: {=IF(OR($D38=0,U38="",$N38=0),"", IF($G38=$E$6, SUM(IF(OFFSET($R$23,,,($F38-1)*3-2,$D$3)=U38,OFFSET($R$25,,,($F38-1)*3-2,$D$3)*OFFSET($B$23,1,,($F38-1)*3-2,1))), IF($D38=1,$N38, SUMIF(OFFSET(Orçamento!$D$1,$B38-1,,$C38,),$F39&"-"&U38,OFFSET(Orçamento!$I$1,$B38-1,,$C38,))*$N38/$E39)))} | V39: {=IF(OR($D38=0,V38="",$N38=0),"", IF($G38=$E$6, SUM(IF(OFFSET($R$23,,,($F38-1)*3-2,$D$3)=V38,OFFSET($R$25,,,($F38-1)*3-2,$D$3)*OFFSET($B$23,1,,($F38-1)*3-2,1))), IF($D38=1,$N38, SUMIF(OFFSET(Orçamento!$D$1,$B38-1,,$C38,),$F39&"-"&V38,OFFSET(Orçamento!$I$1,$B38-1,,$C38,))*$N38/$E39)))} | W39: {=IF(OR($D38=0,W38="",$N38=0),"", IF($G38=$E$6, SUM(IF(OFFSET($R$23,,,($F38-1)*3-2,$D$3)=W38,OFFSET($R$25,,,($F38-1)*3-2,$D$3)*OFFSET($B$23,1,,($F38-1)*3-2,1))), IF($D38=1,$N38, SUMIF(OFFSET(Orçamento!$D$1,$B38-1,,$C38,),$F39&"-"&W38,OFFSET(Orçamento!$I$1,$B38-1,,$C38,))*$N38/$E39)))} | X39: {=IF(OR($D38=0,X38="",$N38=0),"", IF($G38=$E$6, SUM(IF(OFFSET($R$23,,,($F38-1)*3-2,$D$3)=X38,OFFSET($R$25,,,($F38-1)*3-2,$D$3)*OFFSET($B$23,1,,($F38-1)*3-2,1))), IF($D38=1,$N38, SUMIF(OFFSET(Orçamento!$D$1,$B38-1,,$C38,),$F39&"-"&X38,OFFSET(Orçamento!$I$1,$B38-1,,$C38,))*$N38/$E39)))} | Y39: {=IF(OR($D38=0,Y38="",$N38=0),"", IF($G38=$E$6, SUM(IF(OFFSET($R$23,,,($F38-1)*3-2,$D$3)=Y38,OFFSET($R$25,,,($F38-1)*3-2,$D$3)*OFFSET($B$23,1,,($F38-1)*3-2,1))), IF($D38=1,$N38, SUMIF(OFFSET(Orçamento!$D$1,$B38-1,,$C38,),$F39&"-"&Y38,OFFSET(Orçamento!$I$1,$B38-1,,$C38,))*$N38/$E39)))} | ... AK39: {=IF(OR($D38=0,AK38="",$N38=0),"", IF($G38=$E$6, SUM(IF(OFFSET($R$23,,,($F38-1)*3-2,$D$3)=AK38,OFFSET($R$25,,,($F38-1)*3-2,$D$3)*OFFSET($B$23,1,,($F38-1)*3-2,1))), IF($D38=1,$N38, SUMIF(OFFSET(Orçamento!$D$1,$B38-1,,$C38,),$F39&"-"&AK38,OFFSET(Orçamento!$I$1,$B38-1,,$C38,))*$N38/$E39)))}
B40: {=IF($F38>$E$2,"",IF($F$2=1,INDEX('QC rev00'!$M$10:$T$120,$F40,5),IF($F$2=2,INDEX(#REF!,$F40,5),INDEX(#REF!,$F40,5))))} | C40: {=IF($F38>$E$2,"",IF($F$2=1,INDEX('QC rev00'!$M$10:$T$120,$F40,6),IF($F$2=2,INDEX(#REF!,$F40,6),INDEX(#REF!,$F40,6))))} | F40: =IF(F38>$E$2,"",MATCH(F38,'QC rev00'!$C$10:$C$120,)) | Q40: Valor | R40: =IFERROR(R39*$O38,0) -> 0 | S40: =IFERROR(S39*$O38,0) -> 0 | T40: =IFERROR(T39*$O38,0) -> 0 | U40: =IFERROR(U39*$O38,0) -> 0 | V40: =IFERROR(V39*$O38,0) -> 0 | W40: =IFERROR(W39*$O38,0) -> 0 | X40: =IFERROR(X39*$O38,0) -> 0 | Y40: =IFERROR(Y39*$O38,0) -> 0 | ... AK40: =IFERROR(AK39*$O38,0) -> 0
B41: =IF($F41>$E$2,0,IF(E41<>"",MATCH(F42&" - Mapa",Orçamento!J:J,),0)) -> 0 | C41: =IF($D41>1,_xlfn.MAXIFS(Orçamento!G:G,Orçamento!J:J,F42&" - Mapa")+6-B41,0) -> 0 | D41: =IF($F41>$E$2,0,IF($G41=$E$6,$D$2,IF(E41<>"",_xlfn.MAXIFS(Orçamento!E:E,Orçamento!J:J,F42&" - Mapa"),0))) -> 0 | E41: =IF(F42="","",_xlfn.IFNA(MATCH($F42,'QC rev00'!$G$10:$G$120,),"")) | F41: {=OFFSET(F41,-3,,,)+1} -> 7 | G41: {=IF($F41>$E$2,"",IF($F$2=1,INDEX('QC rev00'!$M$10:$T$120,$F43,2),IF($F$2=2,INDEX(#REF!,$F43,2),INDEX(#REF!,$F43,2))))} | H41: {=IF($F41>$E$2,"",IF($F$2=1,INDEX('QC rev00'!$M$10:$T$120,$F43,3),IF($F$2=2,INDEX(#REF!,$F43,3),INDEX(#REF!,$F43,3))))} | L41: {=IF($F41>$E$2,"",IF($F$2=1,INDEX('QC rev00'!$M$10:$T$120,$F43,7),IF($F$2=2,INDEX(#REF!,$F43,7),INDEX(#REF!,$F43,7))))} | M41: {=IF($F41>$E$2,"",IF($F$2=1,INDEX('QC rev00'!$M$10:$T$120,$F43,8),IF($F$2=2,INDEX(#REF!,$F43,8),INDEX(#REF!,$F43,8))))} | N41: {=IF($F41>$E$2,0,IF(_xlfn.IFNA(MATCH($G41,Listas!$E$4:$E$206,),0)>0,$F$5,IF($F$2=1,INDEX('QC rev00'!$M$10:$U$120,$F43,9),IF($F$2=2,INDEX(#REF!,$F43,9),INDEX(#REF!,$F43,9)))))} -> 0 | O41: {=IF($F41>$E$2,0,IF(_xlfn.IFNA(MATCH($G41,Listas!$E$4:$E$206,),0)>0,1,IF($H$10=0,0,IF($F$2=1,INDEX('QC rev00'!$M$10:$BC$120,$F43,9+$F$3),IF($F$2=2,INDEX(#REF!,$F43,9+$F$3),INDEX(#REF!,$F43,9+$F$3)))*IF($E$5="X",1,1-$B43-$C43))))} -> 0 | P41: =N41*O41 -> 0 | Q41: IP | R41: {=IF($D41=0,"",IF($G41=$E$6,INDEX(Orçamento!$U:$U,MATCH(R$21,Orçamento!$C:$C,),1),INDEX(Orçamento!$U:$U,$B41,1)))} | S41: =IF(S$21>$D41,"",IF($G41=$E$6,INDEX(Orçamento!$U:$U,MATCH(S$21,Orçamento!$C:$C,),1),INDEX(Orçamento!$U:$U,MATCH(S$21&"-"&$F42,Orçamento!$F:$F,),1))) | T41: =IF(T$21>$D41,"",IF($G41=$E$6,INDEX(Orçamento!$U:$U,MATCH(T$21,Orçamento!$C:$C,),1),INDEX(Orçamento!$U:$U,MATCH(T$21&"-"&$F42,Orçamento!$F:$F,),1))) | U41: =IF(U$21>$D41,"",IF($G41=$E$6,INDEX(Orçamento!$U:$U,MATCH(U$21,Orçamento!$C:$C,),1),INDEX(Orçamento!$U:$U,MATCH(U$21&"-"&$F42,Orçamento!$F:$F,),1))) | V41: =IF(V$21>$D41,"",IF($G41=$E$6,INDEX(Orçamento!$U:$U,MATCH(V$21,Orçamento!$C:$C,),1),INDEX(Orçamento!$U:$U,MATCH(V$21&"-"&$F42,Orçamento!$F:$F,),1))) | W41: =IF(W$21>$D41,"",IF($G41=$E$6,INDEX(Orçamento!$U:$U,MATCH(W$21,Orçamento!$C:$C,),1),INDEX(Orçamento!$U:$U,MATCH(W$21&"-"&$F42,Orçamento!$F:$F,),1))) | X41: =IF(X$21>$D41,"",IF($G41=$E$6,INDEX(Orçamento!$U:$U,MATCH(X$21,Orçamento!$C:$C,),1),INDEX(Orçamento!$U:$U,MATCH(X$21&"-"&$F42,Orçamento!$F:$F,),1))) | Y41: =IF(Y$21>$D41,"",IF($G41=$E$6,INDEX(Orçamento!$U:$U,MATCH(Y$21,Orçamento!$C:$C,),1),INDEX(Orçamento!$U:$U,MATCH(Y$21&"-"&$F42,Orçamento!$F:$F,),1))) | Z41: =IF(Z$21>$D41,"",IF($G41=$E$6,INDEX(Orçamento!$U:$U,MATCH(Z$21,Orçamento!$C:$C,),1),INDEX(Orçamento!$U:$U,MATCH(Z$21&"-"&$F42,Orçamento!$F:$F,),1))) | ... AK41: =IF(AK$21>$D41,"",IF($G41=$E$6,INDEX(Orçamento!$U:$U,MATCH(AK$21,Orçamento!$C:$C,),1),INDEX(Orçamento!$U:$U,MATCH(AK$21&"-"&$F42,Orçamento!$F:$F,),1)))
B42: =IF($F41>$E$2,0,(1/(1-B43-C43))*(B43+C43)) -> 0 | C42: {=IF(ROUND(SUM(IF(R41:AK41<>"",(R42:AK42)))-N41,3)<>0,"X",0)} -> 0 | E42: {=IF($F41>$E$2,"",INDEX('QC rev00'!$J$9:$J$120,1+E41,1))} | F42: {=IF($F41>$E$2,"",IF($F$2=1,INDEX('QC rev00'!$M$10:$T$120,$F43,1),IF($F$2=2,INDEX(#REF!,$F43,1),INDEX(#REF!,$F43,1))))} | Q42: Qtd | R42: {=IF(OR($D41=0,R41="",$N41=0),"", IF($G41=$E$6, SUM(IF(OFFSET($R$23,,,($F41-1)*3-2,$D$3)=R41,OFFSET($R$25,,,($F41-1)*3-2,$D$3)*OFFSET($B$23,1,,($F41-1)*3-2,1))), IF($D41=1,$N41, SUMIF(OFFSET(Orçamento!$D$1,$B41-1,,$C41,),$F42&"-"&R41,OFFSET(Orçamento!$I$1,$B41-1,,$C41,))*$N41/$E42)))} | S42: {=IF(OR($D41=0,S41="",$N41=0),"", IF($G41=$E$6, SUM(IF(OFFSET($R$23,,,($F41-1)*3-2,$D$3)=S41,OFFSET($R$25,,,($F41-1)*3-2,$D$3)*OFFSET($B$23,1,,($F41-1)*3-2,1))), IF($D41=1,$N41, SUMIF(OFFSET(Orçamento!$D$1,$B41-1,,$C41,),$F42&"-"&S41,OFFSET(Orçamento!$I$1,$B41-1,,$C41,))*$N41/$E42)))} | T42: {=IF(OR($D41=0,T41="",$N41=0),"", IF($G41=$E$6, SUM(IF(OFFSET($R$23,,,($F41-1)*3-2,$D$3)=T41,OFFSET($R$25,,,($F41-1)*3-2,$D$3)*OFFSET($B$23,1,,($F41-1)*3-2,1))), IF($D41=1,$N41, SUMIF(OFFSET(Orçamento!$D$1,$B41-1,,$C41,),$F42&"-"&T41,OFFSET(Orçamento!$I$1,$B41-1,,$C41,))*$N41/$E42)))} | U42: {=IF(OR($D41=0,U41="",$N41=0),"", IF($G41=$E$6, SUM(IF(OFFSET($R$23,,,($F41-1)*3-2,$D$3)=U41,OFFSET($R$25,,,($F41-1)*3-2,$D$3)*OFFSET($B$23,1,,($F41-1)*3-2,1))), IF($D41=1,$N41, SUMIF(OFFSET(Orçamento!$D$1,$B41-1,,$C41,),$F42&"-"&U41,OFFSET(Orçamento!$I$1,$B41-1,,$C41,))*$N41/$E42)))} | V42: {=IF(OR($D41=0,V41="",$N41=0),"", IF($G41=$E$6, SUM(IF(OFFSET($R$23,,,($F41-1)*3-2,$D$3)=V41,OFFSET($R$25,,,($F41-1)*3-2,$D$3)*OFFSET($B$23,1,,($F41-1)*3-2,1))), IF($D41=1,$N41, SUMIF(OFFSET(Orçamento!$D$1,$B41-1,,$C41,),$F42&"-"&V41,OFFSET(Orçamento!$I$1,$B41-1,,$C41,))*$N41/$E42)))} | W42: {=IF(OR($D41=0,W41="",$N41=0),"", IF($G41=$E$6, SUM(IF(OFFSET($R$23,,,($F41-1)*3-2,$D$3)=W41,OFFSET($R$25,,,($F41-1)*3-2,$D$3)*OFFSET($B$23,1,,($F41-1)*3-2,1))), IF($D41=1,$N41, SUMIF(OFFSET(Orçamento!$D$1,$B41-1,,$C41,),$F42&"-"&W41,OFFSET(Orçamento!$I$1,$B41-1,,$C41,))*$N41/$E42)))} | X42: {=IF(OR($D41=0,X41="",$N41=0),"", IF($G41=$E$6, SUM(IF(OFFSET($R$23,,,($F41-1)*3-2,$D$3)=X41,OFFSET($R$25,,,($F41-1)*3-2,$D$3)*OFFSET($B$23,1,,($F41-1)*3-2,1))), IF($D41=1,$N41, SUMIF(OFFSET(Orçamento!$D$1,$B41-1,,$C41,),$F42&"-"&X41,OFFSET(Orçamento!$I$1,$B41-1,,$C41,))*$N41/$E42)))} | Y42: {=IF(OR($D41=0,Y41="",$N41=0),"", IF($G41=$E$6, SUM(IF(OFFSET($R$23,,,($F41-1)*3-2,$D$3)=Y41,OFFSET($R$25,,,($F41-1)*3-2,$D$3)*OFFSET($B$23,1,,($F41-1)*3-2,1))), IF($D41=1,$N41, SUMIF(OFFSET(Orçamento!$D$1,$B41-1,,$C41,),$F42&"-"&Y41,OFFSET(Orçamento!$I$1,$B41-1,,$C41,))*$N41/$E42)))} | ... AK42: {=IF(OR($D41=0,AK41="",$N41=0),"", IF($G41=$E$6, SUM(IF(OFFSET($R$23,,,($F41-1)*3-2,$D$3)=AK41,OFFSET($R$25,,,($F41-1)*3-2,$D$3)*OFFSET($B$23,1,,($F41-1)*3-2,1))), IF($D41=1,$N41, SUMIF(OFFSET(Orçamento!$D$1,$B41-1,,$C41,),$F42&"-"&AK41,OFFSET(Orçamento!$I$1,$B41-1,,$C41,))*$N41/$E42)))}
B43: {=IF($F41>$E$2,"",IF($F$2=1,INDEX('QC rev00'!$M$10:$T$120,$F43,5),IF($F$2=2,INDEX(#REF!,$F43,5),INDEX(#REF!,$F43,5))))} | C43: {=IF($F41>$E$2,"",IF($F$2=1,INDEX('QC rev00'!$M$10:$T$120,$F43,6),IF($F$2=2,INDEX(#REF!,$F43,6),INDEX(#REF!,$F43,6))))} | F43: =IF(F41>$E$2,"",MATCH(F41,'QC rev00'!$C$10:$C$120,)) | Q43: Valor | R43: =IFERROR(R42*$O41,0) -> 0 | S43: =IFERROR(S42*$O41,0) -> 0 | T43: =IFERROR(T42*$O41,0) -> 0 | U43: =IFERROR(U42*$O41,0) -> 0 | V43: =IFERROR(V42*$O41,0) -> 0 | W43: =IFERROR(W42*$O41,0) -> 0 | X43: =IFERROR(X42*$O41,0) -> 0 | Y43: =IFERROR(Y42*$O41,0) -> 0 | ... AK43: =IFERROR(AK42*$O41,0) -> 0
B44: =IF($F44>$E$2,0,IF(E44<>"",MATCH(F45&" - Mapa",Orçamento!J:J,),0)) -> 0 | C44: =IF($D44>1,_xlfn.MAXIFS(Orçamento!G:G,Orçamento!J:J,F45&" - Mapa")+6-B44,0) -> 0 | D44: =IF($F44>$E$2,0,IF($G44=$E$6,$D$2,IF(E44<>"",_xlfn.MAXIFS(Orçamento!E:E,Orçamento!J:J,F45&" - Mapa"),0))) -> 0 | E44: =IF(F45="","",_xlfn.IFNA(MATCH($F45,'QC rev00'!$G$10:$G$120,),"")) | F44: {=OFFSET(F44,-3,,,)+1} -> 8 | G44: {=IF($F44>$E$2,"",IF($F$2=1,INDEX('QC rev00'!$M$10:$T$120,$F46,2),IF($F$2=2,INDEX(#REF!,$F46,2),INDEX(#REF!,$F46,2))))} | H44: {=IF($F44>$E$2,"",IF($F$2=1,INDEX('QC rev00'!$M$10:$T$120,$F46,3),IF($F$2=2,INDEX(#REF!,$F46,3),INDEX(#REF!,$F46,3))))} | L44: {=IF($F44>$E$2,"",IF($F$2=1,INDEX('QC rev00'!$M$10:$T$120,$F46,7),IF($F$2=2,INDEX(#REF!,$F46,7),INDEX(#REF!,$F46,7))))} | M44: {=IF($F44>$E$2,"",IF($F$2=1,INDEX('QC rev00'!$M$10:$T$120,$F46,8),IF($F$2=2,INDEX(#REF!,$F46,8),INDEX(#REF!,$F46,8))))} | N44: {=IF($F44>$E$2,0,IF(_xlfn.IFNA(MATCH($G44,Listas!$E$4:$E$206,),0)>0,$F$5,IF($F$2=1,INDEX('QC rev00'!$M$10:$U$120,$F46,9),IF($F$2=2,INDEX(#REF!,$F46,9),INDEX(#REF!,$F46,9)))))} -> 0 | O44: {=IF($F44>$E$2,0,IF(_xlfn.IFNA(MATCH($G44,Listas!$E$4:$E$206,),0)>0,1,IF($H$10=0,0,IF($F$2=1,INDEX('QC rev00'!$M$10:$BC$120,$F46,9+$F$3),IF($F$2=2,INDEX(#REF!,$F46,9+$F$3),INDEX(#REF!,$F46,9+$F$3)))*IF($E$5="X",1,1-$B46-$C46))))} -> 0 | P44: =N44*O44 -> 0 | Q44: IP | R44: {=IF($D44=0,"",IF($G44=$E$6,INDEX(Orçamento!$U:$U,MATCH(R$21,Orçamento!$C:$C,),1),INDEX(Orçamento!$U:$U,$B44,1)))} | S44: =IF(S$21>$D44,"",IF($G44=$E$6,INDEX(Orçamento!$U:$U,MATCH(S$21,Orçamento!$C:$C,),1),INDEX(Orçamento!$U:$U,MATCH(S$21&"-"&$F45,Orçamento!$F:$F,),1))) | T44: =IF(T$21>$D44,"",IF($G44=$E$6,INDEX(Orçamento!$U:$U,MATCH(T$21,Orçamento!$C:$C,),1),INDEX(Orçamento!$U:$U,MATCH(T$21&"-"&$F45,Orçamento!$F:$F,),1))) | U44: =IF(U$21>$D44,"",IF($G44=$E$6,INDEX(Orçamento!$U:$U,MATCH(U$21,Orçamento!$C:$C,),1),INDEX(Orçamento!$U:$U,MATCH(U$21&"-"&$F45,Orçamento!$F:$F,),1))) | V44: =IF(V$21>$D44,"",IF($G44=$E$6,INDEX(Orçamento!$U:$U,MATCH(V$21,Orçamento!$C:$C,),1),INDEX(Orçamento!$U:$U,MATCH(V$21&"-"&$F45,Orçamento!$F:$F,),1))) | W44: =IF(W$21>$D44,"",IF($G44=$E$6,INDEX(Orçamento!$U:$U,MATCH(W$21,Orçamento!$C:$C,),1),INDEX(Orçamento!$U:$U,MATCH(W$21&"-"&$F45,Orçamento!$F:$F,),1))) | X44: =IF(X$21>$D44,"",IF($G44=$E$6,INDEX(Orçamento!$U:$U,MATCH(X$21,Orçamento!$C:$C,),1),INDEX(Orçamento!$U:$U,MATCH(X$21&"-"&$F45,Orçamento!$F:$F,),1))) | Y44: =IF(Y$21>$D44,"",IF($G44=$E$6,INDEX(Orçamento!$U:$U,MATCH(Y$21,Orçamento!$C:$C,),1),INDEX(Orçamento!$U:$U,MATCH(Y$21&"-"&$F45,Orçamento!$F:$F,),1))) | Z44: =IF(Z$21>$D44,"",IF($G44=$E$6,INDEX(Orçamento!$U:$U,MATCH(Z$21,Orçamento!$C:$C,),1),INDEX(Orçamento!$U:$U,MATCH(Z$21&"-"&$F45,Orçamento!$F:$F,),1))) | ... AK44: =IF(AK$21>$D44,"",IF($G44=$E$6,INDEX(Orçamento!$U:$U,MATCH(AK$21,Orçamento!$C:$C,),1),INDEX(Orçamento!$U:$U,MATCH(AK$21&"-"&$F45,Orçamento!$F:$F,),1)))
B45: =IF($F44>$E$2,0,(1/(1-B46-C46))*(B46+C46)) -> 0 | C45: {=IF(ROUND(SUM(IF(R44:AK44<>"",(R45:AK45)))-N44,3)<>0,"X",0)} -> 0 | E45: {=IF($F44>$E$2,"",INDEX('QC rev00'!$J$9:$J$120,1+E44,1))} | F45: {=IF($F44>$E$2,"",IF($F$2=1,INDEX('QC rev00'!$M$10:$T$120,$F46,1),IF($F$2=2,INDEX(#REF!,$F46,1),INDEX(#REF!,$F46,1))))} | Q45: Qtd | R45: {=IF(OR($D44=0,R44="",$N44=0),"", IF($G44=$E$6, SUM(IF(OFFSET($R$23,,,($F44-1)*3-2,$D$3)=R44,OFFSET($R$25,,,($F44-1)*3-2,$D$3)*OFFSET($B$23,1,,($F44-1)*3-2,1))), IF($D44=1,$N44, SUMIF(OFFSET(Orçamento!$D$1,$B44-1,,$C44,),$F45&"-"&R44,OFFSET(Orçamento!$I$1,$B44-1,,$C44,))*$N44/$E45)))} | S45: {=IF(OR($D44=0,S44="",$N44=0),"", IF($G44=$E$6, SUM(IF(OFFSET($R$23,,,($F44-1)*3-2,$D$3)=S44,OFFSET($R$25,,,($F44-1)*3-2,$D$3)*OFFSET($B$23,1,,($F44-1)*3-2,1))), IF($D44=1,$N44, SUMIF(OFFSET(Orçamento!$D$1,$B44-1,,$C44,),$F45&"-"&S44,OFFSET(Orçamento!$I$1,$B44-1,,$C44,))*$N44/$E45)))} | T45: {=IF(OR($D44=0,T44="",$N44=0),"", IF($G44=$E$6, SUM(IF(OFFSET($R$23,,,($F44-1)*3-2,$D$3)=T44,OFFSET($R$25,,,($F44-1)*3-2,$D$3)*OFFSET($B$23,1,,($F44-1)*3-2,1))), IF($D44=1,$N44, SUMIF(OFFSET(Orçamento!$D$1,$B44-1,,$C44,),$F45&"-"&T44,OFFSET(Orçamento!$I$1,$B44-1,,$C44,))*$N44/$E45)))} | U45: {=IF(OR($D44=0,U44="",$N44=0),"", IF($G44=$E$6, SUM(IF(OFFSET($R$23,,,($F44-1)*3-2,$D$3)=U44,OFFSET($R$25,,,($F44-1)*3-2,$D$3)*OFFSET($B$23,1,,($F44-1)*3-2,1))), IF($D44=1,$N44, SUMIF(OFFSET(Orçamento!$D$1,$B44-1,,$C44,),$F45&"-"&U44,OFFSET(Orçamento!$I$1,$B44-1,,$C44,))*$N44/$E45)))} | V45: {=IF(OR($D44=0,V44="",$N44=0),"", IF($G44=$E$6, SUM(IF(OFFSET($R$23,,,($F44-1)*3-2,$D$3)=V44,OFFSET($R$25,,,($F44-1)*3-2,$D$3)*OFFSET($B$23,1,,($F44-1)*3-2,1))), IF($D44=1,$N44, SUMIF(OFFSET(Orçamento!$D$1,$B44-1,,$C44,),$F45&"-"&V44,OFFSET(Orçamento!$I$1,$B44-1,,$C44,))*$N44/$E45)))} | W45: {=IF(OR($D44=0,W44="",$N44=0),"", IF($G44=$E$6, SUM(IF(OFFSET($R$23,,,($F44-1)*3-2,$D$3)=W44,OFFSET($R$25,,,($F44-1)*3-2,$D$3)*OFFSET($B$23,1,,($F44-1)*3-2,1))), IF($D44=1,$N44, SUMIF(OFFSET(Orçamento!$D$1,$B44-1,,$C44,),$F45&"-"&W44,OFFSET(Orçamento!$I$1,$B44-1,,$C44,))*$N44/$E45)))} | X45: {=IF(OR($D44=0,X44="",$N44=0),"", IF($G44=$E$6, SUM(IF(OFFSET($R$23,,,($F44-1)*3-2,$D$3)=X44,OFFSET($R$25,,,($F44-1)*3-2,$D$3)*OFFSET($B$23,1,,($F44-1)*3-2,1))), IF($D44=1,$N44, SUMIF(OFFSET(Orçamento!$D$1,$B44-1,,$C44,),$F45&"-"&X44,OFFSET(Orçamento!$I$1,$B44-1,,$C44,))*$N44/$E45)))} | Y45: {=IF(OR($D44=0,Y44="",$N44=0),"", IF($G44=$E$6, SUM(IF(OFFSET($R$23,,,($F44-1)*3-2,$D$3)=Y44,OFFSET($R$25,,,($F44-1)*3-2,$D$3)*OFFSET($B$23,1,,($F44-1)*3-2,1))), IF($D44=1,$N44, SUMIF(OFFSET(Orçamento!$D$1,$B44-1,,$C44,),$F45&"-"&Y44,OFFSET(Orçamento!$I$1,$B44-1,,$C44,))*$N44/$E45)))} | ... AK45: {=IF(OR($D44=0,AK44="",$N44=0),"", IF($G44=$E$6, SUM(IF(OFFSET($R$23,,,($F44-1)*3-2,$D$3)=AK44,OFFSET($R$25,,,($F44-1)*3-2,$D$3)*OFFSET($B$23,1,,($F44-1)*3-2,1))), IF($D44=1,$N44, SUMIF(OFFSET(Orçamento!$D$1,$B44-1,,$C44,),$F45&"-"&AK44,OFFSET(Orçamento!$I$1,$B44-1,,$C44,))*$N44/$E45)))}
B46: {=IF($F44>$E$2,"",IF($F$2=1,INDEX('QC rev00'!$M$10:$T$120,$F46,5),IF($F$2=2,INDEX(#REF!,$F46,5),INDEX(#REF!,$F46,5))))} | C46: {=IF($F44>$E$2,"",IF($F$2=1,INDEX('QC rev00'!$M$10:$T$120,$F46,6),IF($F$2=2,INDEX(#REF!,$F46,6),INDEX(#REF!,$F46,6))))} | F46: =IF(F44>$E$2,"",MATCH(F44,'QC rev00'!$C$10:$C$120,)) | Q46: Valor | R46: =IFERROR(R45*$O44,0) -> 0 | S46: =IFERROR(S45*$O44,0) -> 0 | T46: =IFERROR(T45*$O44,0) -> 0 | U46: =IFERROR(U45*$O44,0) -> 0 | V46: =IFERROR(V45*$O44,0) -> 0 | W46: =IFERROR(W45*$O44,0) -> 0 | X46: =IFERROR(X45*$O44,0) -> 0 | Y46: =IFERROR(Y45*$O44,0) -> 0 | ... AK46: =IFERROR(AK45*$O44,0) -> 0
B47: =IF($F47>$E$2,0,IF(E47<>"",MATCH(F48&" - Mapa",Orçamento!J:J,),0)) -> 0 | C47: =IF($D47>1,_xlfn.MAXIFS(Orçamento!G:G,Orçamento!J:J,F48&" - Mapa")+6-B47,0) -> 0 | D47: =IF($F47>$E$2,0,IF($G47=$E$6,$D$2,IF(E47<>"",_xlfn.MAXIFS(Orçamento!E:E,Orçamento!J:J,F48&" - Mapa"),0))) -> 0 | E47: =IF(F48="","",_xlfn.IFNA(MATCH($F48,'QC rev00'!$G$10:$G$120,),"")) | F47: {=OFFSET(F47,-3,,,)+1} -> 9 | G47: {=IF($F47>$E$2,"",IF($F$2=1,INDEX('QC rev00'!$M$10:$T$120,$F49,2),IF($F$2=2,INDEX(#REF!,$F49,2),INDEX(#REF!,$F49,2))))} | H47: {=IF($F47>$E$2,"",IF($F$2=1,INDEX('QC rev00'!$M$10:$T$120,$F49,3),IF($F$2=2,INDEX(#REF!,$F49,3),INDEX(#REF!,$F49,3))))} | L47: {=IF($F47>$E$2,"",IF($F$2=1,INDEX('QC rev00'!$M$10:$T$120,$F49,7),IF($F$2=2,INDEX(#REF!,$F49,7),INDEX(#REF!,$F49,7))))} | M47: {=IF($F47>$E$2,"",IF($F$2=1,INDEX('QC rev00'!$M$10:$T$120,$F49,8),IF($F$2=2,INDEX(#REF!,$F49,8),INDEX(#REF!,$F49,8))))} | N47: {=IF($F47>$E$2,0,IF(_xlfn.IFNA(MATCH($G47,Listas!$E$4:$E$206,),0)>0,$F$5,IF($F$2=1,INDEX('QC rev00'!$M$10:$U$120,$F49,9),IF($F$2=2,INDEX(#REF!,$F49,9),INDEX(#REF!,$F49,9)))))} -> 0 | O47: {=IF($F47>$E$2,0,IF(_xlfn.IFNA(MATCH($G47,Listas!$E$4:$E$206,),0)>0,1,IF($H$10=0,0,IF($F$2=1,INDEX('QC rev00'!$M$10:$BC$120,$F49,9+$F$3),IF($F$2=2,INDEX(#REF!,$F49,9+$F$3),INDEX(#REF!,$F49,9+$F$3)))*IF($E$5="X",1,1-$B49-$C49))))} -> 0 | P47: =N47*O47 -> 0 | Q47: IP | R47: {=IF($D47=0,"",IF($G47=$E$6,INDEX(Orçamento!$U:$U,MATCH(R$21,Orçamento!$C:$C,),1),INDEX(Orçamento!$U:$U,$B47,1)))} | S47: =IF(S$21>$D47,"",IF($G47=$E$6,INDEX(Orçamento!$U:$U,MATCH(S$21,Orçamento!$C:$C,),1),INDEX(Orçamento!$U:$U,MATCH(S$21&"-"&$F48,Orçamento!$F:$F,),1))) | T47: =IF(T$21>$D47,"",IF($G47=$E$6,INDEX(Orçamento!$U:$U,MATCH(T$21,Orçamento!$C:$C,),1),INDEX(Orçamento!$U:$U,MATCH(T$21&"-"&$F48,Orçamento!$F:$F,),1))) | U47: =IF(U$21>$D47,"",IF($G47=$E$6,INDEX(Orçamento!$U:$U,MATCH(U$21,Orçamento!$C:$C,),1),INDEX(Orçamento!$U:$U,MATCH(U$21&"-"&$F48,Orçamento!$F:$F,),1))) | V47: =IF(V$21>$D47,"",IF($G47=$E$6,INDEX(Orçamento!$U:$U,MATCH(V$21,Orçamento!$C:$C,),1),INDEX(Orçamento!$U:$U,MATCH(V$21&"-"&$F48,Orçamento!$F:$F,),1))) | W47: =IF(W$21>$D47,"",IF($G47=$E$6,INDEX(Orçamento!$U:$U,MATCH(W$21,Orçamento!$C:$C,),1),INDEX(Orçamento!$U:$U,MATCH(W$21&"-"&$F48,Orçamento!$F:$F,),1))) | X47: =IF(X$21>$D47,"",IF($G47=$E$6,INDEX(Orçamento!$U:$U,MATCH(X$21,Orçamento!$C:$C,),1),INDEX(Orçamento!$U:$U,MATCH(X$21&"-"&$F48,Orçamento!$F:$F,),1))) | Y47: =IF(Y$21>$D47,"",IF($G47=$E$6,INDEX(Orçamento!$U:$U,MATCH(Y$21,Orçamento!$C:$C,),1),INDEX(Orçamento!$U:$U,MATCH(Y$21&"-"&$F48,Orçamento!$F:$F,),1))) | Z47: =IF(Z$21>$D47,"",IF($G47=$E$6,INDEX(Orçamento!$U:$U,MATCH(Z$21,Orçamento!$C:$C,),1),INDEX(Orçamento!$U:$U,MATCH(Z$21&"-"&$F48,Orçamento!$F:$F,),1))) | ... AK47: =IF(AK$21>$D47,"",IF($G47=$E$6,INDEX(Orçamento!$U:$U,MATCH(AK$21,Orçamento!$C:$C,),1),INDEX(Orçamento!$U:$U,MATCH(AK$21&"-"&$F48,Orçamento!$F:$F,),1)))
B48: =IF($F47>$E$2,0,(1/(1-B49-C49))*(B49+C49)) -> 0 | C48: {=IF(ROUND(SUM(IF(R47:AK47<>"",(R48:AK48)))-N47,3)<>0,"X",0)} -> 0 | E48: {=IF($F47>$E$2,"",INDEX('QC rev00'!$J$9:$J$120,1+E47,1))} | F48: {=IF($F47>$E$2,"",IF($F$2=1,INDEX('QC rev00'!$M$10:$T$120,$F49,1),IF($F$2=2,INDEX(#REF!,$F49,1),INDEX(#REF!,$F49,1))))} | Q48: Qtd | R48: {=IF(OR($D47=0,R47="",$N47=0),"", IF($G47=$E$6, SUM(IF(OFFSET($R$23,,,($F47-1)*3-2,$D$3)=R47,OFFSET($R$25,,,($F47-1)*3-2,$D$3)*OFFSET($B$23,1,,($F47-1)*3-2,1))), IF($D47=1,$N47, SUMIF(OFFSET(Orçamento!$D$1,$B47-1,,$C47,),$F48&"-"&R47,OFFSET(Orçamento!$I$1,$B47-1,,$C47,))*$N47/$E48)))} | S48: {=IF(OR($D47=0,S47="",$N47=0),"", IF($G47=$E$6, SUM(IF(OFFSET($R$23,,,($F47-1)*3-2,$D$3)=S47,OFFSET($R$25,,,($F47-1)*3-2,$D$3)*OFFSET($B$23,1,,($F47-1)*3-2,1))), IF($D47=1,$N47, SUMIF(OFFSET(Orçamento!$D$1,$B47-1,,$C47,),$F48&"-"&S47,OFFSET(Orçamento!$I$1,$B47-1,,$C47,))*$N47/$E48)))} | T48: {=IF(OR($D47=0,T47="",$N47=0),"", IF($G47=$E$6, SUM(IF(OFFSET($R$23,,,($F47-1)*3-2,$D$3)=T47,OFFSET($R$25,,,($F47-1)*3-2,$D$3)*OFFSET($B$23,1,,($F47-1)*3-2,1))), IF($D47=1,$N47, SUMIF(OFFSET(Orçamento!$D$1,$B47-1,,$C47,),$F48&"-"&T47,OFFSET(Orçamento!$I$1,$B47-1,,$C47,))*$N47/$E48)))} | U48: {=IF(OR($D47=0,U47="",$N47=0),"", IF($G47=$E$6, SUM(IF(OFFSET($R$23,,,($F47-1)*3-2,$D$3)=U47,OFFSET($R$25,,,($F47-1)*3-2,$D$3)*OFFSET($B$23,1,,($F47-1)*3-2,1))), IF($D47=1,$N47, SUMIF(OFFSET(Orçamento!$D$1,$B47-1,,$C47,),$F48&"-"&U47,OFFSET(Orçamento!$I$1,$B47-1,,$C47,))*$N47/$E48)))} | V48: {=IF(OR($D47=0,V47="",$N47=0),"", IF($G47=$E$6, SUM(IF(OFFSET($R$23,,,($F47-1)*3-2,$D$3)=V47,OFFSET($R$25,,,($F47-1)*3-2,$D$3)*OFFSET($B$23,1,,($F47-1)*3-2,1))), IF($D47=1,$N47, SUMIF(OFFSET(Orçamento!$D$1,$B47-1,,$C47,),$F48&"-"&V47,OFFSET(Orçamento!$I$1,$B47-1,,$C47,))*$N47/$E48)))} | W48: {=IF(OR($D47=0,W47="",$N47=0),"", IF($G47=$E$6, SUM(IF(OFFSET($R$23,,,($F47-1)*3-2,$D$3)=W47,OFFSET($R$25,,,($F47-1)*3-2,$D$3)*OFFSET($B$23,1,,($F47-1)*3-2,1))), IF($D47=1,$N47, SUMIF(OFFSET(Orçamento!$D$1,$B47-1,,$C47,),$F48&"-"&W47,OFFSET(Orçamento!$I$1,$B47-1,,$C47,))*$N47/$E48)))} | X48: {=IF(OR($D47=0,X47="",$N47=0),"", IF($G47=$E$6, SUM(IF(OFFSET($R$23,,,($F47-1)*3-2,$D$3)=X47,OFFSET($R$25,,,($F47-1)*3-2,$D$3)*OFFSET($B$23,1,,($F47-1)*3-2,1))), IF($D47=1,$N47, SUMIF(OFFSET(Orçamento!$D$1,$B47-1,,$C47,),$F48&"-"&X47,OFFSET(Orçamento!$I$1,$B47-1,,$C47,))*$N47/$E48)))} | Y48: {=IF(OR($D47=0,Y47="",$N47=0),"", IF($G47=$E$6, SUM(IF(OFFSET($R$23,,,($F47-1)*3-2,$D$3)=Y47,OFFSET($R$25,,,($F47-1)*3-2,$D$3)*OFFSET($B$23,1,,($F47-1)*3-2,1))), IF($D47=1,$N47, SUMIF(OFFSET(Orçamento!$D$1,$B47-1,,$C47,),$F48&"-"&Y47,OFFSET(Orçamento!$I$1,$B47-1,,$C47,))*$N47/$E48)))} | ... AK48: {=IF(OR($D47=0,AK47="",$N47=0),"", IF($G47=$E$6, SUM(IF(OFFSET($R$23,,,($F47-1)*3-2,$D$3)=AK47,OFFSET($R$25,,,($F47-1)*3-2,$D$3)*OFFSET($B$23,1,,($F47-1)*3-2,1))), IF($D47=1,$N47, SUMIF(OFFSET(Orçamento!$D$1,$B47-1,,$C47,),$F48&"-"&AK47,OFFSET(Orçamento!$I$1,$B47-1,,$C47,))*$N47/$E48)))}
B49: {=IF($F47>$E$2,"",IF($F$2=1,INDEX('QC rev00'!$M$10:$T$120,$F49,5),IF($F$2=2,INDEX(#REF!,$F49,5),INDEX(#REF!,$F49,5))))} | C49: {=IF($F47>$E$2,"",IF($F$2=1,INDEX('QC rev00'!$M$10:$T$120,$F49,6),IF($F$2=2,INDEX(#REF!,$F49,6),INDEX(#REF!,$F49,6))))} | F49: =IF(F47>$E$2,"",MATCH(F47,'QC rev00'!$C$10:$C$120,)) | Q49: Valor | R49: =IFERROR(R48*$O47,0) -> 0 | S49: =IFERROR(S48*$O47,0) -> 0 | T49: =IFERROR(T48*$O47,0) -> 0 | U49: =IFERROR(U48*$O47,0) -> 0 | V49: =IFERROR(V48*$O47,0) -> 0 | W49: =IFERROR(W48*$O47,0) -> 0 | X49: =IFERROR(X48*$O47,0) -> 0 | Y49: =IFERROR(Y48*$O47,0) -> 0 | ... AK49: =IFERROR(AK48*$O47,0) -> 0
B50: =IF($F50>$E$2,0,IF(E50<>"",MATCH(F51&" - Mapa",Orçamento!J:J,),0)) -> 0 | C50: =IF($D50>1,_xlfn.MAXIFS(Orçamento!G:G,Orçamento!J:J,F51&" - Mapa")+6-B50,0) -> 0 | D50: =IF($F50>$E$2,0,IF($G50=$E$6,$D$2,IF(E50<>"",_xlfn.MAXIFS(Orçamento!E:E,Orçamento!J:J,F51&" - Mapa"),0))) -> 0 | E50: =IF(F51="","",_xlfn.IFNA(MATCH($F51,'QC rev00'!$G$10:$G$120,),"")) | F50: {=OFFSET(F50,-3,,,)+1} -> 10 | G50: {=IF($F50>$E$2,"",IF($F$2=1,INDEX('QC rev00'!$M$10:$T$120,$F52,2),IF($F$2=2,INDEX(#REF!,$F52,2),INDEX(#REF!,$F52,2))))} | H50: {=IF($F50>$E$2,"",IF($F$2=1,INDEX('QC rev00'!$M$10:$T$120,$F52,3),IF($F$2=2,INDEX(#REF!,$F52,3),INDEX(#REF!,$F52,3))))} | L50: {=IF($F50>$E$2,"",IF($F$2=1,INDEX('QC rev00'!$M$10:$T$120,$F52,7),IF($F$2=2,INDEX(#REF!,$F52,7),INDEX(#REF!,$F52,7))))} | M50: {=IF($F50>$E$2,"",IF($F$2=1,INDEX('QC rev00'!$M$10:$T$120,$F52,8),IF($F$2=2,INDEX(#REF!,$F52,8),INDEX(#REF!,$F52,8))))} | N50: {=IF($F50>$E$2,0,IF(_xlfn.IFNA(MATCH($G50,Listas!$E$4:$E$206,),0)>0,$F$5,IF($F$2=1,INDEX('QC rev00'!$M$10:$U$120,$F52,9),IF($F$2=2,INDEX(#REF!,$F52,9),INDEX(#REF!,$F52,9)))))} -> 0 | O50: {=IF($F50>$E$2,0,IF(_xlfn.IFNA(MATCH($G50,Listas!$E$4:$E$206,),0)>0,1,IF($H$10=0,0,IF($F$2=1,INDEX('QC rev00'!$M$10:$BC$120,$F52,9+$F$3),IF($F$2=2,INDEX(#REF!,$F52,9+$F$3),INDEX(#REF!,$F52,9+$F$3)))*IF($E$5="X",1,1-$B52-$C52))))} -> 0 | P50: =N50*O50 -> 0 | Q50: IP | R50: {=IF($D50=0,"",IF($G50=$E$6,INDEX(Orçamento!$U:$U,MATCH(R$21,Orçamento!$C:$C,),1),INDEX(Orçamento!$U:$U,$B50,1)))} | S50: =IF(S$21>$D50,"",IF($G50=$E$6,INDEX(Orçamento!$U:$U,MATCH(S$21,Orçamento!$C:$C,),1),INDEX(Orçamento!$U:$U,MATCH(S$21&"-"&$F51,Orçamento!$F:$F,),1))) | T50: =IF(T$21>$D50,"",IF($G50=$E$6,INDEX(Orçamento!$U:$U,MATCH(T$21,Orçamento!$C:$C,),1),INDEX(Orçamento!$U:$U,MATCH(T$21&"-"&$F51,Orçamento!$F:$F,),1))) | U50: =IF(U$21>$D50,"",IF($G50=$E$6,INDEX(Orçamento!$U:$U,MATCH(U$21,Orçamento!$C:$C,),1),INDEX(Orçamento!$U:$U,MATCH(U$21&"-"&$F51,Orçamento!$F:$F,),1))) | V50: =IF(V$21>$D50,"",IF($G50=$E$6,INDEX(Orçamento!$U:$U,MATCH(V$21,Orçamento!$C:$C,),1),INDEX(Orçamento!$U:$U,MATCH(V$21&"-"&$F51,Orçamento!$F:$F,),1))) | W50: =IF(W$21>$D50,"",IF($G50=$E$6,INDEX(Orçamento!$U:$U,MATCH(W$21,Orçamento!$C:$C,),1),INDEX(Orçamento!$U:$U,MATCH(W$21&"-"&$F51,Orçamento!$F:$F,),1))) | X50: =IF(X$21>$D50,"",IF($G50=$E$6,INDEX(Orçamento!$U:$U,MATCH(X$21,Orçamento!$C:$C,),1),INDEX(Orçamento!$U:$U,MATCH(X$21&"-"&$F51,Orçamento!$F:$F,),1))) | Y50: =IF(Y$21>$D50,"",IF($G50=$E$6,INDEX(Orçamento!$U:$U,MATCH(Y$21,Orçamento!$C:$C,),1),INDEX(Orçamento!$U:$U,MATCH(Y$21&"-"&$F51,Orçamento!$F:$F,),1))) | Z50: =IF(Z$21>$D50,"",IF($G50=$E$6,INDEX(Orçamento!$U:$U,MATCH(Z$21,Orçamento!$C:$C,),1),INDEX(Orçamento!$U:$U,MATCH(Z$21&"-"&$F51,Orçamento!$F:$F,),1))) | ... AK50: =IF(AK$21>$D50,"",IF($G50=$E$6,INDEX(Orçamento!$U:$U,MATCH(AK$21,Orçamento!$C:$C,),1),INDEX(Orçamento!$U:$U,MATCH(AK$21&"-"&$F51,Orçamento!$F:$F,),1)))
B51: =IF($F50>$E$2,0,(1/(1-B52-C52))*(B52+C52)) -> 0 | C51: {=IF(ROUND(SUM(IF(R50:AK50<>"",(R51:AK51)))-N50,3)<>0,"X",0)} -> 0 | E51: {=IF($F50>$E$2,"",INDEX('QC rev00'!$J$9:$J$120,1+E50,1))} | F51: {=IF($F50>$E$2,"",IF($F$2=1,INDEX('QC rev00'!$M$10:$T$120,$F52,1),IF($F$2=2,INDEX(#REF!,$F52,1),INDEX(#REF!,$F52,1))))} | Q51: Qtd | R51: {=IF(OR($D50=0,R50="",$N50=0),"", IF($G50=$E$6, SUM(IF(OFFSET($R$23,,,($F50-1)*3-2,$D$3)=R50,OFFSET($R$25,,,($F50-1)*3-2,$D$3)*OFFSET($B$23,1,,($F50-1)*3-2,1))), IF($D50=1,$N50, SUMIF(OFFSET(Orçamento!$D$1,$B50-1,,$C50,),$F51&"-"&R50,OFFSET(Orçamento!$I$1,$B50-1,,$C50,))*$N50/$E51)))} | S51: {=IF(OR($D50=0,S50="",$N50=0),"", IF($G50=$E$6, SUM(IF(OFFSET($R$23,,,($F50-1)*3-2,$D$3)=S50,OFFSET($R$25,,,($F50-1)*3-2,$D$3)*OFFSET($B$23,1,,($F50-1)*3-2,1))), IF($D50=1,$N50, SUMIF(OFFSET(Orçamento!$D$1,$B50-1,,$C50,),$F51&"-"&S50,OFFSET(Orçamento!$I$1,$B50-1,,$C50,))*$N50/$E51)))} | T51: {=IF(OR($D50=0,T50="",$N50=0),"", IF($G50=$E$6, SUM(IF(OFFSET($R$23,,,($F50-1)*3-2,$D$3)=T50,OFFSET($R$25,,,($F50-1)*3-2,$D$3)*OFFSET($B$23,1,,($F50-1)*3-2,1))), IF($D50=1,$N50, SUMIF(OFFSET(Orçamento!$D$1,$B50-1,,$C50,),$F51&"-"&T50,OFFSET(Orçamento!$I$1,$B50-1,,$C50,))*$N50/$E51)))} | U51: {=IF(OR($D50=0,U50="",$N50=0),"", IF($G50=$E$6, SUM(IF(OFFSET($R$23,,,($F50-1)*3-2,$D$3)=U50,OFFSET($R$25,,,($F50-1)*3-2,$D$3)*OFFSET($B$23,1,,($F50-1)*3-2,1))), IF($D50=1,$N50, SUMIF(OFFSET(Orçamento!$D$1,$B50-1,,$C50,),$F51&"-"&U50,OFFSET(Orçamento!$I$1,$B50-1,,$C50,))*$N50/$E51)))} | V51: {=IF(OR($D50=0,V50="",$N50=0),"", IF($G50=$E$6, SUM(IF(OFFSET($R$23,,,($F50-1)*3-2,$D$3)=V50,OFFSET($R$25,,,($F50-1)*3-2,$D$3)*OFFSET($B$23,1,,($F50-1)*3-2,1))), IF($D50=1,$N50, SUMIF(OFFSET(Orçamento!$D$1,$B50-1,,$C50,),$F51&"-"&V50,OFFSET(Orçamento!$I$1,$B50-1,,$C50,))*$N50/$E51)))} | W51: {=IF(OR($D50=0,W50="",$N50=0),"", IF($G50=$E$6, SUM(IF(OFFSET($R$23,,,($F50-1)*3-2,$D$3)=W50,OFFSET($R$25,,,($F50-1)*3-2,$D$3)*OFFSET($B$23,1,,($F50-1)*3-2,1))), IF($D50=1,$N50, SUMIF(OFFSET(Orçamento!$D$1,$B50-1,,$C50,),$F51&"-"&W50,OFFSET(Orçamento!$I$1,$B50-1,,$C50,))*$N50/$E51)))} | X51: {=IF(OR($D50=0,X50="",$N50=0),"", IF($G50=$E$6, SUM(IF(OFFSET($R$23,,,($F50-1)*3-2,$D$3)=X50,OFFSET($R$25,,,($F50-1)*3-2,$D$3)*OFFSET($B$23,1,,($F50-1)*3-2,1))), IF($D50=1,$N50, SUMIF(OFFSET(Orçamento!$D$1,$B50-1,,$C50,),$F51&"-"&X50,OFFSET(Orçamento!$I$1,$B50-1,,$C50,))*$N50/$E51)))} | Y51: {=IF(OR($D50=0,Y50="",$N50=0),"", IF($G50=$E$6, SUM(IF(OFFSET($R$23,,,($F50-1)*3-2,$D$3)=Y50,OFFSET($R$25,,,($F50-1)*3-2,$D$3)*OFFSET($B$23,1,,($F50-1)*3-2,1))), IF($D50=1,$N50, SUMIF(OFFSET(Orçamento!$D$1,$B50-1,,$C50,),$F51&"-"&Y50,OFFSET(Orçamento!$I$1,$B50-1,,$C50,))*$N50/$E51)))} | ... AK51: {=IF(OR($D50=0,AK50="",$N50=0),"", IF($G50=$E$6, SUM(IF(OFFSET($R$23,,,($F50-1)*3-2,$D$3)=AK50,OFFSET($R$25,,,($F50-1)*3-2,$D$3)*OFFSET($B$23,1,,($F50-1)*3-2,1))), IF($D50=1,$N50, SUMIF(OFFSET(Orçamento!$D$1,$B50-1,,$C50,),$F51&"-"&AK50,OFFSET(Orçamento!$I$1,$B50-1,,$C50,))*$N50/$E51)))}
B52: {=IF($F50>$E$2,"",IF($F$2=1,INDEX('QC rev00'!$M$10:$T$120,$F52,5),IF($F$2=2,INDEX(#REF!,$F52,5),INDEX(#REF!,$F52,5))))} | C52: {=IF($F50>$E$2,"",IF($F$2=1,INDEX('QC rev00'!$M$10:$T$120,$F52,6),IF($F$2=2,INDEX(#REF!,$F52,6),INDEX(#REF!,$F52,6))))} | F52: =IF(F50>$E$2,"",MATCH(F50,'QC rev00'!$C$10:$C$120,)) | Q52: Valor | R52: =IFERROR(R51*$O50,0) -> 0 | S52: =IFERROR(S51*$O50,0) -> 0 | T52: =IFERROR(T51*$O50,0) -> 0 | U52: =IFERROR(U51*$O50,0) -> 0 | V52: =IFERROR(V51*$O50,0) -> 0 | W52: =IFERROR(W51*$O50,0) -> 0 | X52: =IFERROR(X51*$O50,0) -> 0 | Y52: =IFERROR(Y51*$O50,0) -> 0 | ... AK52: =IFERROR(AK51*$O50,0) -> 0
B53: =IF($F53>$E$2,0,IF(E53<>"",MATCH(F54&" - Mapa",Orçamento!J:J,),0)) -> 0 | C53: =IF($D53>1,_xlfn.MAXIFS(Orçamento!G:G,Orçamento!J:J,F54&" - Mapa")+6-B53,0) -> 0 | D53: =IF($F53>$E$2,0,IF($G53=$E$6,$D$2,IF(E53<>"",_xlfn.MAXIFS(Orçamento!E:E,Orçamento!J:J,F54&" - Mapa"),0))) -> 0 | E53: =IF(F54="","",_xlfn.IFNA(MATCH($F54,'QC rev00'!$G$10:$G$120,),"")) | F53: {=OFFSET(F53,-3,,,)+1} -> 11 | G53: {=IF($F53>$E$2,"",IF($F$2=1,INDEX('QC rev00'!$M$10:$T$120,$F55,2),IF($F$2=2,INDEX(#REF!,$F55,2),INDEX(#REF!,$F55,2))))} | H53: {=IF($F53>$E$2,"",IF($F$2=1,INDEX('QC rev00'!$M$10:$T$120,$F55,3),IF($F$2=2,INDEX(#REF!,$F55,3),INDEX(#REF!,$F55,3))))} | L53: {=IF($F53>$E$2,"",IF($F$2=1,INDEX('QC rev00'!$M$10:$T$120,$F55,7),IF($F$2=2,INDEX(#REF!,$F55,7),INDEX(#REF!,$F55,7))))} | M53: {=IF($F53>$E$2,"",IF($F$2=1,INDEX('QC rev00'!$M$10:$T$120,$F55,8),IF($F$2=2,INDEX(#REF!,$F55,8),INDEX(#REF!,$F55,8))))} | N53: {=IF($F53>$E$2,0,IF(_xlfn.IFNA(MATCH($G53,Listas!$E$4:$E$206,),0)>0,$F$5,IF($F$2=1,INDEX('QC rev00'!$M$10:$U$120,$F55,9),IF($F$2=2,INDEX(#REF!,$F55,9),INDEX(#REF!,$F55,9)))))} -> 0 | O53: {=IF($F53>$E$2,0,IF(_xlfn.IFNA(MATCH($G53,Listas!$E$4:$E$206,),0)>0,1,IF($H$10=0,0,IF($F$2=1,INDEX('QC rev00'!$M$10:$BC$120,$F55,9+$F$3),IF($F$2=2,INDEX(#REF!,$F55,9+$F$3),INDEX(#REF!,$F55,9+$F$3)))*IF($E$5="X",1,1-$B55-$C55))))} -> 0 | P53: =N53*O53 -> 0 | Q53: IP | R53: {=IF($D53=0,"",IF($G53=$E$6,INDEX(Orçamento!$U:$U,MATCH(R$21,Orçamento!$C:$C,),1),INDEX(Orçamento!$U:$U,$B53,1)))} | S53: =IF(S$21>$D53,"",IF($G53=$E$6,INDEX(Orçamento!$U:$U,MATCH(S$21,Orçamento!$C:$C,),1),INDEX(Orçamento!$U:$U,MATCH(S$21&"-"&$F54,Orçamento!$F:$F,),1))) | T53: =IF(T$21>$D53,"",IF($G53=$E$6,INDEX(Orçamento!$U:$U,MATCH(T$21,Orçamento!$C:$C,),1),INDEX(Orçamento!$U:$U,MATCH(T$21&"-"&$F54,Orçamento!$F:$F,),1))) | U53: =IF(U$21>$D53,"",IF($G53=$E$6,INDEX(Orçamento!$U:$U,MATCH(U$21,Orçamento!$C:$C,),1),INDEX(Orçamento!$U:$U,MATCH(U$21&"-"&$F54,Orçamento!$F:$F,),1))) | V53: =IF(V$21>$D53,"",IF($G53=$E$6,INDEX(Orçamento!$U:$U,MATCH(V$21,Orçamento!$C:$C,),1),INDEX(Orçamento!$U:$U,MATCH(V$21&"-"&$F54,Orçamento!$F:$F,),1))) | W53: =IF(W$21>$D53,"",IF($G53=$E$6,INDEX(Orçamento!$U:$U,MATCH(W$21,Orçamento!$C:$C,),1),INDEX(Orçamento!$U:$U,MATCH(W$21&"-"&$F54,Orçamento!$F:$F,),1))) | X53: =IF(X$21>$D53,"",IF($G53=$E$6,INDEX(Orçamento!$U:$U,MATCH(X$21,Orçamento!$C:$C,),1),INDEX(Orçamento!$U:$U,MATCH(X$21&"-"&$F54,Orçamento!$F:$F,),1))) | Y53: =IF(Y$21>$D53,"",IF($G53=$E$6,INDEX(Orçamento!$U:$U,MATCH(Y$21,Orçamento!$C:$C,),1),INDEX(Orçamento!$U:$U,MATCH(Y$21&"-"&$F54,Orçamento!$F:$F,),1))) | Z53: =IF(Z$21>$D53,"",IF($G53=$E$6,INDEX(Orçamento!$U:$U,MATCH(Z$21,Orçamento!$C:$C,),1),INDEX(Orçamento!$U:$U,MATCH(Z$21&"-"&$F54,Orçamento!$F:$F,),1))) | ... AK53: =IF(AK$21>$D53,"",IF($G53=$E$6,INDEX(Orçamento!$U:$U,MATCH(AK$21,Orçamento!$C:$C,),1),INDEX(Orçamento!$U:$U,MATCH(AK$21&"-"&$F54,Orçamento!$F:$F,),1)))
B54: =IF($F53>$E$2,0,(1/(1-B55-C55))*(B55+C55)) -> 0 | C54: {=IF(ROUND(SUM(IF(R53:AK53<>"",(R54:AK54)))-N53,3)<>0,"X",0)} -> 0 | E54: {=IF($F53>$E$2,"",INDEX('QC rev00'!$J$9:$J$120,1+E53,1))} | F54: {=IF($F53>$E$2,"",IF($F$2=1,INDEX('QC rev00'!$M$10:$T$120,$F55,1),IF($F$2=2,INDEX(#REF!,$F55,1),INDEX(#REF!,$F55,1))))} | Q54: Qtd | R54: {=IF(OR($D53=0,R53="",$N53=0),"", IF($G53=$E$6, SUM(IF(OFFSET($R$23,,,($F53-1)*3-2,$D$3)=R53,OFFSET($R$25,,,($F53-1)*3-2,$D$3)*OFFSET($B$23,1,,($F53-1)*3-2,1))), IF($D53=1,$N53, SUMIF(OFFSET(Orçamento!$D$1,$B53-1,,$C53,),$F54&"-"&R53,OFFSET(Orçamento!$I$1,$B53-1,,$C53,))*$N53/$E54)))} | S54: {=IF(OR($D53=0,S53="",$N53=0),"", IF($G53=$E$6, SUM(IF(OFFSET($R$23,,,($F53-1)*3-2,$D$3)=S53,OFFSET($R$25,,,($F53-1)*3-2,$D$3)*OFFSET($B$23,1,,($F53-1)*3-2,1))), IF($D53=1,$N53, SUMIF(OFFSET(Orçamento!$D$1,$B53-1,,$C53,),$F54&"-"&S53,OFFSET(Orçamento!$I$1,$B53-1,,$C53,))*$N53/$E54)))} | T54: {=IF(OR($D53=0,T53="",$N53=0),"", IF($G53=$E$6, SUM(IF(OFFSET($R$23,,,($F53-1)*3-2,$D$3)=T53,OFFSET($R$25,,,($F53-1)*3-2,$D$3)*OFFSET($B$23,1,,($F53-1)*3-2,1))), IF($D53=1,$N53, SUMIF(OFFSET(Orçamento!$D$1,$B53-1,,$C53,),$F54&"-"&T53,OFFSET(Orçamento!$I$1,$B53-1,,$C53,))*$N53/$E54)))} | U54: {=IF(OR($D53=0,U53="",$N53=0),"", IF($G53=$E$6, SUM(IF(OFFSET($R$23,,,($F53-1)*3-2,$D$3)=U53,OFFSET($R$25,,,($F53-1)*3-2,$D$3)*OFFSET($B$23,1,,($F53-1)*3-2,1))), IF($D53=1,$N53, SUMIF(OFFSET(Orçamento!$D$1,$B53-1,,$C53,),$F54&"-"&U53,OFFSET(Orçamento!$I$1,$B53-1,,$C53,))*$N53/$E54)))} | V54: {=IF(OR($D53=0,V53="",$N53=0),"", IF($G53=$E$6, SUM(IF(OFFSET($R$23,,,($F53-1)*3-2,$D$3)=V53,OFFSET($R$25,,,($F53-1)*3-2,$D$3)*OFFSET($B$23,1,,($F53-1)*3-2,1))), IF($D53=1,$N53, SUMIF(OFFSET(Orçamento!$D$1,$B53-1,,$C53,),$F54&"-"&V53,OFFSET(Orçamento!$I$1,$B53-1,,$C53,))*$N53/$E54)))} | W54: {=IF(OR($D53=0,W53="",$N53=0),"", IF($G53=$E$6, SUM(IF(OFFSET($R$23,,,($F53-1)*3-2,$D$3)=W53,OFFSET($R$25,,,($F53-1)*3-2,$D$3)*OFFSET($B$23,1,,($F53-1)*3-2,1))), IF($D53=1,$N53, SUMIF(OFFSET(Orçamento!$D$1,$B53-1,,$C53,),$F54&"-"&W53,OFFSET(Orçamento!$I$1,$B53-1,,$C53,))*$N53/$E54)))} | X54: {=IF(OR($D53=0,X53="",$N53=0),"", IF($G53=$E$6, SUM(IF(OFFSET($R$23,,,($F53-1)*3-2,$D$3)=X53,OFFSET($R$25,,,($F53-1)*3-2,$D$3)*OFFSET($B$23,1,,($F53-1)*3-2,1))), IF($D53=1,$N53, SUMIF(OFFSET(Orçamento!$D$1,$B53-1,,$C53,),$F54&"-"&X53,OFFSET(Orçamento!$I$1,$B53-1,,$C53,))*$N53/$E54)))} | Y54: {=IF(OR($D53=0,Y53="",$N53=0),"", IF($G53=$E$6, SUM(IF(OFFSET($R$23,,,($F53-1)*3-2,$D$3)=Y53,OFFSET($R$25,,,($F53-1)*3-2,$D$3)*OFFSET($B$23,1,,($F53-1)*3-2,1))), IF($D53=1,$N53, SUMIF(OFFSET(Orçamento!$D$1,$B53-1,,$C53,),$F54&"-"&Y53,OFFSET(Orçamento!$I$1,$B53-1,,$C53,))*$N53/$E54)))} | ... AK54: {=IF(OR($D53=0,AK53="",$N53=0),"", IF($G53=$E$6, SUM(IF(OFFSET($R$23,,,($F53-1)*3-2,$D$3)=AK53,OFFSET($R$25,,,($F53-1)*3-2,$D$3)*OFFSET($B$23,1,,($F53-1)*3-2,1))), IF($D53=1,$N53, SUMIF(OFFSET(Orçamento!$D$1,$B53-1,,$C53,),$F54&"-"&AK53,OFFSET(Orçamento!$I$1,$B53-1,,$C53,))*$N53/$E54)))}
B55: {=IF($F53>$E$2,"",IF($F$2=1,INDEX('QC rev00'!$M$10:$T$120,$F55,5),IF($F$2=2,INDEX(#REF!,$F55,5),INDEX(#REF!,$F55,5))))} | C55: {=IF($F53>$E$2,"",IF($F$2=1,INDEX('QC rev00'!$M$10:$T$120,$F55,6),IF($F$2=2,INDEX(#REF!,$F55,6),INDEX(#REF!,$F55,6))))} | F55: =IF(F53>$E$2,"",MATCH(F53,'QC rev00'!$C$10:$C$120,)) | Q55: Valor | R55: =IFERROR(R54*$O53,0) -> 0 | S55: =IFERROR(S54*$O53,0) -> 0 | T55: =IFERROR(T54*$O53,0) -> 0 | U55: =IFERROR(U54*$O53,0) -> 0 | V55: =IFERROR(V54*$O53,0) -> 0 | W55: =IFERROR(W54*$O53,0) -> 0 | X55: =IFERROR(X54*$O53,0) -> 0 | Y55: =IFERROR(Y54*$O53,0) -> 0 | ... AK55: =IFERROR(AK54*$O53,0) -> 0
B56: =IF($F56>$E$2,0,IF(E56<>"",MATCH(F57&" - Mapa",Orçamento!J:J,),0)) -> 0 | C56: =IF($D56>1,_xlfn.MAXIFS(Orçamento!G:G,Orçamento!J:J,F57&" - Mapa")+6-B56,0) -> 0 | D56: =IF($F56>$E$2,0,IF($G56=$E$6,$D$2,IF(E56<>"",_xlfn.MAXIFS(Orçamento!E:E,Orçamento!J:J,F57&" - Mapa"),0))) -> 0 | E56: =IF(F57="","",_xlfn.IFNA(MATCH($F57,'QC rev00'!$G$10:$G$120,),"")) | F56: {=OFFSET(F56,-3,,,)+1} -> 12 | G56: {=IF($F56>$E$2,"",IF($F$2=1,INDEX('QC rev00'!$M$10:$T$120,$F58,2),IF($F$2=2,INDEX(#REF!,$F58,2),INDEX(#REF!,$F58,2))))} | H56: {=IF($F56>$E$2,"",IF($F$2=1,INDEX('QC rev00'!$M$10:$T$120,$F58,3),IF($F$2=2,INDEX(#REF!,$F58,3),INDEX(#REF!,$F58,3))))} | L56: {=IF($F56>$E$2,"",IF($F$2=1,INDEX('QC rev00'!$M$10:$T$120,$F58,7),IF($F$2=2,INDEX(#REF!,$F58,7),INDEX(#REF!,$F58,7))))} | M56: {=IF($F56>$E$2,"",IF($F$2=1,INDEX('QC rev00'!$M$10:$T$120,$F58,8),IF($F$2=2,INDEX(#REF!,$F58,8),INDEX(#REF!,$F58,8))))} | N56: {=IF($F56>$E$2,0,IF(_xlfn.IFNA(MATCH($G56,Listas!$E$4:$E$206,),0)>0,$F$5,IF($F$2=1,INDEX('QC rev00'!$M$10:$U$120,$F58,9),IF($F$2=2,INDEX(#REF!,$F58,9),INDEX(#REF!,$F58,9)))))} -> 0 | O56: {=IF($F56>$E$2,0,IF(_xlfn.IFNA(MATCH($G56,Listas!$E$4:$E$206,),0)>0,1,IF($H$10=0,0,IF($F$2=1,INDEX('QC rev00'!$M$10:$BC$120,$F58,9+$F$3),IF($F$2=2,INDEX(#REF!,$F58,9+$F$3),INDEX(#REF!,$F58,9+$F$3)))*IF($E$5="X",1,1-$B58-$C58))))} -> 0 | P56: =N56*O56 -> 0 | Q56: IP | R56: {=IF($D56=0,"",IF($G56=$E$6,INDEX(Orçamento!$U:$U,MATCH(R$21,Orçamento!$C:$C,),1),INDEX(Orçamento!$U:$U,$B56,1)))} | S56: =IF(S$21>$D56,"",IF($G56=$E$6,INDEX(Orçamento!$U:$U,MATCH(S$21,Orçamento!$C:$C,),1),INDEX(Orçamento!$U:$U,MATCH(S$21&"-"&$F57,Orçamento!$F:$F,),1))) | T56: =IF(T$21>$D56,"",IF($G56=$E$6,INDEX(Orçamento!$U:$U,MATCH(T$21,Orçamento!$C:$C,),1),INDEX(Orçamento!$U:$U,MATCH(T$21&"-"&$F57,Orçamento!$F:$F,),1))) | U56: =IF(U$21>$D56,"",IF($G56=$E$6,INDEX(Orçamento!$U:$U,MATCH(U$21,Orçamento!$C:$C,),1),INDEX(Orçamento!$U:$U,MATCH(U$21&"-"&$F57,Orçamento!$F:$F,),1))) | V56: =IF(V$21>$D56,"",IF($G56=$E$6,INDEX(Orçamento!$U:$U,MATCH(V$21,Orçamento!$C:$C,),1),INDEX(Orçamento!$U:$U,MATCH(V$21&"-"&$F57,Orçamento!$F:$F,),1))) | W56: =IF(W$21>$D56,"",IF($G56=$E$6,INDEX(Orçamento!$U:$U,MATCH(W$21,Orçamento!$C:$C,),1),INDEX(Orçamento!$U:$U,MATCH(W$21&"-"&$F57,Orçamento!$F:$F,),1))) | X56: =IF(X$21>$D56,"",IF($G56=$E$6,INDEX(Orçamento!$U:$U,MATCH(X$21,Orçamento!$C:$C,),1),INDEX(Orçamento!$U:$U,MATCH(X$21&"-"&$F57,Orçamento!$F:$F,),1))) | Y56: =IF(Y$21>$D56,"",IF($G56=$E$6,INDEX(Orçamento!$U:$U,MATCH(Y$21,Orçamento!$C:$C,),1),INDEX(Orçamento!$U:$U,MATCH(Y$21&"-"&$F57,Orçamento!$F:$F,),1))) | Z56: =IF(Z$21>$D56,"",IF($G56=$E$6,INDEX(Orçamento!$U:$U,MATCH(Z$21,Orçamento!$C:$C,),1),INDEX(Orçamento!$U:$U,MATCH(Z$21&"-"&$F57,Orçamento!$F:$F,),1))) | ... AK56: =IF(AK$21>$D56,"",IF($G56=$E$6,INDEX(Orçamento!$U:$U,MATCH(AK$21,Orçamento!$C:$C,),1),INDEX(Orçamento!$U:$U,MATCH(AK$21&"-"&$F57,Orçamento!$F:$F,),1)))
B57: =IF($F56>$E$2,0,(1/(1-B58-C58))*(B58+C58)) -> 0 | C57: {=IF(ROUND(SUM(IF(R56:AK56<>"",(R57:AK57)))-N56,3)<>0,"X",0)} -> 0 | E57: {=IF($F56>$E$2,"",INDEX('QC rev00'!$J$9:$J$120,1+E56,1))} | F57: {=IF($F56>$E$2,"",IF($F$2=1,INDEX('QC rev00'!$M$10:$T$120,$F58,1),IF($F$2=2,INDEX(#REF!,$F58,1),INDEX(#REF!,$F58,1))))} | Q57: Qtd | R57: {=IF(OR($D56=0,R56="",$N56=0),"", IF($G56=$E$6, SUM(IF(OFFSET($R$23,,,($F56-1)*3-2,$D$3)=R56,OFFSET($R$25,,,($F56-1)*3-2,$D$3)*OFFSET($B$23,1,,($F56-1)*3-2,1))), IF($D56=1,$N56, SUMIF(OFFSET(Orçamento!$D$1,$B56-1,,$C56,),$F57&"-"&R56,OFFSET(Orçamento!$I$1,$B56-1,,$C56,))*$N56/$E57)))} | S57: {=IF(OR($D56=0,S56="",$N56=0),"", IF($G56=$E$6, SUM(IF(OFFSET($R$23,,,($F56-1)*3-2,$D$3)=S56,OFFSET($R$25,,,($F56-1)*3-2,$D$3)*OFFSET($B$23,1,,($F56-1)*3-2,1))), IF($D56=1,$N56, SUMIF(OFFSET(Orçamento!$D$1,$B56-1,,$C56,),$F57&"-"&S56,OFFSET(Orçamento!$I$1,$B56-1,,$C56,))*$N56/$E57)))} | T57: {=IF(OR($D56=0,T56="",$N56=0),"", IF($G56=$E$6, SUM(IF(OFFSET($R$23,,,($F56-1)*3-2,$D$3)=T56,OFFSET($R$25,,,($F56-1)*3-2,$D$3)*OFFSET($B$23,1,,($F56-1)*3-2,1))), IF($D56=1,$N56, SUMIF(OFFSET(Orçamento!$D$1,$B56-1,,$C56,),$F57&"-"&T56,OFFSET(Orçamento!$I$1,$B56-1,,$C56,))*$N56/$E57)))} | U57: {=IF(OR($D56=0,U56="",$N56=0),"", IF($G56=$E$6, SUM(IF(OFFSET($R$23,,,($F56-1)*3-2,$D$3)=U56,OFFSET($R$25,,,($F56-1)*3-2,$D$3)*OFFSET($B$23,1,,($F56-1)*3-2,1))), IF($D56=1,$N56, SUMIF(OFFSET(Orçamento!$D$1,$B56-1,,$C56,),$F57&"-"&U56,OFFSET(Orçamento!$I$1,$B56-1,,$C56,))*$N56/$E57)))} | V57: {=IF(OR($D56=0,V56="",$N56=0),"", IF($G56=$E$6, SUM(IF(OFFSET($R$23,,,($F56-1)*3-2,$D$3)=V56,OFFSET($R$25,,,($F56-1)*3-2,$D$3)*OFFSET($B$23,1,,($F56-1)*3-2,1))), IF($D56=1,$N56, SUMIF(OFFSET(Orçamento!$D$1,$B56-1,,$C56,),$F57&"-"&V56,OFFSET(Orçamento!$I$1,$B56-1,,$C56,))*$N56/$E57)))} | W57: {=IF(OR($D56=0,W56="",$N56=0),"", IF($G56=$E$6, SUM(IF(OFFSET($R$23,,,($F56-1)*3-2,$D$3)=W56,OFFSET($R$25,,,($F56-1)*3-2,$D$3)*OFFSET($B$23,1,,($F56-1)*3-2,1))), IF($D56=1,$N56, SUMIF(OFFSET(Orçamento!$D$1,$B56-1,,$C56,),$F57&"-"&W56,OFFSET(Orçamento!$I$1,$B56-1,,$C56,))*$N56/$E57)))} | X57: {=IF(OR($D56=0,X56="",$N56=0),"", IF($G56=$E$6, SUM(IF(OFFSET($R$23,,,($F56-1)*3-2,$D$3)=X56,OFFSET($R$25,,,($F56-1)*3-2,$D$3)*OFFSET($B$23,1,,($F56-1)*3-2,1))), IF($D56=1,$N56, SUMIF(OFFSET(Orçamento!$D$1,$B56-1,,$C56,),$F57&"-"&X56,OFFSET(Orçamento!$I$1,$B56-1,,$C56,))*$N56/$E57)))} | Y57: {=IF(OR($D56=0,Y56="",$N56=0),"", IF($G56=$E$6, SUM(IF(OFFSET($R$23,,,($F56-1)*3-2,$D$3)=Y56,OFFSET($R$25,,,($F56-1)*3-2,$D$3)*OFFSET($B$23,1,,($F56-1)*3-2,1))), IF($D56=1,$N56, SUMIF(OFFSET(Orçamento!$D$1,$B56-1,,$C56,),$F57&"-"&Y56,OFFSET(Orçamento!$I$1,$B56-1,,$C56,))*$N56/$E57)))} | ... AK57: {=IF(OR($D56=0,AK56="",$N56=0),"", IF($G56=$E$6, SUM(IF(OFFSET($R$23,,,($F56-1)*3-2,$D$3)=AK56,OFFSET($R$25,,,($F56-1)*3-2,$D$3)*OFFSET($B$23,1,,($F56-1)*3-2,1))), IF($D56=1,$N56, SUMIF(OFFSET(Orçamento!$D$1,$B56-1,,$C56,),$F57&"-"&AK56,OFFSET(Orçamento!$I$1,$B56-1,,$C56,))*$N56/$E57)))}
B58: {=IF($F56>$E$2,"",IF($F$2=1,INDEX('QC rev00'!$M$10:$T$120,$F58,5),IF($F$2=2,INDEX(#REF!,$F58,5),INDEX(#REF!,$F58,5))))} | C58: {=IF($F56>$E$2,"",IF($F$2=1,INDEX('QC rev00'!$M$10:$T$120,$F58,6),IF($F$2=2,INDEX(#REF!,$F58,6),INDEX(#REF!,$F58,6))))} | F58: =IF(F56>$E$2,"",MATCH(F56,'QC rev00'!$C$10:$C$120,)) | Q58: Valor | R58: =IFERROR(R57*$O56,0) -> 0 | S58: =IFERROR(S57*$O56,0) -> 0 | T58: =IFERROR(T57*$O56,0) -> 0 | U58: =IFERROR(U57*$O56,0) -> 0 | V58: =IFERROR(V57*$O56,0) -> 0 | W58: =IFERROR(W57*$O56,0) -> 0 | X58: =IFERROR(X57*$O56,0) -> 0 | Y58: =IFERROR(Y57*$O56,0) -> 0 | ... AK58: =IFERROR(AK57*$O56,0) -> 0
B59: =IF($F59>$E$2,0,IF(E59<>"",MATCH(F60&" - Mapa",Orçamento!J:J,),0)) -> 0 | C59: =IF($D59>1,_xlfn.MAXIFS(Orçamento!G:G,Orçamento!J:J,F60&" - Mapa")+6-B59,0) -> 0 | D59: =IF($F59>$E$2,0,IF($G59=$E$6,$D$2,IF(E59<>"",_xlfn.MAXIFS(Orçamento!E:E,Orçamento!J:J,F60&" - Mapa"),0))) -> 0 | E59: =IF(F60="","",_xlfn.IFNA(MATCH($F60,'QC rev00'!$G$10:$G$120,),"")) | F59: {=OFFSET(F59,-3,,,)+1} -> 13 | G59: {=IF($F59>$E$2,"",IF($F$2=1,INDEX('QC rev00'!$M$10:$T$120,$F61,2),IF($F$2=2,INDEX(#REF!,$F61,2),INDEX(#REF!,$F61,2))))} | H59: {=IF($F59>$E$2,"",IF($F$2=1,INDEX('QC rev00'!$M$10:$T$120,$F61,3),IF($F$2=2,INDEX(#REF!,$F61,3),INDEX(#REF!,$F61,3))))} | L59: {=IF($F59>$E$2,"",IF($F$2=1,INDEX('QC rev00'!$M$10:$T$120,$F61,7),IF($F$2=2,INDEX(#REF!,$F61,7),INDEX(#REF!,$F61,7))))} | M59: {=IF($F59>$E$2,"",IF($F$2=1,INDEX('QC rev00'!$M$10:$T$120,$F61,8),IF($F$2=2,INDEX(#REF!,$F61,8),INDEX(#REF!,$F61,8))))} | N59: {=IF($F59>$E$2,0,IF(_xlfn.IFNA(MATCH($G59,Listas!$E$4:$E$206,),0)>0,$F$5,IF($F$2=1,INDEX('QC rev00'!$M$10:$U$120,$F61,9),IF($F$2=2,INDEX(#REF!,$F61,9),INDEX(#REF!,$F61,9)))))} -> 0 | O59: {=IF($F59>$E$2,0,IF(_xlfn.IFNA(MATCH($G59,Listas!$E$4:$E$206,),0)>0,1,IF($H$10=0,0,IF($F$2=1,INDEX('QC rev00'!$M$10:$BC$120,$F61,9+$F$3),IF($F$2=2,INDEX(#REF!,$F61,9+$F$3),INDEX(#REF!,$F61,9+$F$3)))*IF($E$5="X",1,1-$B61-$C61))))} -> 0 | P59: =N59*O59 -> 0 | Q59: IP | R59: {=IF($D59=0,"",IF($G59=$E$6,INDEX(Orçamento!$U:$U,MATCH(R$21,Orçamento!$C:$C,),1),INDEX(Orçamento!$U:$U,$B59,1)))} | S59: =IF(S$21>$D59,"",IF($G59=$E$6,INDEX(Orçamento!$U:$U,MATCH(S$21,Orçamento!$C:$C,),1),INDEX(Orçamento!$U:$U,MATCH(S$21&"-"&$F60,Orçamento!$F:$F,),1))) | T59: =IF(T$21>$D59,"",IF($G59=$E$6,INDEX(Orçamento!$U:$U,MATCH(T$21,Orçamento!$C:$C,),1),INDEX(Orçamento!$U:$U,MATCH(T$21&"-"&$F60,Orçamento!$F:$F,),1))) | U59: =IF(U$21>$D59,"",IF($G59=$E$6,INDEX(Orçamento!$U:$U,MATCH(U$21,Orçamento!$C:$C,),1),INDEX(Orçamento!$U:$U,MATCH(U$21&"-"&$F60,Orçamento!$F:$F,),1))) | V59: =IF(V$21>$D59,"",IF($G59=$E$6,INDEX(Orçamento!$U:$U,MATCH(V$21,Orçamento!$C:$C,),1),INDEX(Orçamento!$U:$U,MATCH(V$21&"-"&$F60,Orçamento!$F:$F,),1))) | W59: =IF(W$21>$D59,"",IF($G59=$E$6,INDEX(Orçamento!$U:$U,MATCH(W$21,Orçamento!$C:$C,),1),INDEX(Orçamento!$U:$U,MATCH(W$21&"-"&$F60,Orçamento!$F:$F,),1))) | X59: =IF(X$21>$D59,"",IF($G59=$E$6,INDEX(Orçamento!$U:$U,MATCH(X$21,Orçamento!$C:$C,),1),INDEX(Orçamento!$U:$U,MATCH(X$21&"-"&$F60,Orçamento!$F:$F,),1))) | Y59: =IF(Y$21>$D59,"",IF($G59=$E$6,INDEX(Orçamento!$U:$U,MATCH(Y$21,Orçamento!$C:$C,),1),INDEX(Orçamento!$U:$U,MATCH(Y$21&"-"&$F60,Orçamento!$F:$F,),1))) | Z59: =IF(Z$21>$D59,"",IF($G59=$E$6,INDEX(Orçamento!$U:$U,MATCH(Z$21,Orçamento!$C:$C,),1),INDEX(Orçamento!$U:$U,MATCH(Z$21&"-"&$F60,Orçamento!$F:$F,),1))) | ... AK59: =IF(AK$21>$D59,"",IF($G59=$E$6,INDEX(Orçamento!$U:$U,MATCH(AK$21,Orçamento!$C:$C,),1),INDEX(Orçamento!$U:$U,MATCH(AK$21&"-"&$F60,Orçamento!$F:$F,),1)))
B60: =IF($F59>$E$2,0,(1/(1-B61-C61))*(B61+C61)) -> 0 | C60: {=IF(ROUND(SUM(IF(R59:AK59<>"",(R60:AK60)))-N59,3)<>0,"X",0)} -> 0 | E60: {=IF($F59>$E$2,"",INDEX('QC rev00'!$J$9:$J$120,1+E59,1))} | F60: {=IF($F59>$E$2,"",IF($F$2=1,INDEX('QC rev00'!$M$10:$T$120,$F61,1),IF($F$2=2,INDEX(#REF!,$F61,1),INDEX(#REF!,$F61,1))))} | Q60: Qtd | R60: {=IF(OR($D59=0,R59="",$N59=0),"", IF($G59=$E$6, SUM(IF(OFFSET($R$23,,,($F59-1)*3-2,$D$3)=R59,OFFSET($R$25,,,($F59-1)*3-2,$D$3)*OFFSET($B$23,1,,($F59-1)*3-2,1))), IF($D59=1,$N59, SUMIF(OFFSET(Orçamento!$D$1,$B59-1,,$C59,),$F60&"-"&R59,OFFSET(Orçamento!$I$1,$B59-1,,$C59,))*$N59/$E60)))} | S60: {=IF(OR($D59=0,S59="",$N59=0),"", IF($G59=$E$6, SUM(IF(OFFSET($R$23,,,($F59-1)*3-2,$D$3)=S59,OFFSET($R$25,,,($F59-1)*3-2,$D$3)*OFFSET($B$23,1,,($F59-1)*3-2,1))), IF($D59=1,$N59, SUMIF(OFFSET(Orçamento!$D$1,$B59-1,,$C59,),$F60&"-"&S59,OFFSET(Orçamento!$I$1,$B59-1,,$C59,))*$N59/$E60)))} | T60: {=IF(OR($D59=0,T59="",$N59=0),"", IF($G59=$E$6, SUM(IF(OFFSET($R$23,,,($F59-1)*3-2,$D$3)=T59,OFFSET($R$25,,,($F59-1)*3-2,$D$3)*OFFSET($B$23,1,,($F59-1)*3-2,1))), IF($D59=1,$N59, SUMIF(OFFSET(Orçamento!$D$1,$B59-1,,$C59,),$F60&"-"&T59,OFFSET(Orçamento!$I$1,$B59-1,,$C59,))*$N59/$E60)))} | U60: {=IF(OR($D59=0,U59="",$N59=0),"", IF($G59=$E$6, SUM(IF(OFFSET($R$23,,,($F59-1)*3-2,$D$3)=U59,OFFSET($R$25,,,($F59-1)*3-2,$D$3)*OFFSET($B$23,1,,($F59-1)*3-2,1))), IF($D59=1,$N59, SUMIF(OFFSET(Orçamento!$D$1,$B59-1,,$C59,),$F60&"-"&U59,OFFSET(Orçamento!$I$1,$B59-1,,$C59,))*$N59/$E60)))} | V60: {=IF(OR($D59=0,V59="",$N59=0),"", IF($G59=$E$6, SUM(IF(OFFSET($R$23,,,($F59-1)*3-2,$D$3)=V59,OFFSET($R$25,,,($F59-1)*3-2,$D$3)*OFFSET($B$23,1,,($F59-1)*3-2,1))), IF($D59=1,$N59, SUMIF(OFFSET(Orçamento!$D$1,$B59-1,,$C59,),$F60&"-"&V59,OFFSET(Orçamento!$I$1,$B59-1,,$C59,))*$N59/$E60)))} | W60: {=IF(OR($D59=0,W59="",$N59=0),"", IF($G59=$E$6, SUM(IF(OFFSET($R$23,,,($F59-1)*3-2,$D$3)=W59,OFFSET($R$25,,,($F59-1)*3-2,$D$3)*OFFSET($B$23,1,,($F59-1)*3-2,1))), IF($D59=1,$N59, SUMIF(OFFSET(Orçamento!$D$1,$B59-1,,$C59,),$F60&"-"&W59,OFFSET(Orçamento!$I$1,$B59-1,,$C59,))*$N59/$E60)))} | X60: {=IF(OR($D59=0,X59="",$N59=0),"", IF($G59=$E$6, SUM(IF(OFFSET($R$23,,,($F59-1)*3-2,$D$3)=X59,OFFSET($R$25,,,($F59-1)*3-2,$D$3)*OFFSET($B$23,1,,($F59-1)*3-2,1))), IF($D59=1,$N59, SUMIF(OFFSET(Orçamento!$D$1,$B59-1,,$C59,),$F60&"-"&X59,OFFSET(Orçamento!$I$1,$B59-1,,$C59,))*$N59/$E60)))} | Y60: {=IF(OR($D59=0,Y59="",$N59=0),"", IF($G59=$E$6, SUM(IF(OFFSET($R$23,,,($F59-1)*3-2,$D$3)=Y59,OFFSET($R$25,,,($F59-1)*3-2,$D$3)*OFFSET($B$23,1,,($F59-1)*3-2,1))), IF($D59=1,$N59, SUMIF(OFFSET(Orçamento!$D$1,$B59-1,,$C59,),$F60&"-"&Y59,OFFSET(Orçamento!$I$1,$B59-1,,$C59,))*$N59/$E60)))} | ... AK60: {=IF(OR($D59=0,AK59="",$N59=0),"", IF($G59=$E$6, SUM(IF(OFFSET($R$23,,,($F59-1)*3-2,$D$3)=AK59,OFFSET($R$25,,,($F59-1)*3-2,$D$3)*OFFSET($B$23,1,,($F59-1)*3-2,1))), IF($D59=1,$N59, SUMIF(OFFSET(Orçamento!$D$1,$B59-1,,$C59,),$F60&"-"&AK59,OFFSET(Orçamento!$I$1,$B59-1,,$C59,))*$N59/$E60)))}
B61: {=IF($F59>$E$2,"",IF($F$2=1,INDEX('QC rev00'!$M$10:$T$120,$F61,5),IF($F$2=2,INDEX(#REF!,$F61,5),INDEX(#REF!,$F61,5))))} | C61: {=IF($F59>$E$2,"",IF($F$2=1,INDEX('QC rev00'!$M$10:$T$120,$F61,6),IF($F$2=2,INDEX(#REF!,$F61,6),INDEX(#REF!,$F61,6))))} | F61: =IF(F59>$E$2,"",MATCH(F59,'QC rev00'!$C$10:$C$120,)) | Q61: Valor | R61: =IFERROR(R60*$O59,0) -> 0 | S61: =IFERROR(S60*$O59,0) -> 0 | T61: =IFERROR(T60*$O59,0) -> 0 | U61: =IFERROR(U60*$O59,0) -> 0 | V61: =IFERROR(V60*$O59,0) -> 0 | W61: =IFERROR(W60*$O59,0) -> 0 | X61: =IFERROR(X60*$O59,0) -> 0 | Y61: =IFERROR(Y60*$O59,0) -> 0 | ... AK61: =IFERROR(AK60*$O59,0) -> 0
B62: =IF($F62>$E$2,0,IF(E62<>"",MATCH(F63&" - Mapa",Orçamento!J:J,),0)) -> 0 | C62: =IF($D62>1,_xlfn.MAXIFS(Orçamento!G:G,Orçamento!J:J,F63&" - Mapa")+6-B62,0) -> 0 | D62: =IF($F62>$E$2,0,IF($G62=$E$6,$D$2,IF(E62<>"",_xlfn.MAXIFS(Orçamento!E:E,Orçamento!J:J,F63&" - Mapa"),0))) -> 0 | E62: =IF(F63="","",_xlfn.IFNA(MATCH($F63,'QC rev00'!$G$10:$G$120,),"")) | F62: {=OFFSET(F62,-3,,,)+1} -> 14 | G62: {=IF($F62>$E$2,"",IF($F$2=1,INDEX('QC rev00'!$M$10:$T$120,$F64,2),IF($F$2=2,INDEX(#REF!,$F64,2),INDEX(#REF!,$F64,2))))} | H62: {=IF($F62>$E$2,"",IF($F$2=1,INDEX('QC rev00'!$M$10:$T$120,$F64,3),IF($F$2=2,INDEX(#REF!,$F64,3),INDEX(#REF!,$F64,3))))} | L62: {=IF($F62>$E$2,"",IF($F$2=1,INDEX('QC rev00'!$M$10:$T$120,$F64,7),IF($F$2=2,INDEX(#REF!,$F64,7),INDEX(#REF!,$F64,7))))} | M62: {=IF($F62>$E$2,"",IF($F$2=1,INDEX('QC rev00'!$M$10:$T$120,$F64,8),IF($F$2=2,INDEX(#REF!,$F64,8),INDEX(#REF!,$F64,8))))} | N62: {=IF($F62>$E$2,0,IF(_xlfn.IFNA(MATCH($G62,Listas!$E$4:$E$206,),0)>0,$F$5,IF($F$2=1,INDEX('QC rev00'!$M$10:$U$120,$F64,9),IF($F$2=2,INDEX(#REF!,$F64,9),INDEX(#REF!,$F64,9)))))} -> 0 | O62: {=IF($F62>$E$2,0,IF(_xlfn.IFNA(MATCH($G62,Listas!$E$4:$E$206,),0)>0,1,IF($H$10=0,0,IF($F$2=1,INDEX('QC rev00'!$M$10:$BC$120,$F64,9+$F$3),IF($F$2=2,INDEX(#REF!,$F64,9+$F$3),INDEX(#REF!,$F64,9+$F$3)))*IF($E$5="X",1,1-$B64-$C64))))} -> 0 | P62: =N62*O62 -> 0 | Q62: IP | R62: {=IF($D62=0,"",IF($G62=$E$6,INDEX(Orçamento!$U:$U,MATCH(R$21,Orçamento!$C:$C,),1),INDEX(Orçamento!$U:$U,$B62,1)))} | S62: =IF(S$21>$D62,"",IF($G62=$E$6,INDEX(Orçamento!$U:$U,MATCH(S$21,Orçamento!$C:$C,),1),INDEX(Orçamento!$U:$U,MATCH(S$21&"-"&$F63,Orçamento!$F:$F,),1))) | T62: =IF(T$21>$D62,"",IF($G62=$E$6,INDEX(Orçamento!$U:$U,MATCH(T$21,Orçamento!$C:$C,),1),INDEX(Orçamento!$U:$U,MATCH(T$21&"-"&$F63,Orçamento!$F:$F,),1))) | U62: =IF(U$21>$D62,"",IF($G62=$E$6,INDEX(Orçamento!$U:$U,MATCH(U$21,Orçamento!$C:$C,),1),INDEX(Orçamento!$U:$U,MATCH(U$21&"-"&$F63,Orçamento!$F:$F,),1))) | V62: =IF(V$21>$D62,"",IF($G62=$E$6,INDEX(Orçamento!$U:$U,MATCH(V$21,Orçamento!$C:$C,),1),INDEX(Orçamento!$U:$U,MATCH(V$21&"-"&$F63,Orçamento!$F:$F,),1))) | W62: =IF(W$21>$D62,"",IF($G62=$E$6,INDEX(Orçamento!$U:$U,MATCH(W$21,Orçamento!$C:$C,),1),INDEX(Orçamento!$U:$U,MATCH(W$21&"-"&$F63,Orçamento!$F:$F,),1))) | X62: =IF(X$21>$D62,"",IF($G62=$E$6,INDEX(Orçamento!$U:$U,MATCH(X$21,Orçamento!$C:$C,),1),INDEX(Orçamento!$U:$U,MATCH(X$21&"-"&$F63,Orçamento!$F:$F,),1))) | Y62: =IF(Y$21>$D62,"",IF($G62=$E$6,INDEX(Orçamento!$U:$U,MATCH(Y$21,Orçamento!$C:$C,),1),INDEX(Orçamento!$U:$U,MATCH(Y$21&"-"&$F63,Orçamento!$F:$F,),1))) | Z62: =IF(Z$21>$D62,"",IF($G62=$E$6,INDEX(Orçamento!$U:$U,MATCH(Z$21,Orçamento!$C:$C,),1),INDEX(Orçamento!$U:$U,MATCH(Z$21&"-"&$F63,Orçamento!$F:$F,),1))) | ... AK62: =IF(AK$21>$D62,"",IF($G62=$E$6,INDEX(Orçamento!$U:$U,MATCH(AK$21,Orçamento!$C:$C,),1),INDEX(Orçamento!$U:$U,MATCH(AK$21&"-"&$F63,Orçamento!$F:$F,),1)))
B63: =IF($F62>$E$2,0,(1/(1-B64-C64))*(B64+C64)) -> 0 | C63: {=IF(ROUND(SUM(IF(R62:AK62<>"",(R63:AK63)))-N62,3)<>0,"X",0)} -> 0 | E63: {=IF($F62>$E$2,"",INDEX('QC rev00'!$J$9:$J$120,1+E62,1))} | F63: {=IF($F62>$E$2,"",IF($F$2=1,INDEX('QC rev00'!$M$10:$T$120,$F64,1),IF($F$2=2,INDEX(#REF!,$F64,1),INDEX(#REF!,$F64,1))))} | Q63: Qtd | R63: {=IF(OR($D62=0,R62="",$N62=0),"", IF($G62=$E$6, SUM(IF(OFFSET($R$23,,,($F62-1)*3-2,$D$3)=R62,OFFSET($R$25,,,($F62-1)*3-2,$D$3)*OFFSET($B$23,1,,($F62-1)*3-2,1))), IF($D62=1,$N62, SUMIF(OFFSET(Orçamento!$D$1,$B62-1,,$C62,),$F63&"-"&R62,OFFSET(Orçamento!$I$1,$B62-1,,$C62,))*$N62/$E63)))} | S63: {=IF(OR($D62=0,S62="",$N62=0),"", IF($G62=$E$6, SUM(IF(OFFSET($R$23,,,($F62-1)*3-2,$D$3)=S62,OFFSET($R$25,,,($F62-1)*3-2,$D$3)*OFFSET($B$23,1,,($F62-1)*3-2,1))), IF($D62=1,$N62, SUMIF(OFFSET(Orçamento!$D$1,$B62-1,,$C62,),$F63&"-"&S62,OFFSET(Orçamento!$I$1,$B62-1,,$C62,))*$N62/$E63)))} | T63: {=IF(OR($D62=0,T62="",$N62=0),"", IF($G62=$E$6, SUM(IF(OFFSET($R$23,,,($F62-1)*3-2,$D$3)=T62,OFFSET($R$25,,,($F62-1)*3-2,$D$3)*OFFSET($B$23,1,,($F62-1)*3-2,1))), IF($D62=1,$N62, SUMIF(OFFSET(Orçamento!$D$1,$B62-1,,$C62,),$F63&"-"&T62,OFFSET(Orçamento!$I$1,$B62-1,,$C62,))*$N62/$E63)))} | U63: {=IF(OR($D62=0,U62="",$N62=0),"", IF($G62=$E$6, SUM(IF(OFFSET($R$23,,,($F62-1)*3-2,$D$3)=U62,OFFSET($R$25,,,($F62-1)*3-2,$D$3)*OFFSET($B$23,1,,($F62-1)*3-2,1))), IF($D62=1,$N62, SUMIF(OFFSET(Orçamento!$D$1,$B62-1,,$C62,),$F63&"-"&U62,OFFSET(Orçamento!$I$1,$B62-1,,$C62,))*$N62/$E63)))} | V63: {=IF(OR($D62=0,V62="",$N62=0),"", IF($G62=$E$6, SUM(IF(OFFSET($R$23,,,($F62-1)*3-2,$D$3)=V62,OFFSET($R$25,,,($F62-1)*3-2,$D$3)*OFFSET($B$23,1,,($F62-1)*3-2,1))), IF($D62=1,$N62, SUMIF(OFFSET(Orçamento!$D$1,$B62-1,,$C62,),$F63&"-"&V62,OFFSET(Orçamento!$I$1,$B62-1,,$C62,))*$N62/$E63)))} | W63: {=IF(OR($D62=0,W62="",$N62=0),"", IF($G62=$E$6, SUM(IF(OFFSET($R$23,,,($F62-1)*3-2,$D$3)=W62,OFFSET($R$25,,,($F62-1)*3-2,$D$3)*OFFSET($B$23,1,,($F62-1)*3-2,1))), IF($D62=1,$N62, SUMIF(OFFSET(Orçamento!$D$1,$B62-1,,$C62,),$F63&"-"&W62,OFFSET(Orçamento!$I$1,$B62-1,,$C62,))*$N62/$E63)))} | X63: {=IF(OR($D62=0,X62="",$N62=0),"", IF($G62=$E$6, SUM(IF(OFFSET($R$23,,,($F62-1)*3-2,$D$3)=X62,OFFSET($R$25,,,($F62-1)*3-2,$D$3)*OFFSET($B$23,1,,($F62-1)*3-2,1))), IF($D62=1,$N62, SUMIF(OFFSET(Orçamento!$D$1,$B62-1,,$C62,),$F63&"-"&X62,OFFSET(Orçamento!$I$1,$B62-1,,$C62,))*$N62/$E63)))} | Y63: {=IF(OR($D62=0,Y62="",$N62=0),"", IF($G62=$E$6, SUM(IF(OFFSET($R$23,,,($F62-1)*3-2,$D$3)=Y62,OFFSET($R$25,,,($F62-1)*3-2,$D$3)*OFFSET($B$23,1,,($F62-1)*3-2,1))), IF($D62=1,$N62, SUMIF(OFFSET(Orçamento!$D$1,$B62-1,,$C62,),$F63&"-"&Y62,OFFSET(Orçamento!$I$1,$B62-1,,$C62,))*$N62/$E63)))} | ... AK63: {=IF(OR($D62=0,AK62="",$N62=0),"", IF($G62=$E$6, SUM(IF(OFFSET($R$23,,,($F62-1)*3-2,$D$3)=AK62,OFFSET($R$25,,,($F62-1)*3-2,$D$3)*OFFSET($B$23,1,,($F62-1)*3-2,1))), IF($D62=1,$N62, SUMIF(OFFSET(Orçamento!$D$1,$B62-1,,$C62,),$F63&"-"&AK62,OFFSET(Orçamento!$I$1,$B62-1,,$C62,))*$N62/$E63)))}
B64: {=IF($F62>$E$2,"",IF($F$2=1,INDEX('QC rev00'!$M$10:$T$120,$F64,5),IF($F$2=2,INDEX(#REF!,$F64,5),INDEX(#REF!,$F64,5))))} | C64: {=IF($F62>$E$2,"",IF($F$2=1,INDEX('QC rev00'!$M$10:$T$120,$F64,6),IF($F$2=2,INDEX(#REF!,$F64,6),INDEX(#REF!,$F64,6))))} | F64: =IF(F62>$E$2,"",MATCH(F62,'QC rev00'!$C$10:$C$120,)) | Q64: Valor | R64: =IFERROR(R63*$O62,0) -> 0 | S64: =IFERROR(S63*$O62,0) -> 0 | T64: =IFERROR(T63*$O62,0) -> 0 | U64: =IFERROR(U63*$O62,0) -> 0 | V64: =IFERROR(V63*$O62,0) -> 0 | W64: =IFERROR(W63*$O62,0) -> 0 | X64: =IFERROR(X63*$O62,0) -> 0 | Y64: =IFERROR(Y63*$O62,0) -> 0 | ... AK64: =IFERROR(AK63*$O62,0) -> 0
B65: =IF($F65>$E$2,0,IF(E65<>"",MATCH(F66&" - Mapa",Orçamento!J:J,),0)) -> 0 | C65: =IF($D65>1,_xlfn.MAXIFS(Orçamento!G:G,Orçamento!J:J,F66&" - Mapa")+6-B65,0) -> 0 | D65: =IF($F65>$E$2,0,IF($G65=$E$6,$D$2,IF(E65<>"",_xlfn.MAXIFS(Orçamento!E:E,Orçamento!J:J,F66&" - Mapa"),0))) -> 0 | E65: =IF(F66="","",_xlfn.IFNA(MATCH($F66,'QC rev00'!$G$10:$G$120,),"")) | F65: {=OFFSET(F65,-3,,,)+1} -> 15 | G65: {=IF($F65>$E$2,"",IF($F$2=1,INDEX('QC rev00'!$M$10:$T$120,$F67,2),IF($F$2=2,INDEX(#REF!,$F67,2),INDEX(#REF!,$F67,2))))} | H65: {=IF($F65>$E$2,"",IF($F$2=1,INDEX('QC rev00'!$M$10:$T$120,$F67,3),IF($F$2=2,INDEX(#REF!,$F67,3),INDEX(#REF!,$F67,3))))} | L65: {=IF($F65>$E$2,"",IF($F$2=1,INDEX('QC rev00'!$M$10:$T$120,$F67,7),IF($F$2=2,INDEX(#REF!,$F67,7),INDEX(#REF!,$F67,7))))} | M65: {=IF($F65>$E$2,"",IF($F$2=1,INDEX('QC rev00'!$M$10:$T$120,$F67,8),IF($F$2=2,INDEX(#REF!,$F67,8),INDEX(#REF!,$F67,8))))} | N65: {=IF($F65>$E$2,0,IF(_xlfn.IFNA(MATCH($G65,Listas!$E$4:$E$206,),0)>0,$F$5,IF($F$2=1,INDEX('QC rev00'!$M$10:$U$120,$F67,9),IF($F$2=2,INDEX(#REF!,$F67,9),INDEX(#REF!,$F67,9)))))} -> 0 | O65: {=IF($F65>$E$2,0,IF(_xlfn.IFNA(MATCH($G65,Listas!$E$4:$E$206,),0)>0,1,IF($H$10=0,0,IF($F$2=1,INDEX('QC rev00'!$M$10:$BC$120,$F67,9+$F$3),IF($F$2=2,INDEX(#REF!,$F67,9+$F$3),INDEX(#REF!,$F67,9+$F$3)))*IF($E$5="X",1,1-$B67-$C67))))} -> 0 | P65: =N65*O65 -> 0 | Q65: IP | R65: {=IF($D65=0,"",IF($G65=$E$6,INDEX(Orçamento!$U:$U,MATCH(R$21,Orçamento!$C:$C,),1),INDEX(Orçamento!$U:$U,$B65,1)))} | S65: =IF(S$21>$D65,"",IF($G65=$E$6,INDEX(Orçamento!$U:$U,MATCH(S$21,Orçamento!$C:$C,),1),INDEX(Orçamento!$U:$U,MATCH(S$21&"-"&$F66,Orçamento!$F:$F,),1))) | T65: =IF(T$21>$D65,"",IF($G65=$E$6,INDEX(Orçamento!$U:$U,MATCH(T$21,Orçamento!$C:$C,),1),INDEX(Orçamento!$U:$U,MATCH(T$21&"-"&$F66,Orçamento!$F:$F,),1))) | U65: =IF(U$21>$D65,"",IF($G65=$E$6,INDEX(Orçamento!$U:$U,MATCH(U$21,Orçamento!$C:$C,),1),INDEX(Orçamento!$U:$U,MATCH(U$21&"-"&$F66,Orçamento!$F:$F,),1))) | V65: =IF(V$21>$D65,"",IF($G65=$E$6,INDEX(Orçamento!$U:$U,MATCH(V$21,Orçamento!$C:$C,),1),INDEX(Orçamento!$U:$U,MATCH(V$21&"-"&$F66,Orçamento!$F:$F,),1))) | W65: =IF(W$21>$D65,"",IF($G65=$E$6,INDEX(Orçamento!$U:$U,MATCH(W$21,Orçamento!$C:$C,),1),INDEX(Orçamento!$U:$U,MATCH(W$21&"-"&$F66,Orçamento!$F:$F,),1))) | X65: =IF(X$21>$D65,"",IF($G65=$E$6,INDEX(Orçamento!$U:$U,MATCH(X$21,Orçamento!$C:$C,),1),INDEX(Orçamento!$U:$U,MATCH(X$21&"-"&$F66,Orçamento!$F:$F,),1))) | Y65: =IF(Y$21>$D65,"",IF($G65=$E$6,INDEX(Orçamento!$U:$U,MATCH(Y$21,Orçamento!$C:$C,),1),INDEX(Orçamento!$U:$U,MATCH(Y$21&"-"&$F66,Orçamento!$F:$F,),1))) | Z65: =IF(Z$21>$D65,"",IF($G65=$E$6,INDEX(Orçamento!$U:$U,MATCH(Z$21,Orçamento!$C:$C,),1),INDEX(Orçamento!$U:$U,MATCH(Z$21&"-"&$F66,Orçamento!$F:$F,),1))) | ... AK65: =IF(AK$21>$D65,"",IF($G65=$E$6,INDEX(Orçamento!$U:$U,MATCH(AK$21,Orçamento!$C:$C,),1),INDEX(Orçamento!$U:$U,MATCH(AK$21&"-"&$F66,Orçamento!$F:$F,),1)))
B66: =IF($F65>$E$2,0,(1/(1-B67-C67))*(B67+C67)) -> 0 | C66: {=IF(ROUND(SUM(IF(R65:AK65<>"",(R66:AK66)))-N65,3)<>0,"X",0)} -> 0 | E66: {=IF($F65>$E$2,"",INDEX('QC rev00'!$J$9:$J$120,1+E65,1))} | F66: {=IF($F65>$E$2,"",IF($F$2=1,INDEX('QC rev00'!$M$10:$T$120,$F67,1),IF($F$2=2,INDEX(#REF!,$F67,1),INDEX(#REF!,$F67,1))))} | Q66: Qtd | R66: {=IF(OR($D65=0,R65="",$N65=0),"", IF($G65=$E$6, SUM(IF(OFFSET($R$23,,,($F65-1)*3-2,$D$3)=R65,OFFSET($R$25,,,($F65-1)*3-2,$D$3)*OFFSET($B$23,1,,($F65-1)*3-2,1))), IF($D65=1,$N65, SUMIF(OFFSET(Orçamento!$D$1,$B65-1,,$C65,),$F66&"-"&R65,OFFSET(Orçamento!$I$1,$B65-1,,$C65,))*$N65/$E66)))} | S66: {=IF(OR($D65=0,S65="",$N65=0),"", IF($G65=$E$6, SUM(IF(OFFSET($R$23,,,($F65-1)*3-2,$D$3)=S65,OFFSET($R$25,,,($F65-1)*3-2,$D$3)*OFFSET($B$23,1,,($F65-1)*3-2,1))), IF($D65=1,$N65, SUMIF(OFFSET(Orçamento!$D$1,$B65-1,,$C65,),$F66&"-"&S65,OFFSET(Orçamento!$I$1,$B65-1,,$C65,))*$N65/$E66)))} | T66: {=IF(OR($D65=0,T65="",$N65=0),"", IF($G65=$E$6, SUM(IF(OFFSET($R$23,,,($F65-1)*3-2,$D$3)=T65,OFFSET($R$25,,,($F65-1)*3-2,$D$3)*OFFSET($B$23,1,,($F65-1)*3-2,1))), IF($D65=1,$N65, SUMIF(OFFSET(Orçamento!$D$1,$B65-1,,$C65,),$F66&"-"&T65,OFFSET(Orçamento!$I$1,$B65-1,,$C65,))*$N65/$E66)))} | U66: {=IF(OR($D65=0,U65="",$N65=0),"", IF($G65=$E$6, SUM(IF(OFFSET($R$23,,,($F65-1)*3-2,$D$3)=U65,OFFSET($R$25,,,($F65-1)*3-2,$D$3)*OFFSET($B$23,1,,($F65-1)*3-2,1))), IF($D65=1,$N65, SUMIF(OFFSET(Orçamento!$D$1,$B65-1,,$C65,),$F66&"-"&U65,OFFSET(Orçamento!$I$1,$B65-1,,$C65,))*$N65/$E66)))} | V66: {=IF(OR($D65=0,V65="",$N65=0),"", IF($G65=$E$6, SUM(IF(OFFSET($R$23,,,($F65-1)*3-2,$D$3)=V65,OFFSET($R$25,,,($F65-1)*3-2,$D$3)*OFFSET($B$23,1,,($F65-1)*3-2,1))), IF($D65=1,$N65, SUMIF(OFFSET(Orçamento!$D$1,$B65-1,,$C65,),$F66&"-"&V65,OFFSET(Orçamento!$I$1,$B65-1,,$C65,))*$N65/$E66)))} | W66: {=IF(OR($D65=0,W65="",$N65=0),"", IF($G65=$E$6, SUM(IF(OFFSET($R$23,,,($F65-1)*3-2,$D$3)=W65,OFFSET($R$25,,,($F65-1)*3-2,$D$3)*OFFSET($B$23,1,,($F65-1)*3-2,1))), IF($D65=1,$N65, SUMIF(OFFSET(Orçamento!$D$1,$B65-1,,$C65,),$F66&"-"&W65,OFFSET(Orçamento!$I$1,$B65-1,,$C65,))*$N65/$E66)))} | X66: {=IF(OR($D65=0,X65="",$N65=0),"", IF($G65=$E$6, SUM(IF(OFFSET($R$23,,,($F65-1)*3-2,$D$3)=X65,OFFSET($R$25,,,($F65-1)*3-2,$D$3)*OFFSET($B$23,1,,($F65-1)*3-2,1))), IF($D65=1,$N65, SUMIF(OFFSET(Orçamento!$D$1,$B65-1,,$C65,),$F66&"-"&X65,OFFSET(Orçamento!$I$1,$B65-1,,$C65,))*$N65/$E66)))} | Y66: {=IF(OR($D65=0,Y65="",$N65=0),"", IF($G65=$E$6, SUM(IF(OFFSET($R$23,,,($F65-1)*3-2,$D$3)=Y65,OFFSET($R$25,,,($F65-1)*3-2,$D$3)*OFFSET($B$23,1,,($F65-1)*3-2,1))), IF($D65=1,$N65, SUMIF(OFFSET(Orçamento!$D$1,$B65-1,,$C65,),$F66&"-"&Y65,OFFSET(Orçamento!$I$1,$B65-1,,$C65,))*$N65/$E66)))} | ... AK66: {=IF(OR($D65=0,AK65="",$N65=0),"", IF($G65=$E$6, SUM(IF(OFFSET($R$23,,,($F65-1)*3-2,$D$3)=AK65,OFFSET($R$25,,,($F65-1)*3-2,$D$3)*OFFSET($B$23,1,,($F65-1)*3-2,1))), IF($D65=1,$N65, SUMIF(OFFSET(Orçamento!$D$1,$B65-1,,$C65,),$F66&"-"&AK65,OFFSET(Orçamento!$I$1,$B65-1,,$C65,))*$N65/$E66)))}
B67: {=IF($F65>$E$2,"",IF($F$2=1,INDEX('QC rev00'!$M$10:$T$120,$F67,5),IF($F$2=2,INDEX(#REF!,$F67,5),INDEX(#REF!,$F67,5))))} | C67: {=IF($F65>$E$2,"",IF($F$2=1,INDEX('QC rev00'!$M$10:$T$120,$F67,6),IF($F$2=2,INDEX(#REF!,$F67,6),INDEX(#REF!,$F67,6))))} | F67: =IF(F65>$E$2,"",MATCH(F65,'QC rev00'!$C$10:$C$120,)) | Q67: Valor | R67: =IFERROR(R66*$O65,0) -> 0 | S67: =IFERROR(S66*$O65,0) -> 0 | T67: =IFERROR(T66*$O65,0) -> 0 | U67: =IFERROR(U66*$O65,0) -> 0 | V67: =IFERROR(V66*$O65,0) -> 0 | W67: =IFERROR(W66*$O65,0) -> 0 | X67: =IFERROR(X66*$O65,0) -> 0 | Y67: =IFERROR(Y66*$O65,0) -> 0 | ... AK67: =IFERROR(AK66*$O65,0) -> 0
B68: =IF($F68>$E$2,0,IF(E68<>"",MATCH(F69&" - Mapa",Orçamento!J:J,),0)) -> 0 | C68: =IF($D68>1,_xlfn.MAXIFS(Orçamento!G:G,Orçamento!J:J,F69&" - Mapa")+6-B68,0) -> 0 | D68: =IF($F68>$E$2,0,IF($G68=$E$6,$D$2,IF(E68<>"",_xlfn.MAXIFS(Orçamento!E:E,Orçamento!J:J,F69&" - Mapa"),0))) -> 0 | E68: =IF(F69="","",_xlfn.IFNA(MATCH($F69,'QC rev00'!$G$10:$G$120,),"")) | F68: {=OFFSET(F68,-3,,,)+1} -> 16 | G68: {=IF($F68>$E$2,"",IF($F$2=1,INDEX('QC rev00'!$M$10:$T$120,$F70,2),IF($F$2=2,INDEX(#REF!,$F70,2),INDEX(#REF!,$F70,2))))} | H68: {=IF($F68>$E$2,"",IF($F$2=1,INDEX('QC rev00'!$M$10:$T$120,$F70,3),IF($F$2=2,INDEX(#REF!,$F70,3),INDEX(#REF!,$F70,3))))} | L68: {=IF($F68>$E$2,"",IF($F$2=1,INDEX('QC rev00'!$M$10:$T$120,$F70,7),IF($F$2=2,INDEX(#REF!,$F70,7),INDEX(#REF!,$F70,7))))} | M68: {=IF($F68>$E$2,"",IF($F$2=1,INDEX('QC rev00'!$M$10:$T$120,$F70,8),IF($F$2=2,INDEX(#REF!,$F70,8),INDEX(#REF!,$F70,8))))} | N68: {=IF($F68>$E$2,0,IF(_xlfn.IFNA(MATCH($G68,Listas!$E$4:$E$206,),0)>0,$F$5,IF($F$2=1,INDEX('QC rev00'!$M$10:$U$120,$F70,9),IF($F$2=2,INDEX(#REF!,$F70,9),INDEX(#REF!,$F70,9)))))} -> 0 | O68: {=IF($F68>$E$2,0,IF(_xlfn.IFNA(MATCH($G68,Listas!$E$4:$E$206,),0)>0,1,IF($H$10=0,0,IF($F$2=1,INDEX('QC rev00'!$M$10:$BC$120,$F70,9+$F$3),IF($F$2=2,INDEX(#REF!,$F70,9+$F$3),INDEX(#REF!,$F70,9+$F$3)))*IF($E$5="X",1,1-$B70-$C70))))} -> 0 | P68: =N68*O68 -> 0 | Q68: IP | R68: {=IF($D68=0,"",IF($G68=$E$6,INDEX(Orçamento!$U:$U,MATCH(R$21,Orçamento!$C:$C,),1),INDEX(Orçamento!$U:$U,$B68,1)))} | S68: =IF(S$21>$D68,"",IF($G68=$E$6,INDEX(Orçamento!$U:$U,MATCH(S$21,Orçamento!$C:$C,),1),INDEX(Orçamento!$U:$U,MATCH(S$21&"-"&$F69,Orçamento!$F:$F,),1))) | T68: =IF(T$21>$D68,"",IF($G68=$E$6,INDEX(Orçamento!$U:$U,MATCH(T$21,Orçamento!$C:$C,),1),INDEX(Orçamento!$U:$U,MATCH(T$21&"-"&$F69,Orçamento!$F:$F,),1))) | U68: =IF(U$21>$D68,"",IF($G68=$E$6,INDEX(Orçamento!$U:$U,MATCH(U$21,Orçamento!$C:$C,),1),INDEX(Orçamento!$U:$U,MATCH(U$21&"-"&$F69,Orçamento!$F:$F,),1))) | V68: =IF(V$21>$D68,"",IF($G68=$E$6,INDEX(Orçamento!$U:$U,MATCH(V$21,Orçamento!$C:$C,),1),INDEX(Orçamento!$U:$U,MATCH(V$21&"-"&$F69,Orçamento!$F:$F,),1))) | W68: =IF(W$21>$D68,"",IF($G68=$E$6,INDEX(Orçamento!$U:$U,MATCH(W$21,Orçamento!$C:$C,),1),INDEX(Orçamento!$U:$U,MATCH(W$21&"-"&$F69,Orçamento!$F:$F,),1))) | X68: =IF(X$21>$D68,"",IF($G68=$E$6,INDEX(Orçamento!$U:$U,MATCH(X$21,Orçamento!$C:$C,),1),INDEX(Orçamento!$U:$U,MATCH(X$21&"-"&$F69,Orçamento!$F:$F,),1))) | Y68: =IF(Y$21>$D68,"",IF($G68=$E$6,INDEX(Orçamento!$U:$U,MATCH(Y$21,Orçamento!$C:$C,),1),INDEX(Orçamento!$U:$U,MATCH(Y$21&"-"&$F69,Orçamento!$F:$F,),1))) | Z68: =IF(Z$21>$D68,"",IF($G68=$E$6,INDEX(Orçamento!$U:$U,MATCH(Z$21,Orçamento!$C:$C,),1),INDEX(Orçamento!$U:$U,MATCH(Z$21&"-"&$F69,Orçamento!$F:$F,),1))) | ... AK68: =IF(AK$21>$D68,"",IF($G68=$E$6,INDEX(Orçamento!$U:$U,MATCH(AK$21,Orçamento!$C:$C,),1),INDEX(Orçamento!$U:$U,MATCH(AK$21&"-"&$F69,Orçamento!$F:$F,),1)))
B69: =IF($F68>$E$2,0,(1/(1-B70-C70))*(B70+C70)) -> 0 | C69: {=IF(ROUND(SUM(IF(R68:AK68<>"",(R69:AK69)))-N68,3)<>0,"X",0)} -> 0 | E69: {=IF($F68>$E$2,"",INDEX('QC rev00'!$J$9:$J$120,1+E68,1))} | F69: {=IF($F68>$E$2,"",IF($F$2=1,INDEX('QC rev00'!$M$10:$T$120,$F70,1),IF($F$2=2,INDEX(#REF!,$F70,1),INDEX(#REF!,$F70,1))))} | Q69: Qtd | R69: {=IF(OR($D68=0,R68="",$N68=0),"", IF($G68=$E$6, SUM(IF(OFFSET($R$23,,,($F68-1)*3-2,$D$3)=R68,OFFSET($R$25,,,($F68-1)*3-2,$D$3)*OFFSET($B$23,1,,($F68-1)*3-2,1))), IF($D68=1,$N68, SUMIF(OFFSET(Orçamento!$D$1,$B68-1,,$C68,),$F69&"-"&R68,OFFSET(Orçamento!$I$1,$B68-1,,$C68,))*$N68/$E69)))} | S69: {=IF(OR($D68=0,S68="",$N68=0),"", IF($G68=$E$6, SUM(IF(OFFSET($R$23,,,($F68-1)*3-2,$D$3)=S68,OFFSET($R$25,,,($F68-1)*3-2,$D$3)*OFFSET($B$23,1,,($F68-1)*3-2,1))), IF($D68=1,$N68, SUMIF(OFFSET(Orçamento!$D$1,$B68-1,,$C68,),$F69&"-"&S68,OFFSET(Orçamento!$I$1,$B68-1,,$C68,))*$N68/$E69)))} | T69: {=IF(OR($D68=0,T68="",$N68=0),"", IF($G68=$E$6, SUM(IF(OFFSET($R$23,,,($F68-1)*3-2,$D$3)=T68,OFFSET($R$25,,,($F68-1)*3-2,$D$3)*OFFSET($B$23,1,,($F68-1)*3-2,1))), IF($D68=1,$N68, SUMIF(OFFSET(Orçamento!$D$1,$B68-1,,$C68,),$F69&"-"&T68,OFFSET(Orçamento!$I$1,$B68-1,,$C68,))*$N68/$E69)))} | U69: {=IF(OR($D68=0,U68="",$N68=0),"", IF($G68=$E$6, SUM(IF(OFFSET($R$23,,,($F68-1)*3-2,$D$3)=U68,OFFSET($R$25,,,($F68-1)*3-2,$D$3)*OFFSET($B$23,1,,($F68-1)*3-2,1))), IF($D68=1,$N68, SUMIF(OFFSET(Orçamento!$D$1,$B68-1,,$C68,),$F69&"-"&U68,OFFSET(Orçamento!$I$1,$B68-1,,$C68,))*$N68/$E69)))} | V69: {=IF(OR($D68=0,V68="",$N68=0),"", IF($G68=$E$6, SUM(IF(OFFSET($R$23,,,($F68-1)*3-2,$D$3)=V68,OFFSET($R$25,,,($F68-1)*3-2,$D$3)*OFFSET($B$23,1,,($F68-1)*3-2,1))), IF($D68=1,$N68, SUMIF(OFFSET(Orçamento!$D$1,$B68-1,,$C68,),$F69&"-"&V68,OFFSET(Orçamento!$I$1,$B68-1,,$C68,))*$N68/$E69)))} | W69: {=IF(OR($D68=0,W68="",$N68=0),"", IF($G68=$E$6, SUM(IF(OFFSET($R$23,,,($F68-1)*3-2,$D$3)=W68,OFFSET($R$25,,,($F68-1)*3-2,$D$3)*OFFSET($B$23,1,,($F68-1)*3-2,1))), IF($D68=1,$N68, SUMIF(OFFSET(Orçamento!$D$1,$B68-1,,$C68,),$F69&"-"&W68,OFFSET(Orçamento!$I$1,$B68-1,,$C68,))*$N68/$E69)))} | X69: {=IF(OR($D68=0,X68="",$N68=0),"", IF($G68=$E$6, SUM(IF(OFFSET($R$23,,,($F68-1)*3-2,$D$3)=X68,OFFSET($R$25,,,($F68-1)*3-2,$D$3)*OFFSET($B$23,1,,($F68-1)*3-2,1))), IF($D68=1,$N68, SUMIF(OFFSET(Orçamento!$D$1,$B68-1,,$C68,),$F69&"-"&X68,OFFSET(Orçamento!$I$1,$B68-1,,$C68,))*$N68/$E69)))} | Y69: {=IF(OR($D68=0,Y68="",$N68=0),"", IF($G68=$E$6, SUM(IF(OFFSET($R$23,,,($F68-1)*3-2,$D$3)=Y68,OFFSET($R$25,,,($F68-1)*3-2,$D$3)*OFFSET($B$23,1,,($F68-1)*3-2,1))), IF($D68=1,$N68, SUMIF(OFFSET(Orçamento!$D$1,$B68-1,,$C68,),$F69&"-"&Y68,OFFSET(Orçamento!$I$1,$B68-1,,$C68,))*$N68/$E69)))} | ... AK69: {=IF(OR($D68=0,AK68="",$N68=0),"", IF($G68=$E$6, SUM(IF(OFFSET($R$23,,,($F68-1)*3-2,$D$3)=AK68,OFFSET($R$25,,,($F68-1)*3-2,$D$3)*OFFSET($B$23,1,,($F68-1)*3-2,1))), IF($D68=1,$N68, SUMIF(OFFSET(Orçamento!$D$1,$B68-1,,$C68,),$F69&"-"&AK68,OFFSET(Orçamento!$I$1,$B68-1,,$C68,))*$N68/$E69)))}
B70: {=IF($F68>$E$2,"",IF($F$2=1,INDEX('QC rev00'!$M$10:$T$120,$F70,5),IF($F$2=2,INDEX(#REF!,$F70,5),INDEX(#REF!,$F70,5))))} | C70: {=IF($F68>$E$2,"",IF($F$2=1,INDEX('QC rev00'!$M$10:$T$120,$F70,6),IF($F$2=2,INDEX(#REF!,$F70,6),INDEX(#REF!,$F70,6))))} | F70: =IF(F68>$E$2,"",MATCH(F68,'QC rev00'!$C$10:$C$120,)) | Q70: Valor | R70: =IFERROR(R69*$O68,0) -> 0 | S70: =IFERROR(S69*$O68,0) -> 0 | T70: =IFERROR(T69*$O68,0) -> 0 | U70: =IFERROR(U69*$O68,0) -> 0 | V70: =IFERROR(V69*$O68,0) -> 0 | W70: =IFERROR(W69*$O68,0) -> 0 | X70: =IFERROR(X69*$O68,0) -> 0 | Y70: =IFERROR(Y69*$O68,0) -> 0 | ... AK70: =IFERROR(AK69*$O68,0) -> 0
B71: =IF($F71>$E$2,0,IF(E71<>"",MATCH(F72&" - Mapa",Orçamento!J:J,),0)) -> 0 | C71: =IF($D71>1,_xlfn.MAXIFS(Orçamento!G:G,Orçamento!J:J,F72&" - Mapa")+6-B71,0) -> 0 | D71: =IF($F71>$E$2,0,IF($G71=$E$6,$D$2,IF(E71<>"",_xlfn.MAXIFS(Orçamento!E:E,Orçamento!J:J,F72&" - Mapa"),0))) -> 0 | E71: =IF(F72="","",_xlfn.IFNA(MATCH($F72,'QC rev00'!$G$10:$G$120,),"")) | F71: {=OFFSET(F71,-3,,,)+1} -> 17 | G71: {=IF($F71>$E$2,"",IF($F$2=1,INDEX('QC rev00'!$M$10:$T$120,$F73,2),IF($F$2=2,INDEX(#REF!,$F73,2),INDEX(#REF!,$F73,2))))} | H71: {=IF($F71>$E$2,"",IF($F$2=1,INDEX('QC rev00'!$M$10:$T$120,$F73,3),IF($F$2=2,INDEX(#REF!,$F73,3),INDEX(#REF!,$F73,3))))} | L71: {=IF($F71>$E$2,"",IF($F$2=1,INDEX('QC rev00'!$M$10:$T$120,$F73,7),IF($F$2=2,INDEX(#REF!,$F73,7),INDEX(#REF!,$F73,7))))} | M71: {=IF($F71>$E$2,"",IF($F$2=1,INDEX('QC rev00'!$M$10:$T$120,$F73,8),IF($F$2=2,INDEX(#REF!,$F73,8),INDEX(#REF!,$F73,8))))} | N71: {=IF($F71>$E$2,0,IF(_xlfn.IFNA(MATCH($G71,Listas!$E$4:$E$206,),0)>0,$F$5,IF($F$2=1,INDEX('QC rev00'!$M$10:$U$120,$F73,9),IF($F$2=2,INDEX(#REF!,$F73,9),INDEX(#REF!,$F73,9)))))} -> 0 | O71: {=IF($F71>$E$2,0,IF(_xlfn.IFNA(MATCH($G71,Listas!$E$4:$E$206,),0)>0,1,IF($H$10=0,0,IF($F$2=1,INDEX('QC rev00'!$M$10:$BC$120,$F73,9+$F$3),IF($F$2=2,INDEX(#REF!,$F73,9+$F$3),INDEX(#REF!,$F73,9+$F$3)))*IF($E$5="X",1,1-$B73-$C73))))} -> 0 | P71: =N71*O71 -> 0 | Q71: IP | R71: {=IF($D71=0,"",IF($G71=$E$6,INDEX(Orçamento!$U:$U,MATCH(R$21,Orçamento!$C:$C,),1),INDEX(Orçamento!$U:$U,$B71,1)))} | S71: =IF(S$21>$D71,"",IF($G71=$E$6,INDEX(Orçamento!$U:$U,MATCH(S$21,Orçamento!$C:$C,),1),INDEX(Orçamento!$U:$U,MATCH(S$21&"-"&$F72,Orçamento!$F:$F,),1))) | T71: =IF(T$21>$D71,"",IF($G71=$E$6,INDEX(Orçamento!$U:$U,MATCH(T$21,Orçamento!$C:$C,),1),INDEX(Orçamento!$U:$U,MATCH(T$21&"-"&$F72,Orçamento!$F:$F,),1))) | U71: =IF(U$21>$D71,"",IF($G71=$E$6,INDEX(Orçamento!$U:$U,MATCH(U$21,Orçamento!$C:$C,),1),INDEX(Orçamento!$U:$U,MATCH(U$21&"-"&$F72,Orçamento!$F:$F,),1))) | V71: =IF(V$21>$D71,"",IF($G71=$E$6,INDEX(Orçamento!$U:$U,MATCH(V$21,Orçamento!$C:$C,),1),INDEX(Orçamento!$U:$U,MATCH(V$21&"-"&$F72,Orçamento!$F:$F,),1))) | W71: =IF(W$21>$D71,"",IF($G71=$E$6,INDEX(Orçamento!$U:$U,MATCH(W$21,Orçamento!$C:$C,),1),INDEX(Orçamento!$U:$U,MATCH(W$21&"-"&$F72,Orçamento!$F:$F,),1))) | X71: =IF(X$21>$D71,"",IF($G71=$E$6,INDEX(Orçamento!$U:$U,MATCH(X$21,Orçamento!$C:$C,),1),INDEX(Orçamento!$U:$U,MATCH(X$21&"-"&$F72,Orçamento!$F:$F,),1))) | Y71: =IF(Y$21>$D71,"",IF($G71=$E$6,INDEX(Orçamento!$U:$U,MATCH(Y$21,Orçamento!$C:$C,),1),INDEX(Orçamento!$U:$U,MATCH(Y$21&"-"&$F72,Orçamento!$F:$F,),1))) | Z71: =IF(Z$21>$D71,"",IF($G71=$E$6,INDEX(Orçamento!$U:$U,MATCH(Z$21,Orçamento!$C:$C,),1),INDEX(Orçamento!$U:$U,MATCH(Z$21&"-"&$F72,Orçamento!$F:$F,),1))) | ... AK71: =IF(AK$21>$D71,"",IF($G71=$E$6,INDEX(Orçamento!$U:$U,MATCH(AK$21,Orçamento!$C:$C,),1),INDEX(Orçamento!$U:$U,MATCH(AK$21&"-"&$F72,Orçamento!$F:$F,),1)))
B72: =IF($F71>$E$2,0,(1/(1-B73-C73))*(B73+C73)) -> 0 | C72: {=IF(ROUND(SUM(IF(R71:AK71<>"",(R72:AK72)))-N71,3)<>0,"X",0)} -> 0 | E72: {=IF($F71>$E$2,"",INDEX('QC rev00'!$J$9:$J$120,1+E71,1))} | F72: {=IF($F71>$E$2,"",IF($F$2=1,INDEX('QC rev00'!$M$10:$T$120,$F73,1),IF($F$2=2,INDEX(#REF!,$F73,1),INDEX(#REF!,$F73,1))))} | Q72: Qtd | R72: {=IF(OR($D71=0,R71="",$N71=0),"", IF($G71=$E$6, SUM(IF(OFFSET($R$23,,,($F71-1)*3-2,$D$3)=R71,OFFSET($R$25,,,($F71-1)*3-2,$D$3)*OFFSET($B$23,1,,($F71-1)*3-2,1))), IF($D71=1,$N71, SUMIF(OFFSET(Orçamento!$D$1,$B71-1,,$C71,),$F72&"-"&R71,OFFSET(Orçamento!$I$1,$B71-1,,$C71,))*$N71/$E72)))} | S72: {=IF(OR($D71=0,S71="",$N71=0),"", IF($G71=$E$6, SUM(IF(OFFSET($R$23,,,($F71-1)*3-2,$D$3)=S71,OFFSET($R$25,,,($F71-1)*3-2,$D$3)*OFFSET($B$23,1,,($F71-1)*3-2,1))), IF($D71=1,$N71, SUMIF(OFFSET(Orçamento!$D$1,$B71-1,,$C71,),$F72&"-"&S71,OFFSET(Orçamento!$I$1,$B71-1,,$C71,))*$N71/$E72)))} | T72: {=IF(OR($D71=0,T71="",$N71=0),"", IF($G71=$E$6, SUM(IF(OFFSET($R$23,,,($F71-1)*3-2,$D$3)=T71,OFFSET($R$25,,,($F71-1)*3-2,$D$3)*OFFSET($B$23,1,,($F71-1)*3-2,1))), IF($D71=1,$N71, SUMIF(OFFSET(Orçamento!$D$1,$B71-1,,$C71,),$F72&"-"&T71,OFFSET(Orçamento!$I$1,$B71-1,,$C71,))*$N71/$E72)))} | U72: {=IF(OR($D71=0,U71="",$N71=0),"", IF($G71=$E$6, SUM(IF(OFFSET($R$23,,,($F71-1)*3-2,$D$3)=U71,OFFSET($R$25,,,($F71-1)*3-2,$D$3)*OFFSET($B$23,1,,($F71-1)*3-2,1))), IF($D71=1,$N71, SUMIF(OFFSET(Orçamento!$D$1,$B71-1,,$C71,),$F72&"-"&U71,OFFSET(Orçamento!$I$1,$B71-1,,$C71,))*$N71/$E72)))} | V72: {=IF(OR($D71=0,V71="",$N71=0),"", IF($G71=$E$6, SUM(IF(OFFSET($R$23,,,($F71-1)*3-2,$D$3)=V71,OFFSET($R$25,,,($F71-1)*3-2,$D$3)*OFFSET($B$23,1,,($F71-1)*3-2,1))), IF($D71=1,$N71, SUMIF(OFFSET(Orçamento!$D$1,$B71-1,,$C71,),$F72&"-"&V71,OFFSET(Orçamento!$I$1,$B71-1,,$C71,))*$N71/$E72)))} | W72: {=IF(OR($D71=0,W71="",$N71=0),"", IF($G71=$E$6, SUM(IF(OFFSET($R$23,,,($F71-1)*3-2,$D$3)=W71,OFFSET($R$25,,,($F71-1)*3-2,$D$3)*OFFSET($B$23,1,,($F71-1)*3-2,1))), IF($D71=1,$N71, SUMIF(OFFSET(Orçamento!$D$1,$B71-1,,$C71,),$F72&"-"&W71,OFFSET(Orçamento!$I$1,$B71-1,,$C71,))*$N71/$E72)))} | X72: {=IF(OR($D71=0,X71="",$N71=0),"", IF($G71=$E$6, SUM(IF(OFFSET($R$23,,,($F71-1)*3-2,$D$3)=X71,OFFSET($R$25,,,($F71-1)*3-2,$D$3)*OFFSET($B$23,1,,($F71-1)*3-2,1))), IF($D71=1,$N71, SUMIF(OFFSET(Orçamento!$D$1,$B71-1,,$C71,),$F72&"-"&X71,OFFSET(Orçamento!$I$1,$B71-1,,$C71,))*$N71/$E72)))} | Y72: {=IF(OR($D71=0,Y71="",$N71=0),"", IF($G71=$E$6, SUM(IF(OFFSET($R$23,,,($F71-1)*3-2,$D$3)=Y71,OFFSET($R$25,,,($F71-1)*3-2,$D$3)*OFFSET($B$23,1,,($F71-1)*3-2,1))), IF($D71=1,$N71, SUMIF(OFFSET(Orçamento!$D$1,$B71-1,,$C71,),$F72&"-"&Y71,OFFSET(Orçamento!$I$1,$B71-1,,$C71,))*$N71/$E72)))} | ... AK72: {=IF(OR($D71=0,AK71="",$N71=0),"", IF($G71=$E$6, SUM(IF(OFFSET($R$23,,,($F71-1)*3-2,$D$3)=AK71,OFFSET($R$25,,,($F71-1)*3-2,$D$3)*OFFSET($B$23,1,,($F71-1)*3-2,1))), IF($D71=1,$N71, SUMIF(OFFSET(Orçamento!$D$1,$B71-1,,$C71,),$F72&"-"&AK71,OFFSET(Orçamento!$I$1,$B71-1,,$C71,))*$N71/$E72)))}
B73: {=IF($F71>$E$2,"",IF($F$2=1,INDEX('QC rev00'!$M$10:$T$120,$F73,5),IF($F$2=2,INDEX(#REF!,$F73,5),INDEX(#REF!,$F73,5))))} | C73: {=IF($F71>$E$2,"",IF($F$2=1,INDEX('QC rev00'!$M$10:$T$120,$F73,6),IF($F$2=2,INDEX(#REF!,$F73,6),INDEX(#REF!,$F73,6))))} | F73: =IF(F71>$E$2,"",MATCH(F71,'QC rev00'!$C$10:$C$120,)) | Q73: Valor | R73: =IFERROR(R72*$O71,0) -> 0 | S73: =IFERROR(S72*$O71,0) -> 0 | T73: =IFERROR(T72*$O71,0) -> 0 | U73: =IFERROR(U72*$O71,0) -> 0 | V73: =IFERROR(V72*$O71,0) -> 0 | W73: =IFERROR(W72*$O71,0) -> 0 | X73: =IFERROR(X72*$O71,0) -> 0 | Y73: =IFERROR(Y72*$O71,0) -> 0 | ... AK73: =IFERROR(AK72*$O71,0) -> 0
B74: =IF($F74>$E$2,0,IF(E74<>"",MATCH(F75&" - Mapa",Orçamento!J:J,),0)) -> 0 | C74: =IF($D74>1,_xlfn.MAXIFS(Orçamento!G:G,Orçamento!J:J,F75&" - Mapa")+6-B74,0) -> 0 | D74: =IF($F74>$E$2,0,IF($G74=$E$6,$D$2,IF(E74<>"",_xlfn.MAXIFS(Orçamento!E:E,Orçamento!J:J,F75&" - Mapa"),0))) -> 0 | E74: =IF(F75="","",_xlfn.IFNA(MATCH($F75,'QC rev00'!$G$10:$G$120,),"")) | F74: {=OFFSET(F74,-3,,,)+1} -> 18 | G74: {=IF($F74>$E$2,"",IF($F$2=1,INDEX('QC rev00'!$M$10:$T$120,$F76,2),IF($F$2=2,INDEX(#REF!,$F76,2),INDEX(#REF!,$F76,2))))} | H74: {=IF($F74>$E$2,"",IF($F$2=1,INDEX('QC rev00'!$M$10:$T$120,$F76,3),IF($F$2=2,INDEX(#REF!,$F76,3),INDEX(#REF!,$F76,3))))} | L74: {=IF($F74>$E$2,"",IF($F$2=1,INDEX('QC rev00'!$M$10:$T$120,$F76,7),IF($F$2=2,INDEX(#REF!,$F76,7),INDEX(#REF!,$F76,7))))} | M74: {=IF($F74>$E$2,"",IF($F$2=1,INDEX('QC rev00'!$M$10:$T$120,$F76,8),IF($F$2=2,INDEX(#REF!,$F76,8),INDEX(#REF!,$F76,8))))} | N74: {=IF($F74>$E$2,0,IF(_xlfn.IFNA(MATCH($G74,Listas!$E$4:$E$206,),0)>0,$F$5,IF($F$2=1,INDEX('QC rev00'!$M$10:$U$120,$F76,9),IF($F$2=2,INDEX(#REF!,$F76,9),INDEX(#REF!,$F76,9)))))} -> 0 | O74: {=IF($F74>$E$2,0,IF(_xlfn.IFNA(MATCH($G74,Listas!$E$4:$E$206,),0)>0,1,IF($H$10=0,0,IF($F$2=1,INDEX('QC rev00'!$M$10:$BC$120,$F76,9+$F$3),IF($F$2=2,INDEX(#REF!,$F76,9+$F$3),INDEX(#REF!,$F76,9+$F$3)))*IF($E$5="X",1,1-$B76-$C76))))} -> 0 | P74: =N74*O74 -> 0 | Q74: IP | R74: {=IF($D74=0,"",IF($G74=$E$6,INDEX(Orçamento!$U:$U,MATCH(R$21,Orçamento!$C:$C,),1),INDEX(Orçamento!$U:$U,$B74,1)))} | S74: =IF(S$21>$D74,"",IF($G74=$E$6,INDEX(Orçamento!$U:$U,MATCH(S$21,Orçamento!$C:$C,),1),INDEX(Orçamento!$U:$U,MATCH(S$21&"-"&$F75,Orçamento!$F:$F,),1))) | T74: =IF(T$21>$D74,"",IF($G74=$E$6,INDEX(Orçamento!$U:$U,MATCH(T$21,Orçamento!$C:$C,),1),INDEX(Orçamento!$U:$U,MATCH(T$21&"-"&$F75,Orçamento!$F:$F,),1))) | U74: =IF(U$21>$D74,"",IF($G74=$E$6,INDEX(Orçamento!$U:$U,MATCH(U$21,Orçamento!$C:$C,),1),INDEX(Orçamento!$U:$U,MATCH(U$21&"-"&$F75,Orçamento!$F:$F,),1))) | V74: =IF(V$21>$D74,"",IF($G74=$E$6,INDEX(Orçamento!$U:$U,MATCH(V$21,Orçamento!$C:$C,),1),INDEX(Orçamento!$U:$U,MATCH(V$21&"-"&$F75,Orçamento!$F:$F,),1))) | W74: =IF(W$21>$D74,"",IF($G74=$E$6,INDEX(Orçamento!$U:$U,MATCH(W$21,Orçamento!$C:$C,),1),INDEX(Orçamento!$U:$U,MATCH(W$21&"-"&$F75,Orçamento!$F:$F,),1))) | X74: =IF(X$21>$D74,"",IF($G74=$E$6,INDEX(Orçamento!$U:$U,MATCH(X$21,Orçamento!$C:$C,),1),INDEX(Orçamento!$U:$U,MATCH(X$21&"-"&$F75,Orçamento!$F:$F,),1))) | Y74: =IF(Y$21>$D74,"",IF($G74=$E$6,INDEX(Orçamento!$U:$U,MATCH(Y$21,Orçamento!$C:$C,),1),INDEX(Orçamento!$U:$U,MATCH(Y$21&"-"&$F75,Orçamento!$F:$F,),1))) | Z74: =IF(Z$21>$D74,"",IF($G74=$E$6,INDEX(Orçamento!$U:$U,MATCH(Z$21,Orçamento!$C:$C,),1),INDEX(Orçamento!$U:$U,MATCH(Z$21&"-"&$F75,Orçamento!$F:$F,),1))) | ... AK74: =IF(AK$21>$D74,"",IF($G74=$E$6,INDEX(Orçamento!$U:$U,MATCH(AK$21,Orçamento!$C:$C,),1),INDEX(Orçamento!$U:$U,MATCH(AK$21&"-"&$F75,Orçamento!$F:$F,),1)))
B75: =IF($F74>$E$2,0,(1/(1-B76-C76))*(B76+C76)) -> 0 | C75: {=IF(ROUND(SUM(IF(R74:AK74<>"",(R75:AK75)))-N74,3)<>0,"X",0)} -> 0 | E75: {=IF($F74>$E$2,"",INDEX('QC rev00'!$J$9:$J$120,1+E74,1))} | F75: {=IF($F74>$E$2,"",IF($F$2=1,INDEX('QC rev00'!$M$10:$T$120,$F76,1),IF($F$2=2,INDEX(#REF!,$F76,1),INDEX(#REF!,$F76,1))))} | Q75: Qtd | R75: {=IF(OR($D74=0,R74="",$N74=0),"", IF($G74=$E$6, SUM(IF(OFFSET($R$23,,,($F74-1)*3-2,$D$3)=R74,OFFSET($R$25,,,($F74-1)*3-2,$D$3)*OFFSET($B$23,1,,($F74-1)*3-2,1))), IF($D74=1,$N74, SUMIF(OFFSET(Orçamento!$D$1,$B74-1,,$C74,),$F75&"-"&R74,OFFSET(Orçamento!$I$1,$B74-1,,$C74,))*$N74/$E75)))} | S75: {=IF(OR($D74=0,S74="",$N74=0),"", IF($G74=$E$6, SUM(IF(OFFSET($R$23,,,($F74-1)*3-2,$D$3)=S74,OFFSET($R$25,,,($F74-1)*3-2,$D$3)*OFFSET($B$23,1,,($F74-1)*3-2,1))), IF($D74=1,$N74, SUMIF(OFFSET(Orçamento!$D$1,$B74-1,,$C74,),$F75&"-"&S74,OFFSET(Orçamento!$I$1,$B74-1,,$C74,))*$N74/$E75)))} | T75: {=IF(OR($D74=0,T74="",$N74=0),"", IF($G74=$E$6, SUM(IF(OFFSET($R$23,,,($F74-1)*3-2,$D$3)=T74,OFFSET($R$25,,,($F74-1)*3-2,$D$3)*OFFSET($B$23,1,,($F74-1)*3-2,1))), IF($D74=1,$N74, SUMIF(OFFSET(Orçamento!$D$1,$B74-1,,$C74,),$F75&"-"&T74,OFFSET(Orçamento!$I$1,$B74-1,,$C74,))*$N74/$E75)))} | U75: {=IF(OR($D74=0,U74="",$N74=0),"", IF($G74=$E$6, SUM(IF(OFFSET($R$23,,,($F74-1)*3-2,$D$3)=U74,OFFSET($R$25,,,($F74-1)*3-2,$D$3)*OFFSET($B$23,1,,($F74-1)*3-2,1))), IF($D74=1,$N74, SUMIF(OFFSET(Orçamento!$D$1,$B74-1,,$C74,),$F75&"-"&U74,OFFSET(Orçamento!$I$1,$B74-1,,$C74,))*$N74/$E75)))} | V75: {=IF(OR($D74=0,V74="",$N74=0),"", IF($G74=$E$6, SUM(IF(OFFSET($R$23,,,($F74-1)*3-2,$D$3)=V74,OFFSET($R$25,,,($F74-1)*3-2,$D$3)*OFFSET($B$23,1,,($F74-1)*3-2,1))), IF($D74=1,$N74, SUMIF(OFFSET(Orçamento!$D$1,$B74-1,,$C74,),$F75&"-"&V74,OFFSET(Orçamento!$I$1,$B74-1,,$C74,))*$N74/$E75)))} | W75: {=IF(OR($D74=0,W74="",$N74=0),"", IF($G74=$E$6, SUM(IF(OFFSET($R$23,,,($F74-1)*3-2,$D$3)=W74,OFFSET($R$25,,,($F74-1)*3-2,$D$3)*OFFSET($B$23,1,,($F74-1)*3-2,1))), IF($D74=1,$N74, SUMIF(OFFSET(Orçamento!$D$1,$B74-1,,$C74,),$F75&"-"&W74,OFFSET(Orçamento!$I$1,$B74-1,,$C74,))*$N74/$E75)))} | X75: {=IF(OR($D74=0,X74="",$N74=0),"", IF($G74=$E$6, SUM(IF(OFFSET($R$23,,,($F74-1)*3-2,$D$3)=X74,OFFSET($R$25,,,($F74-1)*3-2,$D$3)*OFFSET($B$23,1,,($F74-1)*3-2,1))), IF($D74=1,$N74, SUMIF(OFFSET(Orçamento!$D$1,$B74-1,,$C74,),$F75&"-"&X74,OFFSET(Orçamento!$I$1,$B74-1,,$C74,))*$N74/$E75)))} | Y75: {=IF(OR($D74=0,Y74="",$N74=0),"", IF($G74=$E$6, SUM(IF(OFFSET($R$23,,,($F74-1)*3-2,$D$3)=Y74,OFFSET($R$25,,,($F74-1)*3-2,$D$3)*OFFSET($B$23,1,,($F74-1)*3-2,1))), IF($D74=1,$N74, SUMIF(OFFSET(Orçamento!$D$1,$B74-1,,$C74,),$F75&"-"&Y74,OFFSET(Orçamento!$I$1,$B74-1,,$C74,))*$N74/$E75)))} | ... AK75: {=IF(OR($D74=0,AK74="",$N74=0),"", IF($G74=$E$6, SUM(IF(OFFSET($R$23,,,($F74-1)*3-2,$D$3)=AK74,OFFSET($R$25,,,($F74-1)*3-2,$D$3)*OFFSET($B$23,1,,($F74-1)*3-2,1))), IF($D74=1,$N74, SUMIF(OFFSET(Orçamento!$D$1,$B74-1,,$C74,),$F75&"-"&AK74,OFFSET(Orçamento!$I$1,$B74-1,,$C74,))*$N74/$E75)))}
B76: {=IF($F74>$E$2,"",IF($F$2=1,INDEX('QC rev00'!$M$10:$T$120,$F76,5),IF($F$2=2,INDEX(#REF!,$F76,5),INDEX(#REF!,$F76,5))))} | C76: {=IF($F74>$E$2,"",IF($F$2=1,INDEX('QC rev00'!$M$10:$T$120,$F76,6),IF($F$2=2,INDEX(#REF!,$F76,6),INDEX(#REF!,$F76,6))))} | F76: =IF(F74>$E$2,"",MATCH(F74,'QC rev00'!$C$10:$C$120,)) | Q76: Valor | R76: =IFERROR(R75*$O74,0) -> 0 | S76: =IFERROR(S75*$O74,0) -> 0 | T76: =IFERROR(T75*$O74,0) -> 0 | U76: =IFERROR(U75*$O74,0) -> 0 | V76: =IFERROR(V75*$O74,0) -> 0 | W76: =IFERROR(W75*$O74,0) -> 0 | X76: =IFERROR(X75*$O74,0) -> 0 | Y76: =IFERROR(Y75*$O74,0) -> 0 | ... AK76: =IFERROR(AK75*$O74,0) -> 0
B77: =IF($F77>$E$2,0,IF(E77<>"",MATCH(F78&" - Mapa",Orçamento!J:J,),0)) -> 0 | C77: =IF($D77>1,_xlfn.MAXIFS(Orçamento!G:G,Orçamento!J:J,F78&" - Mapa")+6-B77,0) -> 0 | D77: =IF($F77>$E$2,0,IF($G77=$E$6,$D$2,IF(E77<>"",_xlfn.MAXIFS(Orçamento!E:E,Orçamento!J:J,F78&" - Mapa"),0))) -> 0 | E77: =IF(F78="","",_xlfn.IFNA(MATCH($F78,'QC rev00'!$G$10:$G$120,),"")) | F77: {=OFFSET(F77,-3,,,)+1} -> 19 | G77: {=IF($F77>$E$2,"",IF($F$2=1,INDEX('QC rev00'!$M$10:$T$120,$F79,2),IF($F$2=2,INDEX(#REF!,$F79,2),INDEX(#REF!,$F79,2))))} | H77: {=IF($F77>$E$2,"",IF($F$2=1,INDEX('QC rev00'!$M$10:$T$120,$F79,3),IF($F$2=2,INDEX(#REF!,$F79,3),INDEX(#REF!,$F79,3))))} | L77: {=IF($F77>$E$2,"",IF($F$2=1,INDEX('QC rev00'!$M$10:$T$120,$F79,7),IF($F$2=2,INDEX(#REF!,$F79,7),INDEX(#REF!,$F79,7))))} | M77: {=IF($F77>$E$2,"",IF($F$2=1,INDEX('QC rev00'!$M$10:$T$120,$F79,8),IF($F$2=2,INDEX(#REF!,$F79,8),INDEX(#REF!,$F79,8))))} | N77: {=IF($F77>$E$2,0,IF(_xlfn.IFNA(MATCH($G77,Listas!$E$4:$E$206,),0)>0,$F$5,IF($F$2=1,INDEX('QC rev00'!$M$10:$U$120,$F79,9),IF($F$2=2,INDEX(#REF!,$F79,9),INDEX(#REF!,$F79,9)))))} -> 0 | O77: {=IF($F77>$E$2,0,IF(_xlfn.IFNA(MATCH($G77,Listas!$E$4:$E$206,),0)>0,1,IF($H$10=0,0,IF($F$2=1,INDEX('QC rev00'!$M$10:$BC$120,$F79,9+$F$3),IF($F$2=2,INDEX(#REF!,$F79,9+$F$3),INDEX(#REF!,$F79,9+$F$3)))*IF($E$5="X",1,1-$B79-$C79))))} -> 0 | P77: =N77*O77 -> 0 | Q77: IP | R77: {=IF($D77=0,"",IF($G77=$E$6,INDEX(Orçamento!$U:$U,MATCH(R$21,Orçamento!$C:$C,),1),INDEX(Orçamento!$U:$U,$B77,1)))} | S77: =IF(S$21>$D77,"",IF($G77=$E$6,INDEX(Orçamento!$U:$U,MATCH(S$21,Orçamento!$C:$C,),1),INDEX(Orçamento!$U:$U,MATCH(S$21&"-"&$F78,Orçamento!$F:$F,),1))) | T77: =IF(T$21>$D77,"",IF($G77=$E$6,INDEX(Orçamento!$U:$U,MATCH(T$21,Orçamento!$C:$C,),1),INDEX(Orçamento!$U:$U,MATCH(T$21&"-"&$F78,Orçamento!$F:$F,),1))) | U77: =IF(U$21>$D77,"",IF($G77=$E$6,INDEX(Orçamento!$U:$U,MATCH(U$21,Orçamento!$C:$C,),1),INDEX(Orçamento!$U:$U,MATCH(U$21&"-"&$F78,Orçamento!$F:$F,),1))) | V77: =IF(V$21>$D77,"",IF($G77=$E$6,INDEX(Orçamento!$U:$U,MATCH(V$21,Orçamento!$C:$C,),1),INDEX(Orçamento!$U:$U,MATCH(V$21&"-"&$F78,Orçamento!$F:$F,),1))) | W77: =IF(W$21>$D77,"",IF($G77=$E$6,INDEX(Orçamento!$U:$U,MATCH(W$21,Orçamento!$C:$C,),1),INDEX(Orçamento!$U:$U,MATCH(W$21&"-"&$F78,Orçamento!$F:$F,),1))) | X77: =IF(X$21>$D77,"",IF($G77=$E$6,INDEX(Orçamento!$U:$U,MATCH(X$21,Orçamento!$C:$C,),1),INDEX(Orçamento!$U:$U,MATCH(X$21&"-"&$F78,Orçamento!$F:$F,),1))) | Y77: =IF(Y$21>$D77,"",IF($G77=$E$6,INDEX(Orçamento!$U:$U,MATCH(Y$21,Orçamento!$C:$C,),1),INDEX(Orçamento!$U:$U,MATCH(Y$21&"-"&$F78,Orçamento!$F:$F,),1))) | Z77: =IF(Z$21>$D77,"",IF($G77=$E$6,INDEX(Orçamento!$U:$U,MATCH(Z$21,Orçamento!$C:$C,),1),INDEX(Orçamento!$U:$U,MATCH(Z$21&"-"&$F78,Orçamento!$F:$F,),1))) | ... AK77: =IF(AK$21>$D77,"",IF($G77=$E$6,INDEX(Orçamento!$U:$U,MATCH(AK$21,Orçamento!$C:$C,),1),INDEX(Orçamento!$U:$U,MATCH(AK$21&"-"&$F78,Orçamento!$F:$F,),1)))
B78: =IF($F77>$E$2,0,(1/(1-B79-C79))*(B79+C79)) -> 0 | C78: {=IF(ROUND(SUM(IF(R77:AK77<>"",(R78:AK78)))-N77,3)<>0,"X",0)} -> 0 | E78: {=IF($F77>$E$2,"",INDEX('QC rev00'!$J$9:$J$120,1+E77,1))} | F78: {=IF($F77>$E$2,"",IF($F$2=1,INDEX('QC rev00'!$M$10:$T$120,$F79,1),IF($F$2=2,INDEX(#REF!,$F79,1),INDEX(#REF!,$F79,1))))} | Q78: Qtd | R78: {=IF(OR($D77=0,R77="",$N77=0),"", IF($G77=$E$6, SUM(IF(OFFSET($R$23,,,($F77-1)*3-2,$D$3)=R77,OFFSET($R$25,,,($F77-1)*3-2,$D$3)*OFFSET($B$23,1,,($F77-1)*3-2,1))), IF($D77=1,$N77, SUMIF(OFFSET(Orçamento!$D$1,$B77-1,,$C77,),$F78&"-"&R77,OFFSET(Orçamento!$I$1,$B77-1,,$C77,))*$N77/$E78)))} | S78: {=IF(OR($D77=0,S77="",$N77=0),"", IF($G77=$E$6, SUM(IF(OFFSET($R$23,,,($F77-1)*3-2,$D$3)=S77,OFFSET($R$25,,,($F77-1)*3-2,$D$3)*OFFSET($B$23,1,,($F77-1)*3-2,1))), IF($D77=1,$N77, SUMIF(OFFSET(Orçamento!$D$1,$B77-1,,$C77,),$F78&"-"&S77,OFFSET(Orçamento!$I$1,$B77-1,,$C77,))*$N77/$E78)))} | T78: {=IF(OR($D77=0,T77="",$N77=0),"", IF($G77=$E$6, SUM(IF(OFFSET($R$23,,,($F77-1)*3-2,$D$3)=T77,OFFSET($R$25,,,($F77-1)*3-2,$D$3)*OFFSET($B$23,1,,($F77-1)*3-2,1))), IF($D77=1,$N77, SUMIF(OFFSET(Orçamento!$D$1,$B77-1,,$C77,),$F78&"-"&T77,OFFSET(Orçamento!$I$1,$B77-1,,$C77,))*$N77/$E78)))} | U78: {=IF(OR($D77=0,U77="",$N77=0),"", IF($G77=$E$6, SUM(IF(OFFSET($R$23,,,($F77-1)*3-2,$D$3)=U77,OFFSET($R$25,,,($F77-1)*3-2,$D$3)*OFFSET($B$23,1,,($F77-1)*3-2,1))), IF($D77=1,$N77, SUMIF(OFFSET(Orçamento!$D$1,$B77-1,,$C77,),$F78&"-"&U77,OFFSET(Orçamento!$I$1,$B77-1,,$C77,))*$N77/$E78)))} | V78: {=IF(OR($D77=0,V77="",$N77=0),"", IF($G77=$E$6, SUM(IF(OFFSET($R$23,,,($F77-1)*3-2,$D$3)=V77,OFFSET($R$25,,,($F77-1)*3-2,$D$3)*OFFSET($B$23,1,,($F77-1)*3-2,1))), IF($D77=1,$N77, SUMIF(OFFSET(Orçamento!$D$1,$B77-1,,$C77,),$F78&"-"&V77,OFFSET(Orçamento!$I$1,$B77-1,,$C77,))*$N77/$E78)))} | W78: {=IF(OR($D77=0,W77="",$N77=0),"", IF($G77=$E$6, SUM(IF(OFFSET($R$23,,,($F77-1)*3-2,$D$3)=W77,OFFSET($R$25,,,($F77-1)*3-2,$D$3)*OFFSET($B$23,1,,($F77-1)*3-2,1))), IF($D77=1,$N77, SUMIF(OFFSET(Orçamento!$D$1,$B77-1,,$C77,),$F78&"-"&W77,OFFSET(Orçamento!$I$1,$B77-1,,$C77,))*$N77/$E78)))} | X78: {=IF(OR($D77=0,X77="",$N77=0),"", IF($G77=$E$6, SUM(IF(OFFSET($R$23,,,($F77-1)*3-2,$D$3)=X77,OFFSET($R$25,,,($F77-1)*3-2,$D$3)*OFFSET($B$23,1,,($F77-1)*3-2,1))), IF($D77=1,$N77, SUMIF(OFFSET(Orçamento!$D$1,$B77-1,,$C77,),$F78&"-"&X77,OFFSET(Orçamento!$I$1,$B77-1,,$C77,))*$N77/$E78)))} | Y78: {=IF(OR($D77=0,Y77="",$N77=0),"", IF($G77=$E$6, SUM(IF(OFFSET($R$23,,,($F77-1)*3-2,$D$3)=Y77,OFFSET($R$25,,,($F77-1)*3-2,$D$3)*OFFSET($B$23,1,,($F77-1)*3-2,1))), IF($D77=1,$N77, SUMIF(OFFSET(Orçamento!$D$1,$B77-1,,$C77,),$F78&"-"&Y77,OFFSET(Orçamento!$I$1,$B77-1,,$C77,))*$N77/$E78)))} | ... AK78: {=IF(OR($D77=0,AK77="",$N77=0),"", IF($G77=$E$6, SUM(IF(OFFSET($R$23,,,($F77-1)*3-2,$D$3)=AK77,OFFSET($R$25,,,($F77-1)*3-2,$D$3)*OFFSET($B$23,1,,($F77-1)*3-2,1))), IF($D77=1,$N77, SUMIF(OFFSET(Orçamento!$D$1,$B77-1,,$C77,),$F78&"-"&AK77,OFFSET(Orçamento!$I$1,$B77-1,,$C77,))*$N77/$E78)))}
B79: {=IF($F77>$E$2,"",IF($F$2=1,INDEX('QC rev00'!$M$10:$T$120,$F79,5),IF($F$2=2,INDEX(#REF!,$F79,5),INDEX(#REF!,$F79,5))))} | C79: {=IF($F77>$E$2,"",IF($F$2=1,INDEX('QC rev00'!$M$10:$T$120,$F79,6),IF($F$2=2,INDEX(#REF!,$F79,6),INDEX(#REF!,$F79,6))))} | F79: =IF(F77>$E$2,"",MATCH(F77,'QC rev00'!$C$10:$C$120,)) | Q79: Valor | R79: =IFERROR(R78*$O77,0) -> 0 | S79: =IFERROR(S78*$O77,0) -> 0 | T79: =IFERROR(T78*$O77,0) -> 0 | U79: =IFERROR(U78*$O77,0) -> 0 | V79: =IFERROR(V78*$O77,0) -> 0 | W79: =IFERROR(W78*$O77,0) -> 0 | X79: =IFERROR(X78*$O77,0) -> 0 | Y79: =IFERROR(Y78*$O77,0) -> 0 | ... AK79: =IFERROR(AK78*$O77,0) -> 0
B80: =IF($F80>$E$2,0,IF(E80<>"",MATCH(F81&" - Mapa",Orçamento!J:J,),0)) -> 0 | C80: =IF($D80>1,_xlfn.MAXIFS(Orçamento!G:G,Orçamento!J:J,F81&" - Mapa")+6-B80,0) -> 0 | D80: =IF($F80>$E$2,0,IF($G80=$E$6,$D$2,IF(E80<>"",_xlfn.MAXIFS(Orçamento!E:E,Orçamento!J:J,F81&" - Mapa"),0))) -> 0 | E80: =IF(F81="","",_xlfn.IFNA(MATCH($F81,'QC rev00'!$G$10:$G$120,),"")) | F80: {=OFFSET(F80,-3,,,)+1} -> 20 | G80: {=IF($F80>$E$2,"",IF($F$2=1,INDEX('QC rev00'!$M$10:$T$120,$F82,2),IF($F$2=2,INDEX(#REF!,$F82,2),INDEX(#REF!,$F82,2))))} | H80: {=IF($F80>$E$2,"",IF($F$2=1,INDEX('QC rev00'!$M$10:$T$120,$F82,3),IF($F$2=2,INDEX(#REF!,$F82,3),INDEX(#REF!,$F82,3))))} | L80: {=IF($F80>$E$2,"",IF($F$2=1,INDEX('QC rev00'!$M$10:$T$120,$F82,7),IF($F$2=2,INDEX(#REF!,$F82,7),INDEX(#REF!,$F82,7))))} | M80: {=IF($F80>$E$2,"",IF($F$2=1,INDEX('QC rev00'!$M$10:$T$120,$F82,8),IF($F$2=2,INDEX(#REF!,$F82,8),INDEX(#REF!,$F82,8))))} | N80: {=IF($F80>$E$2,0,IF(_xlfn.IFNA(MATCH($G80,Listas!$E$4:$E$206,),0)>0,$F$5,IF($F$2=1,INDEX('QC rev00'!$M$10:$U$120,$F82,9),IF($F$2=2,INDEX(#REF!,$F82,9),INDEX(#REF!,$F82,9)))))} -> 0 | O80: {=IF($F80>$E$2,0,IF(_xlfn.IFNA(MATCH($G80,Listas!$E$4:$E$206,),0)>0,1,IF($H$10=0,0,IF($F$2=1,INDEX('QC rev00'!$M$10:$BC$120,$F82,9+$F$3),IF($F$2=2,INDEX(#REF!,$F82,9+$F$3),INDEX(#REF!,$F82,9+$F$3)))*IF($E$5="X",1,1-$B82-$C82))))} -> 0 | P80: =N80*O80 -> 0 | Q80: IP | R80: {=IF($D80=0,"",IF($G80=$E$6,INDEX(Orçamento!$U:$U,MATCH(R$21,Orçamento!$C:$C,),1),INDEX(Orçamento!$U:$U,$B80,1)))} | S80: =IF(S$21>$D80,"",IF($G80=$E$6,INDEX(Orçamento!$U:$U,MATCH(S$21,Orçamento!$C:$C,),1),INDEX(Orçamento!$U:$U,MATCH(S$21&"-"&$F81,Orçamento!$F:$F,),1))) | T80: =IF(T$21>$D80,"",IF($G80=$E$6,INDEX(Orçamento!$U:$U,MATCH(T$21,Orçamento!$C:$C,),1),INDEX(Orçamento!$U:$U,MATCH(T$21&"-"&$F81,Orçamento!$F:$F,),1))) | U80: =IF(U$21>$D80,"",IF($G80=$E$6,INDEX(Orçamento!$U:$U,MATCH(U$21,Orçamento!$C:$C,),1),INDEX(Orçamento!$U:$U,MATCH(U$21&"-"&$F81,Orçamento!$F:$F,),1))) | V80: =IF(V$21>$D80,"",IF($G80=$E$6,INDEX(Orçamento!$U:$U,MATCH(V$21,Orçamento!$C:$C,),1),INDEX(Orçamento!$U:$U,MATCH(V$21&"-"&$F81,Orçamento!$F:$F,),1))) | W80: =IF(W$21>$D80,"",IF($G80=$E$6,INDEX(Orçamento!$U:$U,MATCH(W$21,Orçamento!$C:$C,),1),INDEX(Orçamento!$U:$U,MATCH(W$21&"-"&$F81,Orçamento!$F:$F,),1))) | X80: =IF(X$21>$D80,"",IF($G80=$E$6,INDEX(Orçamento!$U:$U,MATCH(X$21,Orçamento!$C:$C,),1),INDEX(Orçamento!$U:$U,MATCH(X$21&"-"&$F81,Orçamento!$F:$F,),1))) | Y80: =IF(Y$21>$D80,"",IF($G80=$E$6,INDEX(Orçamento!$U:$U,MATCH(Y$21,Orçamento!$C:$C,),1),INDEX(Orçamento!$U:$U,MATCH(Y$21&"-"&$F81,Orçamento!$F:$F,),1))) | Z80: =IF(Z$21>$D80,"",IF($G80=$E$6,INDEX(Orçamento!$U:$U,MATCH(Z$21,Orçamento!$C:$C,),1),INDEX(Orçamento!$U:$U,MATCH(Z$21&"-"&$F81,Orçamento!$F:$F,),1))) | ... AK80: =IF(AK$21>$D80,"",IF($G80=$E$6,INDEX(Orçamento!$U:$U,MATCH(AK$21,Orçamento!$C:$C,),1),INDEX(Orçamento!$U:$U,MATCH(AK$21&"-"&$F81,Orçamento!$F:$F,),1)))
B81: =IF($F80>$E$2,0,(1/(1-B82-C82))*(B82+C82)) -> 0 | C81: {=IF(ROUND(SUM(IF(R80:AK80<>"",(R81:AK81)))-N80,3)<>0,"X",0)} -> 0 | E81: {=IF($F80>$E$2,"",INDEX('QC rev00'!$J$9:$J$120,1+E80,1))} | F81: {=IF($F80>$E$2,"",IF($F$2=1,INDEX('QC rev00'!$M$10:$T$120,$F82,1),IF($F$2=2,INDEX(#REF!,$F82,1),INDEX(#REF!,$F82,1))))} | Q81: Qtd | R81: {=IF(OR($D80=0,R80="",$N80=0),"", IF($G80=$E$6, SUM(IF(OFFSET($R$23,,,($F80-1)*3-2,$D$3)=R80,OFFSET($R$25,,,($F80-1)*3-2,$D$3)*OFFSET($B$23,1,,($F80-1)*3-2,1))), IF($D80=1,$N80, SUMIF(OFFSET(Orçamento!$D$1,$B80-1,,$C80,),$F81&"-"&R80,OFFSET(Orçamento!$I$1,$B80-1,,$C80,))*$N80/$E81)))} | S81: {=IF(OR($D80=0,S80="",$N80=0),"", IF($G80=$E$6, SUM(IF(OFFSET($R$23,,,($F80-1)*3-2,$D$3)=S80,OFFSET($R$25,,,($F80-1)*3-2,$D$3)*OFFSET($B$23,1,,($F80-1)*3-2,1))), IF($D80=1,$N80, SUMIF(OFFSET(Orçamento!$D$1,$B80-1,,$C80,),$F81&"-"&S80,OFFSET(Orçamento!$I$1,$B80-1,,$C80,))*$N80/$E81)))} | T81: {=IF(OR($D80=0,T80="",$N80=0),"", IF($G80=$E$6, SUM(IF(OFFSET($R$23,,,($F80-1)*3-2,$D$3)=T80,OFFSET($R$25,,,($F80-1)*3-2,$D$3)*OFFSET($B$23,1,,($F80-1)*3-2,1))), IF($D80=1,$N80, SUMIF(OFFSET(Orçamento!$D$1,$B80-1,,$C80,),$F81&"-"&T80,OFFSET(Orçamento!$I$1,$B80-1,,$C80,))*$N80/$E81)))} | U81: {=IF(OR($D80=0,U80="",$N80=0),"", IF($G80=$E$6, SUM(IF(OFFSET($R$23,,,($F80-1)*3-2,$D$3)=U80,OFFSET($R$25,,,($F80-1)*3-2,$D$3)*OFFSET($B$23,1,,($F80-1)*3-2,1))), IF($D80=1,$N80, SUMIF(OFFSET(Orçamento!$D$1,$B80-1,,$C80,),$F81&"-"&U80,OFFSET(Orçamento!$I$1,$B80-1,,$C80,))*$N80/$E81)))} | V81: {=IF(OR($D80=0,V80="",$N80=0),"", IF($G80=$E$6, SUM(IF(OFFSET($R$23,,,($F80-1)*3-2,$D$3)=V80,OFFSET($R$25,,,($F80-1)*3-2,$D$3)*OFFSET($B$23,1,,($F80-1)*3-2,1))), IF($D80=1,$N80, SUMIF(OFFSET(Orçamento!$D$1,$B80-1,,$C80,),$F81&"-"&V80,OFFSET(Orçamento!$I$1,$B80-1,,$C80,))*$N80/$E81)))} | W81: {=IF(OR($D80=0,W80="",$N80=0),"", IF($G80=$E$6, SUM(IF(OFFSET($R$23,,,($F80-1)*3-2,$D$3)=W80,OFFSET($R$25,,,($F80-1)*3-2,$D$3)*OFFSET($B$23,1,,($F80-1)*3-2,1))), IF($D80=1,$N80, SUMIF(OFFSET(Orçamento!$D$1,$B80-1,,$C80,),$F81&"-"&W80,OFFSET(Orçamento!$I$1,$B80-1,,$C80,))*$N80/$E81)))} | X81: {=IF(OR($D80=0,X80="",$N80=0),"", IF($G80=$E$6, SUM(IF(OFFSET($R$23,,,($F80-1)*3-2,$D$3)=X80,OFFSET($R$25,,,($F80-1)*3-2,$D$3)*OFFSET($B$23,1,,($F80-1)*3-2,1))), IF($D80=1,$N80, SUMIF(OFFSET(Orçamento!$D$1,$B80-1,,$C80,),$F81&"-"&X80,OFFSET(Orçamento!$I$1,$B80-1,,$C80,))*$N80/$E81)))} | Y81: {=IF(OR($D80=0,Y80="",$N80=0),"", IF($G80=$E$6, SUM(IF(OFFSET($R$23,,,($F80-1)*3-2,$D$3)=Y80,OFFSET($R$25,,,($F80-1)*3-2,$D$3)*OFFSET($B$23,1,,($F80-1)*3-2,1))), IF($D80=1,$N80, SUMIF(OFFSET(Orçamento!$D$1,$B80-1,,$C80,),$F81&"-"&Y80,OFFSET(Orçamento!$I$1,$B80-1,,$C80,))*$N80/$E81)))} | ... AK81: {=IF(OR($D80=0,AK80="",$N80=0),"", IF($G80=$E$6, SUM(IF(OFFSET($R$23,,,($F80-1)*3-2,$D$3)=AK80,OFFSET($R$25,,,($F80-1)*3-2,$D$3)*OFFSET($B$23,1,,($F80-1)*3-2,1))), IF($D80=1,$N80, SUMIF(OFFSET(Orçamento!$D$1,$B80-1,,$C80,),$F81&"-"&AK80,OFFSET(Orçamento!$I$1,$B80-1,,$C80,))*$N80/$E81)))}
B82: {=IF($F80>$E$2,"",IF($F$2=1,INDEX('QC rev00'!$M$10:$T$120,$F82,5),IF($F$2=2,INDEX(#REF!,$F82,5),INDEX(#REF!,$F82,5))))} | C82: {=IF($F80>$E$2,"",IF($F$2=1,INDEX('QC rev00'!$M$10:$T$120,$F82,6),IF($F$2=2,INDEX(#REF!,$F82,6),INDEX(#REF!,$F82,6))))} | F82: =IF(F80>$E$2,"",MATCH(F80,'QC rev00'!$C$10:$C$120,)) | Q82: Valor | R82: =IFERROR(R81*$O80,0) -> 0 | S82: =IFERROR(S81*$O80,0) -> 0 | T82: =IFERROR(T81*$O80,0) -> 0 | U82: =IFERROR(U81*$O80,0) -> 0 | V82: =IFERROR(V81*$O80,0) -> 0 | W82: =IFERROR(W81*$O80,0) -> 0 | X82: =IFERROR(X81*$O80,0) -> 0 | Y82: =IFERROR(Y81*$O80,0) -> 0 | ... AK82: =IFERROR(AK81*$O80,0) -> 0
B83: =IF($F83>$E$2,0,IF(E83<>"",MATCH(F84&" - Mapa",Orçamento!J:J,),0)) -> 0 | C83: =IF($D83>1,_xlfn.MAXIFS(Orçamento!G:G,Orçamento!J:J,F84&" - Mapa")+6-B83,0) -> 0 | D83: =IF($F83>$E$2,0,IF($G83=$E$6,$D$2,IF(E83<>"",_xlfn.MAXIFS(Orçamento!E:E,Orçamento!J:J,F84&" - Mapa"),0))) -> 0 | E83: =IF(F84="","",_xlfn.IFNA(MATCH($F84,'QC rev00'!$G$10:$G$120,),"")) | F83: {=OFFSET(F83,-3,,,)+1} -> 21 | G83: {=IF($F83>$E$2,"",IF($F$2=1,INDEX('QC rev00'!$M$10:$T$120,$F85,2),IF($F$2=2,INDEX(#REF!,$F85,2),INDEX(#REF!,$F85,2))))} | H83: {=IF($F83>$E$2,"",IF($F$2=1,INDEX('QC rev00'!$M$10:$T$120,$F85,3),IF($F$2=2,INDEX(#REF!,$F85,3),INDEX(#REF!,$F85,3))))} | L83: {=IF($F83>$E$2,"",IF($F$2=1,INDEX('QC rev00'!$M$10:$T$120,$F85,7),IF($F$2=2,INDEX(#REF!,$F85,7),INDEX(#REF!,$F85,7))))} | M83: {=IF($F83>$E$2,"",IF($F$2=1,INDEX('QC rev00'!$M$10:$T$120,$F85,8),IF($F$2=2,INDEX(#REF!,$F85,8),INDEX(#REF!,$F85,8))))} | N83: {=IF($F83>$E$2,0,IF(_xlfn.IFNA(MATCH($G83,Listas!$E$4:$E$206,),0)>0,$F$5,IF($F$2=1,INDEX('QC rev00'!$M$10:$U$120,$F85,9),IF($F$2=2,INDEX(#REF!,$F85,9),INDEX(#REF!,$F85,9)))))} -> 0 | O83: {=IF($F83>$E$2,0,IF(_xlfn.IFNA(MATCH($G83,Listas!$E$4:$E$206,),0)>0,1,IF($H$10=0,0,IF($F$2=1,INDEX('QC rev00'!$M$10:$BC$120,$F85,9+$F$3),IF($F$2=2,INDEX(#REF!,$F85,9+$F$3),INDEX(#REF!,$F85,9+$F$3)))*IF($E$5="X",1,1-$B85-$C85))))} -> 0 | P83: =N83*O83 -> 0 | Q83: IP | R83: {=IF($D83=0,"",IF($G83=$E$6,INDEX(Orçamento!$U:$U,MATCH(R$21,Orçamento!$C:$C,),1),INDEX(Orçamento!$U:$U,$B83,1)))} | S83: =IF(S$21>$D83,"",IF($G83=$E$6,INDEX(Orçamento!$U:$U,MATCH(S$21,Orçamento!$C:$C,),1),INDEX(Orçamento!$U:$U,MATCH(S$21&"-"&$F84,Orçamento!$F:$F,),1))) | T83: =IF(T$21>$D83,"",IF($G83=$E$6,INDEX(Orçamento!$U:$U,MATCH(T$21,Orçamento!$C:$C,),1),INDEX(Orçamento!$U:$U,MATCH(T$21&"-"&$F84,Orçamento!$F:$F,),1))) | U83: =IF(U$21>$D83,"",IF($G83=$E$6,INDEX(Orçamento!$U:$U,MATCH(U$21,Orçamento!$C:$C,),1),INDEX(Orçamento!$U:$U,MATCH(U$21&"-"&$F84,Orçamento!$F:$F,),1))) | V83: =IF(V$21>$D83,"",IF($G83=$E$6,INDEX(Orçamento!$U:$U,MATCH(V$21,Orçamento!$C:$C,),1),INDEX(Orçamento!$U:$U,MATCH(V$21&"-"&$F84,Orçamento!$F:$F,),1))) | W83: =IF(W$21>$D83,"",IF($G83=$E$6,INDEX(Orçamento!$U:$U,MATCH(W$21,Orçamento!$C:$C,),1),INDEX(Orçamento!$U:$U,MATCH(W$21&"-"&$F84,Orçamento!$F:$F,),1))) | X83: =IF(X$21>$D83,"",IF($G83=$E$6,INDEX(Orçamento!$U:$U,MATCH(X$21,Orçamento!$C:$C,),1),INDEX(Orçamento!$U:$U,MATCH(X$21&"-"&$F84,Orçamento!$F:$F,),1))) | Y83: =IF(Y$21>$D83,"",IF($G83=$E$6,INDEX(Orçamento!$U:$U,MATCH(Y$21,Orçamento!$C:$C,),1),INDEX(Orçamento!$U:$U,MATCH(Y$21&"-"&$F84,Orçamento!$F:$F,),1))) | Z83: =IF(Z$21>$D83,"",IF($G83=$E$6,INDEX(Orçamento!$U:$U,MATCH(Z$21,Orçamento!$C:$C,),1),INDEX(Orçamento!$U:$U,MATCH(Z$21&"-"&$F84,Orçamento!$F:$F,),1))) | ... AK83: =IF(AK$21>$D83,"",IF($G83=$E$6,INDEX(Orçamento!$U:$U,MATCH(AK$21,Orçamento!$C:$C,),1),INDEX(Orçamento!$U:$U,MATCH(AK$21&"-"&$F84,Orçamento!$F:$F,),1)))
B84: =IF($F83>$E$2,0,(1/(1-B85-C85))*(B85+C85)) -> 0 | C84: {=IF(ROUND(SUM(IF(R83:AK83<>"",(R84:AK84)))-N83,3)<>0,"X",0)} -> 0 | E84: {=IF($F83>$E$2,"",INDEX('QC rev00'!$J$9:$J$120,1+E83,1))} | F84: {=IF($F83>$E$2,"",IF($F$2=1,INDEX('QC rev00'!$M$10:$T$120,$F85,1),IF($F$2=2,INDEX(#REF!,$F85,1),INDEX(#REF!,$F85,1))))} | Q84: Qtd | R84: {=IF(OR($D83=0,R83="",$N83=0),"", IF($G83=$E$6, SUM(IF(OFFSET($R$23,,,($F83-1)*3-2,$D$3)=R83,OFFSET($R$25,,,($F83-1)*3-2,$D$3)*OFFSET($B$23,1,,($F83-1)*3-2,1))), IF($D83=1,$N83, SUMIF(OFFSET(Orçamento!$D$1,$B83-1,,$C83,),$F84&"-"&R83,OFFSET(Orçamento!$I$1,$B83-1,,$C83,))*$N83/$E84)))} | S84: {=IF(OR($D83=0,S83="",$N83=0),"", IF($G83=$E$6, SUM(IF(OFFSET($R$23,,,($F83-1)*3-2,$D$3)=S83,OFFSET($R$25,,,($F83-1)*3-2,$D$3)*OFFSET($B$23,1,,($F83-1)*3-2,1))), IF($D83=1,$N83, SUMIF(OFFSET(Orçamento!$D$1,$B83-1,,$C83,),$F84&"-"&S83,OFFSET(Orçamento!$I$1,$B83-1,,$C83,))*$N83/$E84)))} | T84: {=IF(OR($D83=0,T83="",$N83=0),"", IF($G83=$E$6, SUM(IF(OFFSET($R$23,,,($F83-1)*3-2,$D$3)=T83,OFFSET($R$25,,,($F83-1)*3-2,$D$3)*OFFSET($B$23,1,,($F83-1)*3-2,1))), IF($D83=1,$N83, SUMIF(OFFSET(Orçamento!$D$1,$B83-1,,$C83,),$F84&"-"&T83,OFFSET(Orçamento!$I$1,$B83-1,,$C83,))*$N83/$E84)))} | U84: {=IF(OR($D83=0,U83="",$N83=0),"", IF($G83=$E$6, SUM(IF(OFFSET($R$23,,,($F83-1)*3-2,$D$3)=U83,OFFSET($R$25,,,($F83-1)*3-2,$D$3)*OFFSET($B$23,1,,($F83-1)*3-2,1))), IF($D83=1,$N83, SUMIF(OFFSET(Orçamento!$D$1,$B83-1,,$C83,),$F84&"-"&U83,OFFSET(Orçamento!$I$1,$B83-1,,$C83,))*$N83/$E84)))} | V84: {=IF(OR($D83=0,V83="",$N83=0),"", IF($G83=$E$6, SUM(IF(OFFSET($R$23,,,($F83-1)*3-2,$D$3)=V83,OFFSET($R$25,,,($F83-1)*3-2,$D$3)*OFFSET($B$23,1,,($F83-1)*3-2,1))), IF($D83=1,$N83, SUMIF(OFFSET(Orçamento!$D$1,$B83-1,,$C83,),$F84&"-"&V83,OFFSET(Orçamento!$I$1,$B83-1,,$C83,))*$N83/$E84)))} | W84: {=IF(OR($D83=0,W83="",$N83=0),"", IF($G83=$E$6, SUM(IF(OFFSET($R$23,,,($F83-1)*3-2,$D$3)=W83,OFFSET($R$25,,,($F83-1)*3-2,$D$3)*OFFSET($B$23,1,,($F83-1)*3-2,1))), IF($D83=1,$N83, SUMIF(OFFSET(Orçamento!$D$1,$B83-1,,$C83,),$F84&"-"&W83,OFFSET(Orçamento!$I$1,$B83-1,,$C83,))*$N83/$E84)))} | X84: {=IF(OR($D83=0,X83="",$N83=0),"", IF($G83=$E$6, SUM(IF(OFFSET($R$23,,,($F83-1)*3-2,$D$3)=X83,OFFSET($R$25,,,($F83-1)*3-2,$D$3)*OFFSET($B$23,1,,($F83-1)*3-2,1))), IF($D83=1,$N83, SUMIF(OFFSET(Orçamento!$D$1,$B83-1,,$C83,),$F84&"-"&X83,OFFSET(Orçamento!$I$1,$B83-1,,$C83,))*$N83/$E84)))} | Y84: {=IF(OR($D83=0,Y83="",$N83=0),"", IF($G83=$E$6, SUM(IF(OFFSET($R$23,,,($F83-1)*3-2,$D$3)=Y83,OFFSET($R$25,,,($F83-1)*3-2,$D$3)*OFFSET($B$23,1,,($F83-1)*3-2,1))), IF($D83=1,$N83, SUMIF(OFFSET(Orçamento!$D$1,$B83-1,,$C83,),$F84&"-"&Y83,OFFSET(Orçamento!$I$1,$B83-1,,$C83,))*$N83/$E84)))} | ... AK84: {=IF(OR($D83=0,AK83="",$N83=0),"", IF($G83=$E$6, SUM(IF(OFFSET($R$23,,,($F83-1)*3-2,$D$3)=AK83,OFFSET($R$25,,,($F83-1)*3-2,$D$3)*OFFSET($B$23,1,,($F83-1)*3-2,1))), IF($D83=1,$N83, SUMIF(OFFSET(Orçamento!$D$1,$B83-1,,$C83,),$F84&"-"&AK83,OFFSET(Orçamento!$I$1,$B83-1,,$C83,))*$N83/$E84)))}
B85: {=IF($F83>$E$2,"",IF($F$2=1,INDEX('QC rev00'!$M$10:$T$120,$F85,5),IF($F$2=2,INDEX(#REF!,$F85,5),INDEX(#REF!,$F85,5))))} | C85: {=IF($F83>$E$2,"",IF($F$2=1,INDEX('QC rev00'!$M$10:$T$120,$F85,6),IF($F$2=2,INDEX(#REF!,$F85,6),INDEX(#REF!,$F85,6))))} | F85: =IF(F83>$E$2,"",MATCH(F83,'QC rev00'!$C$10:$C$120,)) | Q85: Valor | R85: =IFERROR(R84*$O83,0) -> 0 | S85: =IFERROR(S84*$O83,0) -> 0 | T85: =IFERROR(T84*$O83,0) -> 0 | U85: =IFERROR(U84*$O83,0) -> 0 | V85: =IFERROR(V84*$O83,0) -> 0 | W85: =IFERROR(W84*$O83,0) -> 0 | X85: =IFERROR(X84*$O83,0) -> 0 | Y85: =IFERROR(Y84*$O83,0) -> 0 | ... AK85: =IFERROR(AK84*$O83,0) -> 0
B86: =IF($F86>$E$2,0,IF(E86<>"",MATCH(F87&" - Mapa",Orçamento!J:J,),0)) -> 0 | C86: =IF($D86>1,_xlfn.MAXIFS(Orçamento!G:G,Orçamento!J:J,F87&" - Mapa")+6-B86,0) -> 0 | D86: =IF($F86>$E$2,0,IF($G86=$E$6,$D$2,IF(E86<>"",_xlfn.MAXIFS(Orçamento!E:E,Orçamento!J:J,F87&" - Mapa"),0))) -> 0 | E86: =IF(F87="","",_xlfn.IFNA(MATCH($F87,'QC rev00'!$G$10:$G$120,),"")) | F86: {=OFFSET(F86,-3,,,)+1} -> 22 | G86: {=IF($F86>$E$2,"",IF($F$2=1,INDEX('QC rev00'!$M$10:$T$120,$F88,2),IF($F$2=2,INDEX(#REF!,$F88,2),INDEX(#REF!,$F88,2))))} | H86: {=IF($F86>$E$2,"",IF($F$2=1,INDEX('QC rev00'!$M$10:$T$120,$F88,3),IF($F$2=2,INDEX(#REF!,$F88,3),INDEX(#REF!,$F88,3))))} | L86: {=IF($F86>$E$2,"",IF($F$2=1,INDEX('QC rev00'!$M$10:$T$120,$F88,7),IF($F$2=2,INDEX(#REF!,$F88,7),INDEX(#REF!,$F88,7))))} | M86: {=IF($F86>$E$2,"",IF($F$2=1,INDEX('QC rev00'!$M$10:$T$120,$F88,8),IF($F$2=2,INDEX(#REF!,$F88,8),INDEX(#REF!,$F88,8))))} | N86: {=IF($F86>$E$2,0,IF(_xlfn.IFNA(MATCH($G86,Listas!$E$4:$E$206,),0)>0,$F$5,IF($F$2=1,INDEX('QC rev00'!$M$10:$U$120,$F88,9),IF($F$2=2,INDEX(#REF!,$F88,9),INDEX(#REF!,$F88,9)))))} -> 0 | O86: {=IF($F86>$E$2,0,IF(_xlfn.IFNA(MATCH($G86,Listas!$E$4:$E$206,),0)>0,1,IF($H$10=0,0,IF($F$2=1,INDEX('QC rev00'!$M$10:$BC$120,$F88,9+$F$3),IF($F$2=2,INDEX(#REF!,$F88,9+$F$3),INDEX(#REF!,$F88,9+$F$3)))*IF($E$5="X",1,1-$B88-$C88))))} -> 0 | P86: =N86*O86 -> 0 | Q86: IP | R86: {=IF($D86=0,"",IF($G86=$E$6,INDEX(Orçamento!$U:$U,MATCH(R$21,Orçamento!$C:$C,),1),INDEX(Orçamento!$U:$U,$B86,1)))} | S86: =IF(S$21>$D86,"",IF($G86=$E$6,INDEX(Orçamento!$U:$U,MATCH(S$21,Orçamento!$C:$C,),1),INDEX(Orçamento!$U:$U,MATCH(S$21&"-"&$F87,Orçamento!$F:$F,),1))) | T86: =IF(T$21>$D86,"",IF($G86=$E$6,INDEX(Orçamento!$U:$U,MATCH(T$21,Orçamento!$C:$C,),1),INDEX(Orçamento!$U:$U,MATCH(T$21&"-"&$F87,Orçamento!$F:$F,),1))) | U86: =IF(U$21>$D86,"",IF($G86=$E$6,INDEX(Orçamento!$U:$U,MATCH(U$21,Orçamento!$C:$C,),1),INDEX(Orçamento!$U:$U,MATCH(U$21&"-"&$F87,Orçamento!$F:$F,),1))) | V86: =IF(V$21>$D86,"",IF($G86=$E$6,INDEX(Orçamento!$U:$U,MATCH(V$21,Orçamento!$C:$C,),1),INDEX(Orçamento!$U:$U,MATCH(V$21&"-"&$F87,Orçamento!$F:$F,),1))) | W86: =IF(W$21>$D86,"",IF($G86=$E$6,INDEX(Orçamento!$U:$U,MATCH(W$21,Orçamento!$C:$C,),1),INDEX(Orçamento!$U:$U,MATCH(W$21&"-"&$F87,Orçamento!$F:$F,),1))) | X86: =IF(X$21>$D86,"",IF($G86=$E$6,INDEX(Orçamento!$U:$U,MATCH(X$21,Orçamento!$C:$C,),1),INDEX(Orçamento!$U:$U,MATCH(X$21&"-"&$F87,Orçamento!$F:$F,),1))) | Y86: =IF(Y$21>$D86,"",IF($G86=$E$6,INDEX(Orçamento!$U:$U,MATCH(Y$21,Orçamento!$C:$C,),1),INDEX(Orçamento!$U:$U,MATCH(Y$21&"-"&$F87,Orçamento!$F:$F,),1))) | Z86: =IF(Z$21>$D86,"",IF($G86=$E$6,INDEX(Orçamento!$U:$U,MATCH(Z$21,Orçamento!$C:$C,),1),INDEX(Orçamento!$U:$U,MATCH(Z$21&"-"&$F87,Orçamento!$F:$F,),1))) | ... AK86: =IF(AK$21>$D86,"",IF($G86=$E$6,INDEX(Orçamento!$U:$U,MATCH(AK$21,Orçamento!$C:$C,),1),INDEX(Orçamento!$U:$U,MATCH(AK$21&"-"&$F87,Orçamento!$F:$F,),1)))
B87: =IF($F86>$E$2,0,(1/(1-B88-C88))*(B88+C88)) -> 0 | C87: {=IF(ROUND(SUM(IF(R86:AK86<>"",(R87:AK87)))-N86,3)<>0,"X",0)} -> 0 | E87: {=IF($F86>$E$2,"",INDEX('QC rev00'!$J$9:$J$120,1+E86,1))} | F87: {=IF($F86>$E$2,"",IF($F$2=1,INDEX('QC rev00'!$M$10:$T$120,$F88,1),IF($F$2=2,INDEX(#REF!,$F88,1),INDEX(#REF!,$F88,1))))} | Q87: Qtd | R87: {=IF(OR($D86=0,R86="",$N86=0),"", IF($G86=$E$6, SUM(IF(OFFSET($R$23,,,($F86-1)*3-2,$D$3)=R86,OFFSET($R$25,,,($F86-1)*3-2,$D$3)*OFFSET($B$23,1,,($F86-1)*3-2,1))), IF($D86=1,$N86, SUMIF(OFFSET(Orçamento!$D$1,$B86-1,,$C86,),$F87&"-"&R86,OFFSET(Orçamento!$I$1,$B86-1,,$C86,))*$N86/$E87)))} | S87: {=IF(OR($D86=0,S86="",$N86=0),"", IF($G86=$E$6, SUM(IF(OFFSET($R$23,,,($F86-1)*3-2,$D$3)=S86,OFFSET($R$25,,,($F86-1)*3-2,$D$3)*OFFSET($B$23,1,,($F86-1)*3-2,1))), IF($D86=1,$N86, SUMIF(OFFSET(Orçamento!$D$1,$B86-1,,$C86,),$F87&"-"&S86,OFFSET(Orçamento!$I$1,$B86-1,,$C86,))*$N86/$E87)))} | T87: {=IF(OR($D86=0,T86="",$N86=0),"", IF($G86=$E$6, SUM(IF(OFFSET($R$23,,,($F86-1)*3-2,$D$3)=T86,OFFSET($R$25,,,($F86-1)*3-2,$D$3)*OFFSET($B$23,1,,($F86-1)*3-2,1))), IF($D86=1,$N86, SUMIF(OFFSET(Orçamento!$D$1,$B86-1,,$C86,),$F87&"-"&T86,OFFSET(Orçamento!$I$1,$B86-1,,$C86,))*$N86/$E87)))} | U87: {=IF(OR($D86=0,U86="",$N86=0),"", IF($G86=$E$6, SUM(IF(OFFSET($R$23,,,($F86-1)*3-2,$D$3)=U86,OFFSET($R$25,,,($F86-1)*3-2,$D$3)*OFFSET($B$23,1,,($F86-1)*3-2,1))), IF($D86=1,$N86, SUMIF(OFFSET(Orçamento!$D$1,$B86-1,,$C86,),$F87&"-"&U86,OFFSET(Orçamento!$I$1,$B86-1,,$C86,))*$N86/$E87)))} | V87: {=IF(OR($D86=0,V86="",$N86=0),"", IF($G86=$E$6, SUM(IF(OFFSET($R$23,,,($F86-1)*3-2,$D$3)=V86,OFFSET($R$25,,,($F86-1)*3-2,$D$3)*OFFSET($B$23,1,,($F86-1)*3-2,1))), IF($D86=1,$N86, SUMIF(OFFSET(Orçamento!$D$1,$B86-1,,$C86,),$F87&"-"&V86,OFFSET(Orçamento!$I$1,$B86-1,,$C86,))*$N86/$E87)))} | W87: {=IF(OR($D86=0,W86="",$N86=0),"", IF($G86=$E$6, SUM(IF(OFFSET($R$23,,,($F86-1)*3-2,$D$3)=W86,OFFSET($R$25,,,($F86-1)*3-2,$D$3)*OFFSET($B$23,1,,($F86-1)*3-2,1))), IF($D86=1,$N86, SUMIF(OFFSET(Orçamento!$D$1,$B86-1,,$C86,),$F87&"-"&W86,OFFSET(Orçamento!$I$1,$B86-1,,$C86,))*$N86/$E87)))} | X87: {=IF(OR($D86=0,X86="",$N86=0),"", IF($G86=$E$6, SUM(IF(OFFSET($R$23,,,($F86-1)*3-2,$D$3)=X86,OFFSET($R$25,,,($F86-1)*3-2,$D$3)*OFFSET($B$23,1,,($F86-1)*3-2,1))), IF($D86=1,$N86, SUMIF(OFFSET(Orçamento!$D$1,$B86-1,,$C86,),$F87&"-"&X86,OFFSET(Orçamento!$I$1,$B86-1,,$C86,))*$N86/$E87)))} | Y87: {=IF(OR($D86=0,Y86="",$N86=0),"", IF($G86=$E$6, SUM(IF(OFFSET($R$23,,,($F86-1)*3-2,$D$3)=Y86,OFFSET($R$25,,,($F86-1)*3-2,$D$3)*OFFSET($B$23,1,,($F86-1)*3-2,1))), IF($D86=1,$N86, SUMIF(OFFSET(Orçamento!$D$1,$B86-1,,$C86,),$F87&"-"&Y86,OFFSET(Orçamento!$I$1,$B86-1,,$C86,))*$N86/$E87)))} | ... AK87: {=IF(OR($D86=0,AK86="",$N86=0),"", IF($G86=$E$6, SUM(IF(OFFSET($R$23,,,($F86-1)*3-2,$D$3)=AK86,OFFSET($R$25,,,($F86-1)*3-2,$D$3)*OFFSET($B$23,1,,($F86-1)*3-2,1))), IF($D86=1,$N86, SUMIF(OFFSET(Orçamento!$D$1,$B86-1,,$C86,),$F87&"-"&AK86,OFFSET(Orçamento!$I$1,$B86-1,,$C86,))*$N86/$E87)))}
B88: {=IF($F86>$E$2,"",IF($F$2=1,INDEX('QC rev00'!$M$10:$T$120,$F88,5),IF($F$2=2,INDEX(#REF!,$F88,5),INDEX(#REF!,$F88,5))))} | C88: {=IF($F86>$E$2,"",IF($F$2=1,INDEX('QC rev00'!$M$10:$T$120,$F88,6),IF($F$2=2,INDEX(#REF!,$F88,6),INDEX(#REF!,$F88,6))))} | F88: =IF(F86>$E$2,"",MATCH(F86,'QC rev00'!$C$10:$C$120,)) | Q88: Valor | R88: =IFERROR(R87*$O86,0) -> 0 | S88: =IFERROR(S87*$O86,0) -> 0 | T88: =IFERROR(T87*$O86,0) -> 0 | U88: =IFERROR(U87*$O86,0) -> 0 | V88: =IFERROR(V87*$O86,0) -> 0 | W88: =IFERROR(W87*$O86,0) -> 0 | X88: =IFERROR(X87*$O86,0) -> 0 | Y88: =IFERROR(Y87*$O86,0) -> 0 | ... AK88: =IFERROR(AK87*$O86,0) -> 0
B89: =IF($F89>$E$2,0,IF(E89<>"",MATCH(F90&" - Mapa",Orçamento!J:J,),0)) -> 0 | C89: =IF($D89>1,_xlfn.MAXIFS(Orçamento!G:G,Orçamento!J:J,F90&" - Mapa")+6-B89,0) -> 0 | D89: =IF($F89>$E$2,0,IF($G89=$E$6,$D$2,IF(E89<>"",_xlfn.MAXIFS(Orçamento!E:E,Orçamento!J:J,F90&" - Mapa"),0))) -> 0 | E89: =IF(F90="","",_xlfn.IFNA(MATCH($F90,'QC rev00'!$G$10:$G$120,),"")) | F89: {=OFFSET(F89,-3,,,)+1} -> 23 | G89: {=IF($F89>$E$2,"",IF($F$2=1,INDEX('QC rev00'!$M$10:$T$120,$F91,2),IF($F$2=2,INDEX(#REF!,$F91,2),INDEX(#REF!,$F91,2))))} | H89: {=IF($F89>$E$2,"",IF($F$2=1,INDEX('QC rev00'!$M$10:$T$120,$F91,3),IF($F$2=2,INDEX(#REF!,$F91,3),INDEX(#REF!,$F91,3))))} | L89: {=IF($F89>$E$2,"",IF($F$2=1,INDEX('QC rev00'!$M$10:$T$120,$F91,7),IF($F$2=2,INDEX(#REF!,$F91,7),INDEX(#REF!,$F91,7))))} | M89: {=IF($F89>$E$2,"",IF($F$2=1,INDEX('QC rev00'!$M$10:$T$120,$F91,8),IF($F$2=2,INDEX(#REF!,$F91,8),INDEX(#REF!,$F91,8))))} | N89: {=IF($F89>$E$2,0,IF(_xlfn.IFNA(MATCH($G89,Listas!$E$4:$E$206,),0)>0,$F$5,IF($F$2=1,INDEX('QC rev00'!$M$10:$U$120,$F91,9),IF($F$2=2,INDEX(#REF!,$F91,9),INDEX(#REF!,$F91,9)))))} -> 0 | O89: {=IF($F89>$E$2,0,IF(_xlfn.IFNA(MATCH($G89,Listas!$E$4:$E$206,),0)>0,1,IF($H$10=0,0,IF($F$2=1,INDEX('QC rev00'!$M$10:$BC$120,$F91,9+$F$3),IF($F$2=2,INDEX(#REF!,$F91,9+$F$3),INDEX(#REF!,$F91,9+$F$3)))*IF($E$5="X",1,1-$B91-$C91))))} -> 0 | P89: =N89*O89 -> 0 | Q89: IP | R89: {=IF($D89=0,"",IF($G89=$E$6,INDEX(Orçamento!$U:$U,MATCH(R$21,Orçamento!$C:$C,),1),INDEX(Orçamento!$U:$U,$B89,1)))} | S89: =IF(S$21>$D89,"",IF($G89=$E$6,INDEX(Orçamento!$U:$U,MATCH(S$21,Orçamento!$C:$C,),1),INDEX(Orçamento!$U:$U,MATCH(S$21&"-"&$F90,Orçamento!$F:$F,),1))) | T89: =IF(T$21>$D89,"",IF($G89=$E$6,INDEX(Orçamento!$U:$U,MATCH(T$21,Orçamento!$C:$C,),1),INDEX(Orçamento!$U:$U,MATCH(T$21&"-"&$F90,Orçamento!$F:$F,),1))) | U89: =IF(U$21>$D89,"",IF($G89=$E$6,INDEX(Orçamento!$U:$U,MATCH(U$21,Orçamento!$C:$C,),1),INDEX(Orçamento!$U:$U,MATCH(U$21&"-"&$F90,Orçamento!$F:$F,),1))) | V89: =IF(V$21>$D89,"",IF($G89=$E$6,INDEX(Orçamento!$U:$U,MATCH(V$21,Orçamento!$C:$C,),1),INDEX(Orçamento!$U:$U,MATCH(V$21&"-"&$F90,Orçamento!$F:$F,),1))) | W89: =IF(W$21>$D89,"",IF($G89=$E$6,INDEX(Orçamento!$U:$U,MATCH(W$21,Orçamento!$C:$C,),1),INDEX(Orçamento!$U:$U,MATCH(W$21&"-"&$F90,Orçamento!$F:$F,),1))) | X89: =IF(X$21>$D89,"",IF($G89=$E$6,INDEX(Orçamento!$U:$U,MATCH(X$21,Orçamento!$C:$C,),1),INDEX(Orçamento!$U:$U,MATCH(X$21&"-"&$F90,Orçamento!$F:$F,),1))) | Y89: =IF(Y$21>$D89,"",IF($G89=$E$6,INDEX(Orçamento!$U:$U,MATCH(Y$21,Orçamento!$C:$C,),1),INDEX(Orçamento!$U:$U,MATCH(Y$21&"-"&$F90,Orçamento!$F:$F,),1))) | Z89: =IF(Z$21>$D89,"",IF($G89=$E$6,INDEX(Orçamento!$U:$U,MATCH(Z$21,Orçamento!$C:$C,),1),INDEX(Orçamento!$U:$U,MATCH(Z$21&"-"&$F90,Orçamento!$F:$F,),1))) | ... AK89: =IF(AK$21>$D89,"",IF($G89=$E$6,INDEX(Orçamento!$U:$U,MATCH(AK$21,Orçamento!$C:$C,),1),INDEX(Orçamento!$U:$U,MATCH(AK$21&"-"&$F90,Orçamento!$F:$F,),1)))
B90: =IF($F89>$E$2,0,(1/(1-B91-C91))*(B91+C91)) -> 0 | C90: {=IF(ROUND(SUM(IF(R89:AK89<>"",(R90:AK90)))-N89,3)<>0,"X",0)} -> 0 | E90: {=IF($F89>$E$2,"",INDEX('QC rev00'!$J$9:$J$120,1+E89,1))} | F90: {=IF($F89>$E$2,"",IF($F$2=1,INDEX('QC rev00'!$M$10:$T$120,$F91,1),IF($F$2=2,INDEX(#REF!,$F91,1),INDEX(#REF!,$F91,1))))} | Q90: Qtd | R90: {=IF(OR($D89=0,R89="",$N89=0),"", IF($G89=$E$6, SUM(IF(OFFSET($R$23,,,($F89-1)*3-2,$D$3)=R89,OFFSET($R$25,,,($F89-1)*3-2,$D$3)*OFFSET($B$23,1,,($F89-1)*3-2,1))), IF($D89=1,$N89, SUMIF(OFFSET(Orçamento!$D$1,$B89-1,,$C89,),$F90&"-"&R89,OFFSET(Orçamento!$I$1,$B89-1,,$C89,))*$N89/$E90)))} | S90: {=IF(OR($D89=0,S89="",$N89=0),"", IF($G89=$E$6, SUM(IF(OFFSET($R$23,,,($F89-1)*3-2,$D$3)=S89,OFFSET($R$25,,,($F89-1)*3-2,$D$3)*OFFSET($B$23,1,,($F89-1)*3-2,1))), IF($D89=1,$N89, SUMIF(OFFSET(Orçamento!$D$1,$B89-1,,$C89,),$F90&"-"&S89,OFFSET(Orçamento!$I$1,$B89-1,,$C89,))*$N89/$E90)))} | T90: {=IF(OR($D89=0,T89="",$N89=0),"", IF($G89=$E$6, SUM(IF(OFFSET($R$23,,,($F89-1)*3-2,$D$3)=T89,OFFSET($R$25,,,($F89-1)*3-2,$D$3)*OFFSET($B$23,1,,($F89-1)*3-2,1))), IF($D89=1,$N89, SUMIF(OFFSET(Orçamento!$D$1,$B89-1,,$C89,),$F90&"-"&T89,OFFSET(Orçamento!$I$1,$B89-1,,$C89,))*$N89/$E90)))} | U90: {=IF(OR($D89=0,U89="",$N89=0),"", IF($G89=$E$6, SUM(IF(OFFSET($R$23,,,($F89-1)*3-2,$D$3)=U89,OFFSET($R$25,,,($F89-1)*3-2,$D$3)*OFFSET($B$23,1,,($F89-1)*3-2,1))), IF($D89=1,$N89, SUMIF(OFFSET(Orçamento!$D$1,$B89-1,,$C89,),$F90&"-"&U89,OFFSET(Orçamento!$I$1,$B89-1,,$C89,))*$N89/$E90)))} | V90: {=IF(OR($D89=0,V89="",$N89=0),"", IF($G89=$E$6, SUM(IF(OFFSET($R$23,,,($F89-1)*3-2,$D$3)=V89,OFFSET($R$25,,,($F89-1)*3-2,$D$3)*OFFSET($B$23,1,,($F89-1)*3-2,1))), IF($D89=1,$N89, SUMIF(OFFSET(Orçamento!$D$1,$B89-1,,$C89,),$F90&"-"&V89,OFFSET(Orçamento!$I$1,$B89-1,,$C89,))*$N89/$E90)))} | W90: {=IF(OR($D89=0,W89="",$N89=0),"", IF($G89=$E$6, SUM(IF(OFFSET($R$23,,,($F89-1)*3-2,$D$3)=W89,OFFSET($R$25,,,($F89-1)*3-2,$D$3)*OFFSET($B$23,1,,($F89-1)*3-2,1))), IF($D89=1,$N89, SUMIF(OFFSET(Orçamento!$D$1,$B89-1,,$C89,),$F90&"-"&W89,OFFSET(Orçamento!$I$1,$B89-1,,$C89,))*$N89/$E90)))} | X90: {=IF(OR($D89=0,X89="",$N89=0),"", IF($G89=$E$6, SUM(IF(OFFSET($R$23,,,($F89-1)*3-2,$D$3)=X89,OFFSET($R$25,,,($F89-1)*3-2,$D$3)*OFFSET($B$23,1,,($F89-1)*3-2,1))), IF($D89=1,$N89, SUMIF(OFFSET(Orçamento!$D$1,$B89-1,,$C89,),$F90&"-"&X89,OFFSET(Orçamento!$I$1,$B89-1,,$C89,))*$N89/$E90)))} | Y90: {=IF(OR($D89=0,Y89="",$N89=0),"", IF($G89=$E$6, SUM(IF(OFFSET($R$23,,,($F89-1)*3-2,$D$3)=Y89,OFFSET($R$25,,,($F89-1)*3-2,$D$3)*OFFSET($B$23,1,,($F89-1)*3-2,1))), IF($D89=1,$N89, SUMIF(OFFSET(Orçamento!$D$1,$B89-1,,$C89,),$F90&"-"&Y89,OFFSET(Orçamento!$I$1,$B89-1,,$C89,))*$N89/$E90)))} | ... AK90: {=IF(OR($D89=0,AK89="",$N89=0),"", IF($G89=$E$6, SUM(IF(OFFSET($R$23,,,($F89-1)*3-2,$D$3)=AK89,OFFSET($R$25,,,($F89-1)*3-2,$D$3)*OFFSET($B$23,1,,($F89-1)*3-2,1))), IF($D89=1,$N89, SUMIF(OFFSET(Orçamento!$D$1,$B89-1,,$C89,),$F90&"-"&AK89,OFFSET(Orçamento!$I$1,$B89-1,,$C89,))*$N89/$E90)))}
B91: {=IF($F89>$E$2,"",IF($F$2=1,INDEX('QC rev00'!$M$10:$T$120,$F91,5),IF($F$2=2,INDEX(#REF!,$F91,5),INDEX(#REF!,$F91,5))))} | C91: {=IF($F89>$E$2,"",IF($F$2=1,INDEX('QC rev00'!$M$10:$T$120,$F91,6),IF($F$2=2,INDEX(#REF!,$F91,6),INDEX(#REF!,$F91,6))))} | F91: =IF(F89>$E$2,"",MATCH(F89,'QC rev00'!$C$10:$C$120,)) | Q91: Valor | R91: =IFERROR(R90*$O89,0) -> 0 | S91: =IFERROR(S90*$O89,0) -> 0 | T91: =IFERROR(T90*$O89,0) -> 0 | U91: =IFERROR(U90*$O89,0) -> 0 | V91: =IFERROR(V90*$O89,0) -> 0 | W91: =IFERROR(W90*$O89,0) -> 0 | X91: =IFERROR(X90*$O89,0) -> 0 | Y91: =IFERROR(Y90*$O89,0) -> 0 | ... AK91: =IFERROR(AK90*$O89,0) -> 0
B92: =IF($F92>$E$2,0,IF(E92<>"",MATCH(F93&" - Mapa",Orçamento!J:J,),0)) -> 0 | C92: =IF($D92>1,_xlfn.MAXIFS(Orçamento!G:G,Orçamento!J:J,F93&" - Mapa")+6-B92,0) -> 0 | D92: =IF($F92>$E$2,0,IF($G92=$E$6,$D$2,IF(E92<>"",_xlfn.MAXIFS(Orçamento!E:E,Orçamento!J:J,F93&" - Mapa"),0))) -> 0 | E92: =IF(F93="","",_xlfn.IFNA(MATCH($F93,'QC rev00'!$G$10:$G$120,),"")) | F92: {=OFFSET(F92,-3,,,)+1} -> 24 | G92: {=IF($F92>$E$2,"",IF($F$2=1,INDEX('QC rev00'!$M$10:$T$120,$F94,2),IF($F$2=2,INDEX(#REF!,$F94,2),INDEX(#REF!,$F94,2))))} | H92: {=IF($F92>$E$2,"",IF($F$2=1,INDEX('QC rev00'!$M$10:$T$120,$F94,3),IF($F$2=2,INDEX(#REF!,$F94,3),INDEX(#REF!,$F94,3))))} | L92: {=IF($F92>$E$2,"",IF($F$2=1,INDEX('QC rev00'!$M$10:$T$120,$F94,7),IF($F$2=2,INDEX(#REF!,$F94,7),INDEX(#REF!,$F94,7))))} | M92: {=IF($F92>$E$2,"",IF($F$2=1,INDEX('QC rev00'!$M$10:$T$120,$F94,8),IF($F$2=2,INDEX(#REF!,$F94,8),INDEX(#REF!,$F94,8))))} | N92: {=IF($F92>$E$2,0,IF(_xlfn.IFNA(MATCH($G92,Listas!$E$4:$E$206,),0)>0,$F$5,IF($F$2=1,INDEX('QC rev00'!$M$10:$U$120,$F94,9),IF($F$2=2,INDEX(#REF!,$F94,9),INDEX(#REF!,$F94,9)))))} -> 0 | O92: {=IF($F92>$E$2,0,IF(_xlfn.IFNA(MATCH($G92,Listas!$E$4:$E$206,),0)>0,1,IF($H$10=0,0,IF($F$2=1,INDEX('QC rev00'!$M$10:$BC$120,$F94,9+$F$3),IF($F$2=2,INDEX(#REF!,$F94,9+$F$3),INDEX(#REF!,$F94,9+$F$3)))*IF($E$5="X",1,1-$B94-$C94))))} -> 0 | P92: =N92*O92 -> 0 | Q92: IP | R92: {=IF($D92=0,"",IF($G92=$E$6,INDEX(Orçamento!$U:$U,MATCH(R$21,Orçamento!$C:$C,),1),INDEX(Orçamento!$U:$U,$B92,1)))} | S92: =IF(S$21>$D92,"",IF($G92=$E$6,INDEX(Orçamento!$U:$U,MATCH(S$21,Orçamento!$C:$C,),1),INDEX(Orçamento!$U:$U,MATCH(S$21&"-"&$F93,Orçamento!$F:$F,),1))) | T92: =IF(T$21>$D92,"",IF($G92=$E$6,INDEX(Orçamento!$U:$U,MATCH(T$21,Orçamento!$C:$C,),1),INDEX(Orçamento!$U:$U,MATCH(T$21&"-"&$F93,Orçamento!$F:$F,),1))) | U92: =IF(U$21>$D92,"",IF($G92=$E$6,INDEX(Orçamento!$U:$U,MATCH(U$21,Orçamento!$C:$C,),1),INDEX(Orçamento!$U:$U,MATCH(U$21&"-"&$F93,Orçamento!$F:$F,),1))) | V92: =IF(V$21>$D92,"",IF($G92=$E$6,INDEX(Orçamento!$U:$U,MATCH(V$21,Orçamento!$C:$C,),1),INDEX(Orçamento!$U:$U,MATCH(V$21&"-"&$F93,Orçamento!$F:$F,),1))) | W92: =IF(W$21>$D92,"",IF($G92=$E$6,INDEX(Orçamento!$U:$U,MATCH(W$21,Orçamento!$C:$C,),1),INDEX(Orçamento!$U:$U,MATCH(W$21&"-"&$F93,Orçamento!$F:$F,),1))) | X92: =IF(X$21>$D92,"",IF($G92=$E$6,INDEX(Orçamento!$U:$U,MATCH(X$21,Orçamento!$C:$C,),1),INDEX(Orçamento!$U:$U,MATCH(X$21&"-"&$F93,Orçamento!$F:$F,),1))) | Y92: =IF(Y$21>$D92,"",IF($G92=$E$6,INDEX(Orçamento!$U:$U,MATCH(Y$21,Orçamento!$C:$C,),1),INDEX(Orçamento!$U:$U,MATCH(Y$21&"-"&$F93,Orçamento!$F:$F,),1))) | Z92: =IF(Z$21>$D92,"",IF($G92=$E$6,INDEX(Orçamento!$U:$U,MATCH(Z$21,Orçamento!$C:$C,),1),INDEX(Orçamento!$U:$U,MATCH(Z$21&"-"&$F93,Orçamento!$F:$F,),1))) | ... AK92: =IF(AK$21>$D92,"",IF($G92=$E$6,INDEX(Orçamento!$U:$U,MATCH(AK$21,Orçamento!$C:$C,),1),INDEX(Orçamento!$U:$U,MATCH(AK$21&"-"&$F93,Orçamento!$F:$F,),1)))
B93: =IF($F92>$E$2,0,(1/(1-B94-C94))*(B94+C94)) -> 0 | C93: {=IF(ROUND(SUM(IF(R92:AK92<>"",(R93:AK93)))-N92,3)<>0,"X",0)} -> 0 | E93: {=IF($F92>$E$2,"",INDEX('QC rev00'!$J$9:$J$120,1+E92,1))} | F93: {=IF($F92>$E$2,"",IF($F$2=1,INDEX('QC rev00'!$M$10:$T$120,$F94,1),IF($F$2=2,INDEX(#REF!,$F94,1),INDEX(#REF!,$F94,1))))} | Q93: Qtd | R93: {=IF(OR($D92=0,R92="",$N92=0),"", IF($G92=$E$6, SUM(IF(OFFSET($R$23,,,($F92-1)*3-2,$D$3)=R92,OFFSET($R$25,,,($F92-1)*3-2,$D$3)*OFFSET($B$23,1,,($F92-1)*3-2,1))), IF($D92=1,$N92, SUMIF(OFFSET(Orçamento!$D$1,$B92-1,,$C92,),$F93&"-"&R92,OFFSET(Orçamento!$I$1,$B92-1,,$C92,))*$N92/$E93)))} | S93: {=IF(OR($D92=0,S92="",$N92=0),"", IF($G92=$E$6, SUM(IF(OFFSET($R$23,,,($F92-1)*3-2,$D$3)=S92,OFFSET($R$25,,,($F92-1)*3-2,$D$3)*OFFSET($B$23,1,,($F92-1)*3-2,1))), IF($D92=1,$N92, SUMIF(OFFSET(Orçamento!$D$1,$B92-1,,$C92,),$F93&"-"&S92,OFFSET(Orçamento!$I$1,$B92-1,,$C92,))*$N92/$E93)))} | T93: {=IF(OR($D92=0,T92="",$N92=0),"", IF($G92=$E$6, SUM(IF(OFFSET($R$23,,,($F92-1)*3-2,$D$3)=T92,OFFSET($R$25,,,($F92-1)*3-2,$D$3)*OFFSET($B$23,1,,($F92-1)*3-2,1))), IF($D92=1,$N92, SUMIF(OFFSET(Orçamento!$D$1,$B92-1,,$C92,),$F93&"-"&T92,OFFSET(Orçamento!$I$1,$B92-1,,$C92,))*$N92/$E93)))} | U93: {=IF(OR($D92=0,U92="",$N92=0),"", IF($G92=$E$6, SUM(IF(OFFSET($R$23,,,($F92-1)*3-2,$D$3)=U92,OFFSET($R$25,,,($F92-1)*3-2,$D$3)*OFFSET($B$23,1,,($F92-1)*3-2,1))), IF($D92=1,$N92, SUMIF(OFFSET(Orçamento!$D$1,$B92-1,,$C92,),$F93&"-"&U92,OFFSET(Orçamento!$I$1,$B92-1,,$C92,))*$N92/$E93)))} | V93: {=IF(OR($D92=0,V92="",$N92=0),"", IF($G92=$E$6, SUM(IF(OFFSET($R$23,,,($F92-1)*3-2,$D$3)=V92,OFFSET($R$25,,,($F92-1)*3-2,$D$3)*OFFSET($B$23,1,,($F92-1)*3-2,1))), IF($D92=1,$N92, SUMIF(OFFSET(Orçamento!$D$1,$B92-1,,$C92,),$F93&"-"&V92,OFFSET(Orçamento!$I$1,$B92-1,,$C92,))*$N92/$E93)))} | W93: {=IF(OR($D92=0,W92="",$N92=0),"", IF($G92=$E$6, SUM(IF(OFFSET($R$23,,,($F92-1)*3-2,$D$3)=W92,OFFSET($R$25,,,($F92-1)*3-2,$D$3)*OFFSET($B$23,1,,($F92-1)*3-2,1))), IF($D92=1,$N92, SUMIF(OFFSET(Orçamento!$D$1,$B92-1,,$C92,),$F93&"-"&W92,OFFSET(Orçamento!$I$1,$B92-1,,$C92,))*$N92/$E93)))} | X93: {=IF(OR($D92=0,X92="",$N92=0),"", IF($G92=$E$6, SUM(IF(OFFSET($R$23,,,($F92-1)*3-2,$D$3)=X92,OFFSET($R$25,,,($F92-1)*3-2,$D$3)*OFFSET($B$23,1,,($F92-1)*3-2,1))), IF($D92=1,$N92, SUMIF(OFFSET(Orçamento!$D$1,$B92-1,,$C92,),$F93&"-"&X92,OFFSET(Orçamento!$I$1,$B92-1,,$C92,))*$N92/$E93)))} | Y93: {=IF(OR($D92=0,Y92="",$N92=0),"", IF($G92=$E$6, SUM(IF(OFFSET($R$23,,,($F92-1)*3-2,$D$3)=Y92,OFFSET($R$25,,,($F92-1)*3-2,$D$3)*OFFSET($B$23,1,,($F92-1)*3-2,1))), IF($D92=1,$N92, SUMIF(OFFSET(Orçamento!$D$1,$B92-1,,$C92,),$F93&"-"&Y92,OFFSET(Orçamento!$I$1,$B92-1,,$C92,))*$N92/$E93)))} | ... AK93: {=IF(OR($D92=0,AK92="",$N92=0),"", IF($G92=$E$6, SUM(IF(OFFSET($R$23,,,($F92-1)*3-2,$D$3)=AK92,OFFSET($R$25,,,($F92-1)*3-2,$D$3)*OFFSET($B$23,1,,($F92-1)*3-2,1))), IF($D92=1,$N92, SUMIF(OFFSET(Orçamento!$D$1,$B92-1,,$C92,),$F93&"-"&AK92,OFFSET(Orçamento!$I$1,$B92-1,,$C92,))*$N92/$E93)))}
B94: {=IF($F92>$E$2,"",IF($F$2=1,INDEX('QC rev00'!$M$10:$T$120,$F94,5),IF($F$2=2,INDEX(#REF!,$F94,5),INDEX(#REF!,$F94,5))))} | C94: {=IF($F92>$E$2,"",IF($F$2=1,INDEX('QC rev00'!$M$10:$T$120,$F94,6),IF($F$2=2,INDEX(#REF!,$F94,6),INDEX(#REF!,$F94,6))))} | F94: =IF(F92>$E$2,"",MATCH(F92,'QC rev00'!$C$10:$C$120,)) | Q94: Valor | R94: =IFERROR(R93*$O92,0) -> 0 | S94: =IFERROR(S93*$O92,0) -> 0 | T94: =IFERROR(T93*$O92,0) -> 0 | U94: =IFERROR(U93*$O92,0) -> 0 | V94: =IFERROR(V93*$O92,0) -> 0 | W94: =IFERROR(W93*$O92,0) -> 0 | X94: =IFERROR(X93*$O92,0) -> 0 | Y94: =IFERROR(Y93*$O92,0) -> 0 | ... AK94: =IFERROR(AK93*$O92,0) -> 0
B95: =IF($F95>$E$2,0,IF(E95<>"",MATCH(F96&" - Mapa",Orçamento!J:J,),0)) -> 0 | C95: =IF($D95>1,_xlfn.MAXIFS(Orçamento!G:G,Orçamento!J:J,F96&" - Mapa")+6-B95,0) -> 0 | D95: =IF($F95>$E$2,0,IF($G95=$E$6,$D$2,IF(E95<>"",_xlfn.MAXIFS(Orçamento!E:E,Orçamento!J:J,F96&" - Mapa"),0))) -> 0 | E95: =IF(F96="","",_xlfn.IFNA(MATCH($F96,'QC rev00'!$G$10:$G$120,),"")) | F95: {=OFFSET(F95,-3,,,)+1} -> 25 | G95: {=IF($F95>$E$2,"",IF($F$2=1,INDEX('QC rev00'!$M$10:$T$120,$F97,2),IF($F$2=2,INDEX(#REF!,$F97,2),INDEX(#REF!,$F97,2))))} | H95: {=IF($F95>$E$2,"",IF($F$2=1,INDEX('QC rev00'!$M$10:$T$120,$F97,3),IF($F$2=2,INDEX(#REF!,$F97,3),INDEX(#REF!,$F97,3))))} | L95: {=IF($F95>$E$2,"",IF($F$2=1,INDEX('QC rev00'!$M$10:$T$120,$F97,7),IF($F$2=2,INDEX(#REF!,$F97,7),INDEX(#REF!,$F97,7))))} | M95: {=IF($F95>$E$2,"",IF($F$2=1,INDEX('QC rev00'!$M$10:$T$120,$F97,8),IF($F$2=2,INDEX(#REF!,$F97,8),INDEX(#REF!,$F97,8))))} | N95: {=IF($F95>$E$2,0,IF(_xlfn.IFNA(MATCH($G95,Listas!$E$4:$E$206,),0)>0,$F$5,IF($F$2=1,INDEX('QC rev00'!$M$10:$U$120,$F97,9),IF($F$2=2,INDEX(#REF!,$F97,9),INDEX(#REF!,$F97,9)))))} -> 0 | O95: {=IF($F95>$E$2,0,IF(_xlfn.IFNA(MATCH($G95,Listas!$E$4:$E$206,),0)>0,1,IF($H$10=0,0,IF($F$2=1,INDEX('QC rev00'!$M$10:$BC$120,$F97,9+$F$3),IF($F$2=2,INDEX(#REF!,$F97,9+$F$3),INDEX(#REF!,$F97,9+$F$3)))*IF($E$5="X",1,1-$B97-$C97))))} -> 0 | P95: =N95*O95 -> 0 | Q95: IP | R95: {=IF($D95=0,"",IF($G95=$E$6,INDEX(Orçamento!$U:$U,MATCH(R$21,Orçamento!$C:$C,),1),INDEX(Orçamento!$U:$U,$B95,1)))} | S95: =IF(S$21>$D95,"",IF($G95=$E$6,INDEX(Orçamento!$U:$U,MATCH(S$21,Orçamento!$C:$C,),1),INDEX(Orçamento!$U:$U,MATCH(S$21&"-"&$F96,Orçamento!$F:$F,),1))) | T95: =IF(T$21>$D95,"",IF($G95=$E$6,INDEX(Orçamento!$U:$U,MATCH(T$21,Orçamento!$C:$C,),1),INDEX(Orçamento!$U:$U,MATCH(T$21&"-"&$F96,Orçamento!$F:$F,),1))) | U95: =IF(U$21>$D95,"",IF($G95=$E$6,INDEX(Orçamento!$U:$U,MATCH(U$21,Orçamento!$C:$C,),1),INDEX(Orçamento!$U:$U,MATCH(U$21&"-"&$F96,Orçamento!$F:$F,),1))) | V95: =IF(V$21>$D95,"",IF($G95=$E$6,INDEX(Orçamento!$U:$U,MATCH(V$21,Orçamento!$C:$C,),1),INDEX(Orçamento!$U:$U,MATCH(V$21&"-"&$F96,Orçamento!$F:$F,),1))) | W95: =IF(W$21>$D95,"",IF($G95=$E$6,INDEX(Orçamento!$U:$U,MATCH(W$21,Orçamento!$C:$C,),1),INDEX(Orçamento!$U:$U,MATCH(W$21&"-"&$F96,Orçamento!$F:$F,),1))) | X95: =IF(X$21>$D95,"",IF($G95=$E$6,INDEX(Orçamento!$U:$U,MATCH(X$21,Orçamento!$C:$C,),1),INDEX(Orçamento!$U:$U,MATCH(X$21&"-"&$F96,Orçamento!$F:$F,),1))) | Y95: =IF(Y$21>$D95,"",IF($G95=$E$6,INDEX(Orçamento!$U:$U,MATCH(Y$21,Orçamento!$C:$C,),1),INDEX(Orçamento!$U:$U,MATCH(Y$21&"-"&$F96,Orçamento!$F:$F,),1))) | Z95: =IF(Z$21>$D95,"",IF($G95=$E$6,INDEX(Orçamento!$U:$U,MATCH(Z$21,Orçamento!$C:$C,),1),INDEX(Orçamento!$U:$U,MATCH(Z$21&"-"&$F96,Orçamento!$F:$F,),1))) | ... AK95: =IF(AK$21>$D95,"",IF($G95=$E$6,INDEX(Orçamento!$U:$U,MATCH(AK$21,Orçamento!$C:$C,),1),INDEX(Orçamento!$U:$U,MATCH(AK$21&"-"&$F96,Orçamento!$F:$F,),1)))
B96: =IF($F95>$E$2,0,(1/(1-B97-C97))*(B97+C97)) -> 0 | C96: {=IF(ROUND(SUM(IF(R95:AK95<>"",(R96:AK96)))-N95,3)<>0,"X",0)} -> 0 | E96: {=IF($F95>$E$2,"",INDEX('QC rev00'!$J$9:$J$120,1+E95,1))} | F96: {=IF($F95>$E$2,"",IF($F$2=1,INDEX('QC rev00'!$M$10:$T$120,$F97,1),IF($F$2=2,INDEX(#REF!,$F97,1),INDEX(#REF!,$F97,1))))} | Q96: Qtd | R96: {=IF(OR($D95=0,R95="",$N95=0),"", IF($G95=$E$6, SUM(IF(OFFSET($R$23,,,($F95-1)*3-2,$D$3)=R95,OFFSET($R$25,,,($F95-1)*3-2,$D$3)*OFFSET($B$23,1,,($F95-1)*3-2,1))), IF($D95=1,$N95, SUMIF(OFFSET(Orçamento!$D$1,$B95-1,,$C95,),$F96&"-"&R95,OFFSET(Orçamento!$I$1,$B95-1,,$C95,))*$N95/$E96)))} | S96: {=IF(OR($D95=0,S95="",$N95=0),"", IF($G95=$E$6, SUM(IF(OFFSET($R$23,,,($F95-1)*3-2,$D$3)=S95,OFFSET($R$25,,,($F95-1)*3-2,$D$3)*OFFSET($B$23,1,,($F95-1)*3-2,1))), IF($D95=1,$N95, SUMIF(OFFSET(Orçamento!$D$1,$B95-1,,$C95,),$F96&"-"&S95,OFFSET(Orçamento!$I$1,$B95-1,,$C95,))*$N95/$E96)))} | T96: {=IF(OR($D95=0,T95="",$N95=0),"", IF($G95=$E$6, SUM(IF(OFFSET($R$23,,,($F95-1)*3-2,$D$3)=T95,OFFSET($R$25,,,($F95-1)*3-2,$D$3)*OFFSET($B$23,1,,($F95-1)*3-2,1))), IF($D95=1,$N95, SUMIF(OFFSET(Orçamento!$D$1,$B95-1,,$C95,),$F96&"-"&T95,OFFSET(Orçamento!$I$1,$B95-1,,$C95,))*$N95/$E96)))} | U96: {=IF(OR($D95=0,U95="",$N95=0),"", IF($G95=$E$6, SUM(IF(OFFSET($R$23,,,($F95-1)*3-2,$D$3)=U95,OFFSET($R$25,,,($F95-1)*3-2,$D$3)*OFFSET($B$23,1,,($F95-1)*3-2,1))), IF($D95=1,$N95, SUMIF(OFFSET(Orçamento!$D$1,$B95-1,,$C95,),$F96&"-"&U95,OFFSET(Orçamento!$I$1,$B95-1,,$C95,))*$N95/$E96)))} | V96: {=IF(OR($D95=0,V95="",$N95=0),"", IF($G95=$E$6, SUM(IF(OFFSET($R$23,,,($F95-1)*3-2,$D$3)=V95,OFFSET($R$25,,,($F95-1)*3-2,$D$3)*OFFSET($B$23,1,,($F95-1)*3-2,1))), IF($D95=1,$N95, SUMIF(OFFSET(Orçamento!$D$1,$B95-1,,$C95,),$F96&"-"&V95,OFFSET(Orçamento!$I$1,$B95-1,,$C95,))*$N95/$E96)))} | W96: {=IF(OR($D95=0,W95="",$N95=0),"", IF($G95=$E$6, SUM(IF(OFFSET($R$23,,,($F95-1)*3-2,$D$3)=W95,OFFSET($R$25,,,($F95-1)*3-2,$D$3)*OFFSET($B$23,1,,($F95-1)*3-2,1))), IF($D95=1,$N95, SUMIF(OFFSET(Orçamento!$D$1,$B95-1,,$C95,),$F96&"-"&W95,OFFSET(Orçamento!$I$1,$B95-1,,$C95,))*$N95/$E96)))} | X96: {=IF(OR($D95=0,X95="",$N95=0),"", IF($G95=$E$6, SUM(IF(OFFSET($R$23,,,($F95-1)*3-2,$D$3)=X95,OFFSET($R$25,,,($F95-1)*3-2,$D$3)*OFFSET($B$23,1,,($F95-1)*3-2,1))), IF($D95=1,$N95, SUMIF(OFFSET(Orçamento!$D$1,$B95-1,,$C95,),$F96&"-"&X95,OFFSET(Orçamento!$I$1,$B95-1,,$C95,))*$N95/$E96)))} | Y96: {=IF(OR($D95=0,Y95="",$N95=0),"", IF($G95=$E$6, SUM(IF(OFFSET($R$23,,,($F95-1)*3-2,$D$3)=Y95,OFFSET($R$25,,,($F95-1)*3-2,$D$3)*OFFSET($B$23,1,,($F95-1)*3-2,1))), IF($D95=1,$N95, SUMIF(OFFSET(Orçamento!$D$1,$B95-1,,$C95,),$F96&"-"&Y95,OFFSET(Orçamento!$I$1,$B95-1,,$C95,))*$N95/$E96)))} | ... AK96: {=IF(OR($D95=0,AK95="",$N95=0),"", IF($G95=$E$6, SUM(IF(OFFSET($R$23,,,($F95-1)*3-2,$D$3)=AK95,OFFSET($R$25,,,($F95-1)*3-2,$D$3)*OFFSET($B$23,1,,($F95-1)*3-2,1))), IF($D95=1,$N95, SUMIF(OFFSET(Orçamento!$D$1,$B95-1,,$C95,),$F96&"-"&AK95,OFFSET(Orçamento!$I$1,$B95-1,,$C95,))*$N95/$E96)))}
B97: {=IF($F95>$E$2,"",IF($F$2=1,INDEX('QC rev00'!$M$10:$T$120,$F97,5),IF($F$2=2,INDEX(#REF!,$F97,5),INDEX(#REF!,$F97,5))))} | C97: {=IF($F95>$E$2,"",IF($F$2=1,INDEX('QC rev00'!$M$10:$T$120,$F97,6),IF($F$2=2,INDEX(#REF!,$F97,6),INDEX(#REF!,$F97,6))))} | F97: =IF(F95>$E$2,"",MATCH(F95,'QC rev00'!$C$10:$C$120,)) | Q97: Valor | R97: =IFERROR(R96*$O95,0) -> 0 | S97: =IFERROR(S96*$O95,0) -> 0 | T97: =IFERROR(T96*$O95,0) -> 0 | U97: =IFERROR(U96*$O95,0) -> 0 | V97: =IFERROR(V96*$O95,0) -> 0 | W97: =IFERROR(W96*$O95,0) -> 0 | X97: =IFERROR(X96*$O95,0) -> 0 | Y97: =IFERROR(Y96*$O95,0) -> 0 | ... AK97: =IFERROR(AK96*$O95,0) -> 0
B98: =IF($F98>$E$2,0,IF(E98<>"",MATCH(F99&" - Mapa",Orçamento!J:J,),0)) -> 0 | C98: =IF($D98>1,_xlfn.MAXIFS(Orçamento!G:G,Orçamento!J:J,F99&" - Mapa")+6-B98,0) -> 0 | D98: =IF($F98>$E$2,0,IF($G98=$E$6,$D$2,IF(E98<>"",_xlfn.MAXIFS(Orçamento!E:E,Orçamento!J:J,F99&" - Mapa"),0))) -> 0 | E98: =IF(F99="","",_xlfn.IFNA(MATCH($F99,'QC rev00'!$G$10:$G$120,),"")) | F98: {=OFFSET(F98,-3,,,)+1} -> 26 | G98: {=IF($F98>$E$2,"",IF($F$2=1,INDEX('QC rev00'!$M$10:$T$120,$F100,2),IF($F$2=2,INDEX(#REF!,$F100,2),INDEX(#REF!,$F100,2))))} | H98: {=IF($F98>$E$2,"",IF($F$2=1,INDEX('QC rev00'!$M$10:$T$120,$F100,3),IF($F$2=2,INDEX(#REF!,$F100,3),INDEX(#REF!,$F100,3))))} | L98: {=IF($F98>$E$2,"",IF($F$2=1,INDEX('QC rev00'!$M$10:$T$120,$F100,7),IF($F$2=2,INDEX(#REF!,$F100,7),INDEX(#REF!,$F100,7))))} | M98: {=IF($F98>$E$2,"",IF($F$2=1,INDEX('QC rev00'!$M$10:$T$120,$F100,8),IF($F$2=2,INDEX(#REF!,$F100,8),INDEX(#REF!,$F100,8))))} | N98: {=IF($F98>$E$2,0,IF(_xlfn.IFNA(MATCH($G98,Listas!$E$4:$E$206,),0)>0,$F$5,IF($F$2=1,INDEX('QC rev00'!$M$10:$U$120,$F100,9),IF($F$2=2,INDEX(#REF!,$F100,9),INDEX(#REF!,$F100,9)))))} -> 0 | O98: {=IF($F98>$E$2,0,IF(_xlfn.IFNA(MATCH($G98,Listas!$E$4:$E$206,),0)>0,1,IF($H$10=0,0,IF($F$2=1,INDEX('QC rev00'!$M$10:$BC$120,$F100,9+$F$3),IF($F$2=2,INDEX(#REF!,$F100,9+$F$3),INDEX(#REF!,$F100,9+$F$3)))*IF($E$5="X",1,1-$B100-$C100))))} -> 0 | P98: =N98*O98 -> 0 | Q98: IP | R98: {=IF($D98=0,"",IF($G98=$E$6,INDEX(Orçamento!$U:$U,MATCH(R$21,Orçamento!$C:$C,),1),INDEX(Orçamento!$U:$U,$B98,1)))} | S98: =IF(S$21>$D98,"",IF($G98=$E$6,INDEX(Orçamento!$U:$U,MATCH(S$21,Orçamento!$C:$C,),1),INDEX(Orçamento!$U:$U,MATCH(S$21&"-"&$F99,Orçamento!$F:$F,),1))) | T98: =IF(T$21>$D98,"",IF($G98=$E$6,INDEX(Orçamento!$U:$U,MATCH(T$21,Orçamento!$C:$C,),1),INDEX(Orçamento!$U:$U,MATCH(T$21&"-"&$F99,Orçamento!$F:$F,),1))) | U98: =IF(U$21>$D98,"",IF($G98=$E$6,INDEX(Orçamento!$U:$U,MATCH(U$21,Orçamento!$C:$C,),1),INDEX(Orçamento!$U:$U,MATCH(U$21&"-"&$F99,Orçamento!$F:$F,),1))) | V98: =IF(V$21>$D98,"",IF($G98=$E$6,INDEX(Orçamento!$U:$U,MATCH(V$21,Orçamento!$C:$C,),1),INDEX(Orçamento!$U:$U,MATCH(V$21&"-"&$F99,Orçamento!$F:$F,),1))) | W98: =IF(W$21>$D98,"",IF($G98=$E$6,INDEX(Orçamento!$U:$U,MATCH(W$21,Orçamento!$C:$C,),1),INDEX(Orçamento!$U:$U,MATCH(W$21&"-"&$F99,Orçamento!$F:$F,),1))) | X98: =IF(X$21>$D98,"",IF($G98=$E$6,INDEX(Orçamento!$U:$U,MATCH(X$21,Orçamento!$C:$C,),1),INDEX(Orçamento!$U:$U,MATCH(X$21&"-"&$F99,Orçamento!$F:$F,),1))) | Y98: =IF(Y$21>$D98,"",IF($G98=$E$6,INDEX(Orçamento!$U:$U,MATCH(Y$21,Orçamento!$C:$C,),1),INDEX(Orçamento!$U:$U,MATCH(Y$21&"-"&$F99,Orçamento!$F:$F,),1))) | Z98: =IF(Z$21>$D98,"",IF($G98=$E$6,INDEX(Orçamento!$U:$U,MATCH(Z$21,Orçamento!$C:$C,),1),INDEX(Orçamento!$U:$U,MATCH(Z$21&"-"&$F99,Orçamento!$F:$F,),1))) | ... AK98: =IF(AK$21>$D98,"",IF($G98=$E$6,INDEX(Orçamento!$U:$U,MATCH(AK$21,Orçamento!$C:$C,),1),INDEX(Orçamento!$U:$U,MATCH(AK$21&"-"&$F99,Orçamento!$F:$F,),1)))
B99: =IF($F98>$E$2,0,(1/(1-B100-C100))*(B100+C100)) -> 0 | C99: {=IF(ROUND(SUM(IF(R98:AK98<>"",(R99:AK99)))-N98,3)<>0,"X",0)} -> 0 | E99: {=IF($F98>$E$2,"",INDEX('QC rev00'!$J$9:$J$120,1+E98,1))} | F99: {=IF($F98>$E$2,"",IF($F$2=1,INDEX('QC rev00'!$M$10:$T$120,$F100,1),IF($F$2=2,INDEX(#REF!,$F100,1),INDEX(#REF!,$F100,1))))} | Q99: Qtd | R99: {=IF(OR($D98=0,R98="",$N98=0),"", IF($G98=$E$6, SUM(IF(OFFSET($R$23,,,($F98-1)*3-2,$D$3)=R98,OFFSET($R$25,,,($F98-1)*3-2,$D$3)*OFFSET($B$23,1,,($F98-1)*3-2,1))), IF($D98=1,$N98, SUMIF(OFFSET(Orçamento!$D$1,$B98-1,,$C98,),$F99&"-"&R98,OFFSET(Orçamento!$I$1,$B98-1,,$C98,))*$N98/$E99)))} | S99: {=IF(OR($D98=0,S98="",$N98=0),"", IF($G98=$E$6, SUM(IF(OFFSET($R$23,,,($F98-1)*3-2,$D$3)=S98,OFFSET($R$25,,,($F98-1)*3-2,$D$3)*OFFSET($B$23,1,,($F98-1)*3-2,1))), IF($D98=1,$N98, SUMIF(OFFSET(Orçamento!$D$1,$B98-1,,$C98,),$F99&"-"&S98,OFFSET(Orçamento!$I$1,$B98-1,,$C98,))*$N98/$E99)))} | T99: {=IF(OR($D98=0,T98="",$N98=0),"", IF($G98=$E$6, SUM(IF(OFFSET($R$23,,,($F98-1)*3-2,$D$3)=T98,OFFSET($R$25,,,($F98-1)*3-2,$D$3)*OFFSET($B$23,1,,($F98-1)*3-2,1))), IF($D98=1,$N98, SUMIF(OFFSET(Orçamento!$D$1,$B98-1,,$C98,),$F99&"-"&T98,OFFSET(Orçamento!$I$1,$B98-1,,$C98,))*$N98/$E99)))} | U99: {=IF(OR($D98=0,U98="",$N98=0),"", IF($G98=$E$6, SUM(IF(OFFSET($R$23,,,($F98-1)*3-2,$D$3)=U98,OFFSET($R$25,,,($F98-1)*3-2,$D$3)*OFFSET($B$23,1,,($F98-1)*3-2,1))), IF($D98=1,$N98, SUMIF(OFFSET(Orçamento!$D$1,$B98-1,,$C98,),$F99&"-"&U98,OFFSET(Orçamento!$I$1,$B98-1,,$C98,))*$N98/$E99)))} | V99: {=IF(OR($D98=0,V98="",$N98=0),"", IF($G98=$E$6, SUM(IF(OFFSET($R$23,,,($F98-1)*3-2,$D$3)=V98,OFFSET($R$25,,,($F98-1)*3-2,$D$3)*OFFSET($B$23,1,,($F98-1)*3-2,1))), IF($D98=1,$N98, SUMIF(OFFSET(Orçamento!$D$1,$B98-1,,$C98,),$F99&"-"&V98,OFFSET(Orçamento!$I$1,$B98-1,,$C98,))*$N98/$E99)))} | W99: {=IF(OR($D98=0,W98="",$N98=0),"", IF($G98=$E$6, SUM(IF(OFFSET($R$23,,,($F98-1)*3-2,$D$3)=W98,OFFSET($R$25,,,($F98-1)*3-2,$D$3)*OFFSET($B$23,1,,($F98-1)*3-2,1))), IF($D98=1,$N98, SUMIF(OFFSET(Orçamento!$D$1,$B98-1,,$C98,),$F99&"-"&W98,OFFSET(Orçamento!$I$1,$B98-1,,$C98,))*$N98/$E99)))} | X99: {=IF(OR($D98=0,X98="",$N98=0),"", IF($G98=$E$6, SUM(IF(OFFSET($R$23,,,($F98-1)*3-2,$D$3)=X98,OFFSET($R$25,,,($F98-1)*3-2,$D$3)*OFFSET($B$23,1,,($F98-1)*3-2,1))), IF($D98=1,$N98, SUMIF(OFFSET(Orçamento!$D$1,$B98-1,,$C98,),$F99&"-"&X98,OFFSET(Orçamento!$I$1,$B98-1,,$C98,))*$N98/$E99)))} | Y99: {=IF(OR($D98=0,Y98="",$N98=0),"", IF($G98=$E$6, SUM(IF(OFFSET($R$23,,,($F98-1)*3-2,$D$3)=Y98,OFFSET($R$25,,,($F98-1)*3-2,$D$3)*OFFSET($B$23,1,,($F98-1)*3-2,1))), IF($D98=1,$N98, SUMIF(OFFSET(Orçamento!$D$1,$B98-1,,$C98,),$F99&"-"&Y98,OFFSET(Orçamento!$I$1,$B98-1,,$C98,))*$N98/$E99)))} | ... AK99: {=IF(OR($D98=0,AK98="",$N98=0),"", IF($G98=$E$6, SUM(IF(OFFSET($R$23,,,($F98-1)*3-2,$D$3)=AK98,OFFSET($R$25,,,($F98-1)*3-2,$D$3)*OFFSET($B$23,1,,($F98-1)*3-2,1))), IF($D98=1,$N98, SUMIF(OFFSET(Orçamento!$D$1,$B98-1,,$C98,),$F99&"-"&AK98,OFFSET(Orçamento!$I$1,$B98-1,,$C98,))*$N98/$E99)))}
B100: {=IF($F98>$E$2,"",IF($F$2=1,INDEX('QC rev00'!$M$10:$T$120,$F100,5),IF($F$2=2,INDEX(#REF!,$F100,5),INDEX(#REF!,$F100,5))))} | C100: {=IF($F98>$E$2,"",IF($F$2=1,INDEX('QC rev00'!$M$10:$T$120,$F100,6),IF($F$2=2,INDEX(#REF!,$F100,6),INDEX(#REF!,$F100,6))))} | F100: =IF(F98>$E$2,"",MATCH(F98,'QC rev00'!$C$10:$C$120,)) | Q100: Valor | R100: =IFERROR(R99*$O98,0) -> 0 | S100: =IFERROR(S99*$O98,0) -> 0 | T100: =IFERROR(T99*$O98,0) -> 0 | U100: =IFERROR(U99*$O98,0) -> 0 | V100: =IFERROR(V99*$O98,0) -> 0 | W100: =IFERROR(W99*$O98,0) -> 0 | X100: =IFERROR(X99*$O98,0) -> 0 | Y100: =IFERROR(Y99*$O98,0) -> 0 | ... AK100: =IFERROR(AK99*$O98,0) -> 0
B101: =IF($F101>$E$2,0,IF(E101<>"",MATCH(F102&" - Mapa",Orçamento!J:J,),0)) -> 0 | C101: =IF($D101>1,_xlfn.MAXIFS(Orçamento!G:G,Orçamento!J:J,F102&" - Mapa")+6-B101,0) -> 0 | D101: =IF($F101>$E$2,0,IF($G101=$E$6,$D$2,IF(E101<>"",_xlfn.MAXIFS(Orçamento!E:E,Orçamento!J:J,F102&" - Mapa"),0))) -> 0 | E101: =IF(F102="","",_xlfn.IFNA(MATCH($F102,'QC rev00'!$G$10:$G$120,),"")) | F101: {=OFFSET(F101,-3,,,)+1} -> 27 | G101: {=IF($F101>$E$2,"",IF($F$2=1,INDEX('QC rev00'!$M$10:$T$120,$F103,2),IF($F$2=2,INDEX(#REF!,$F103,2),INDEX(#REF!,$F103,2))))} | H101: {=IF($F101>$E$2,"",IF($F$2=1,INDEX('QC rev00'!$M$10:$T$120,$F103,3),IF($F$2=2,INDEX(#REF!,$F103,3),INDEX(#REF!,$F103,3))))} | L101: {=IF($F101>$E$2,"",IF($F$2=1,INDEX('QC rev00'!$M$10:$T$120,$F103,7),IF($F$2=2,INDEX(#REF!,$F103,7),INDEX(#REF!,$F103,7))))} | M101: {=IF($F101>$E$2,"",IF($F$2=1,INDEX('QC rev00'!$M$10:$T$120,$F103,8),IF($F$2=2,INDEX(#REF!,$F103,8),INDEX(#REF!,$F103,8))))} | N101: {=IF($F101>$E$2,0,IF(_xlfn.IFNA(MATCH($G101,Listas!$E$4:$E$206,),0)>0,$F$5,IF($F$2=1,INDEX('QC rev00'!$M$10:$U$120,$F103,9),IF($F$2=2,INDEX(#REF!,$F103,9),INDEX(#REF!,$F103,9)))))} -> 0 | O101: {=IF($F101>$E$2,0,IF(_xlfn.IFNA(MATCH($G101,Listas!$E$4:$E$206,),0)>0,1,IF($H$10=0,0,IF($F$2=1,INDEX('QC rev00'!$M$10:$BC$120,$F103,9+$F$3),IF($F$2=2,INDEX(#REF!,$F103,9+$F$3),INDEX(#REF!,$F103,9+$F$3)))*IF($E$5="X",1,1-$B103-$C103))))} -> 0 | P101: =N101*O101 -> 0 | Q101: IP | R101: {=IF($D101=0,"",IF($G101=$E$6,INDEX(Orçamento!$U:$U,MATCH(R$21,Orçamento!$C:$C,),1),INDEX(Orçamento!$U:$U,$B101,1)))} | S101: =IF(S$21>$D101,"",IF($G101=$E$6,INDEX(Orçamento!$U:$U,MATCH(S$21,Orçamento!$C:$C,),1),INDEX(Orçamento!$U:$U,MATCH(S$21&"-"&$F102,Orçamento!$F:$F,),1))) | T101: =IF(T$21>$D101,"",IF($G101=$E$6,INDEX(Orçamento!$U:$U,MATCH(T$21,Orçamento!$C:$C,),1),INDEX(Orçamento!$U:$U,MATCH(T$21&"-"&$F102,Orçamento!$F:$F,),1))) | U101: =IF(U$21>$D101,"",IF($G101=$E$6,INDEX(Orçamento!$U:$U,MATCH(U$21,Orçamento!$C:$C,),1),INDEX(Orçamento!$U:$U,MATCH(U$21&"-"&$F102,Orçamento!$F:$F,),1))) | V101: =IF(V$21>$D101,"",IF($G101=$E$6,INDEX(Orçamento!$U:$U,MATCH(V$21,Orçamento!$C:$C,),1),INDEX(Orçamento!$U:$U,MATCH(V$21&"-"&$F102,Orçamento!$F:$F,),1))) | W101: =IF(W$21>$D101,"",IF($G101=$E$6,INDEX(Orçamento!$U:$U,MATCH(W$21,Orçamento!$C:$C,),1),INDEX(Orçamento!$U:$U,MATCH(W$21&"-"&$F102,Orçamento!$F:$F,),1))) | X101: =IF(X$21>$D101,"",IF($G101=$E$6,INDEX(Orçamento!$U:$U,MATCH(X$21,Orçamento!$C:$C,),1),INDEX(Orçamento!$U:$U,MATCH(X$21&"-"&$F102,Orçamento!$F:$F,),1))) | Y101: =IF(Y$21>$D101,"",IF($G101=$E$6,INDEX(Orçamento!$U:$U,MATCH(Y$21,Orçamento!$C:$C,),1),INDEX(Orçamento!$U:$U,MATCH(Y$21&"-"&$F102,Orçamento!$F:$F,),1))) | Z101: =IF(Z$21>$D101,"",IF($G101=$E$6,INDEX(Orçamento!$U:$U,MATCH(Z$21,Orçamento!$C:$C,),1),INDEX(Orçamento!$U:$U,MATCH(Z$21&"-"&$F102,Orçamento!$F:$F,),1))) | ... AK101: =IF(AK$21>$D101,"",IF($G101=$E$6,INDEX(Orçamento!$U:$U,MATCH(AK$21,Orçamento!$C:$C,),1),INDEX(Orçamento!$U:$U,MATCH(AK$21&"-"&$F102,Orçamento!$F:$F,),1)))
B102: =IF($F101>$E$2,0,(1/(1-B103-C103))*(B103+C103)) -> 0 | C102: {=IF(ROUND(SUM(IF(R101:AK101<>"",(R102:AK102)))-N101,3)<>0,"X",0)} -> 0 | E102: {=IF($F101>$E$2,"",INDEX('QC rev00'!$J$9:$J$120,1+E101,1))} | F102: {=IF($F101>$E$2,"",IF($F$2=1,INDEX('QC rev00'!$M$10:$T$120,$F103,1),IF($F$2=2,INDEX(#REF!,$F103,1),INDEX(#REF!,$F103,1))))} | Q102: Qtd | R102: {=IF(OR($D101=0,R101="",$N101=0),"", IF($G101=$E$6, SUM(IF(OFFSET($R$23,,,($F101-1)*3-2,$D$3)=R101,OFFSET($R$25,,,($F101-1)*3-2,$D$3)*OFFSET($B$23,1,,($F101-1)*3-2,1))), IF($D101=1,$N101, SUMIF(OFFSET(Orçamento!$D$1,$B101-1,,$C101,),$F102&"-"&R101,OFFSET(Orçamento!$I$1,$B101-1,,$C101,))*$N101/$E102)))} | S102: {=IF(OR($D101=0,S101="",$N101=0),"", IF($G101=$E$6, SUM(IF(OFFSET($R$23,,,($F101-1)*3-2,$D$3)=S101,OFFSET($R$25,,,($F101-1)*3-2,$D$3)*OFFSET($B$23,1,,($F101-1)*3-2,1))), IF($D101=1,$N101, SUMIF(OFFSET(Orçamento!$D$1,$B101-1,,$C101,),$F102&"-"&S101,OFFSET(Orçamento!$I$1,$B101-1,,$C101,))*$N101/$E102)))} | T102: {=IF(OR($D101=0,T101="",$N101=0),"", IF($G101=$E$6, SUM(IF(OFFSET($R$23,,,($F101-1)*3-2,$D$3)=T101,OFFSET($R$25,,,($F101-1)*3-2,$D$3)*OFFSET($B$23,1,,($F101-1)*3-2,1))), IF($D101=1,$N101, SUMIF(OFFSET(Orçamento!$D$1,$B101-1,,$C101,),$F102&"-"&T101,OFFSET(Orçamento!$I$1,$B101-1,,$C101,))*$N101/$E102)))} | U102: {=IF(OR($D101=0,U101="",$N101=0),"", IF($G101=$E$6, SUM(IF(OFFSET($R$23,,,($F101-1)*3-2,$D$3)=U101,OFFSET($R$25,,,($F101-1)*3-2,$D$3)*OFFSET($B$23,1,,($F101-1)*3-2,1))), IF($D101=1,$N101, SUMIF(OFFSET(Orçamento!$D$1,$B101-1,,$C101,),$F102&"-"&U101,OFFSET(Orçamento!$I$1,$B101-1,,$C101,))*$N101/$E102)))} | V102: {=IF(OR($D101=0,V101="",$N101=0),"", IF($G101=$E$6, SUM(IF(OFFSET($R$23,,,($F101-1)*3-2,$D$3)=V101,OFFSET($R$25,,,($F101-1)*3-2,$D$3)*OFFSET($B$23,1,,($F101-1)*3-2,1))), IF($D101=1,$N101, SUMIF(OFFSET(Orçamento!$D$1,$B101-1,,$C101,),$F102&"-"&V101,OFFSET(Orçamento!$I$1,$B101-1,,$C101,))*$N101/$E102)))} | W102: {=IF(OR($D101=0,W101="",$N101=0),"", IF($G101=$E$6, SUM(IF(OFFSET($R$23,,,($F101-1)*3-2,$D$3)=W101,OFFSET($R$25,,,($F101-1)*3-2,$D$3)*OFFSET($B$23,1,,($F101-1)*3-2,1))), IF($D101=1,$N101, SUMIF(OFFSET(Orçamento!$D$1,$B101-1,,$C101,),$F102&"-"&W101,OFFSET(Orçamento!$I$1,$B101-1,,$C101,))*$N101/$E102)))} | X102: {=IF(OR($D101=0,X101="",$N101=0),"", IF($G101=$E$6, SUM(IF(OFFSET($R$23,,,($F101-1)*3-2,$D$3)=X101,OFFSET($R$25,,,($F101-1)*3-2,$D$3)*OFFSET($B$23,1,,($F101-1)*3-2,1))), IF($D101=1,$N101, SUMIF(OFFSET(Orçamento!$D$1,$B101-1,,$C101,),$F102&"-"&X101,OFFSET(Orçamento!$I$1,$B101-1,,$C101,))*$N101/$E102)))} | Y102: {=IF(OR($D101=0,Y101="",$N101=0),"", IF($G101=$E$6, SUM(IF(OFFSET($R$23,,,($F101-1)*3-2,$D$3)=Y101,OFFSET($R$25,,,($F101-1)*3-2,$D$3)*OFFSET($B$23,1,,($F101-1)*3-2,1))), IF($D101=1,$N101, SUMIF(OFFSET(Orçamento!$D$1,$B101-1,,$C101,),$F102&"-"&Y101,OFFSET(Orçamento!$I$1,$B101-1,,$C101,))*$N101/$E102)))} | ... AK102: {=IF(OR($D101=0,AK101="",$N101=0),"", IF($G101=$E$6, SUM(IF(OFFSET($R$23,,,($F101-1)*3-2,$D$3)=AK101,OFFSET($R$25,,,($F101-1)*3-2,$D$3)*OFFSET($B$23,1,,($F101-1)*3-2,1))), IF($D101=1,$N101, SUMIF(OFFSET(Orçamento!$D$1,$B101-1,,$C101,),$F102&"-"&AK101,OFFSET(Orçamento!$I$1,$B101-1,,$C101,))*$N101/$E102)))}
B103: {=IF($F101>$E$2,"",IF($F$2=1,INDEX('QC rev00'!$M$10:$T$120,$F103,5),IF($F$2=2,INDEX(#REF!,$F103,5),INDEX(#REF!,$F103,5))))} | C103: {=IF($F101>$E$2,"",IF($F$2=1,INDEX('QC rev00'!$M$10:$T$120,$F103,6),IF($F$2=2,INDEX(#REF!,$F103,6),INDEX(#REF!,$F103,6))))} | F103: =IF(F101>$E$2,"",MATCH(F101,'QC rev00'!$C$10:$C$120,)) | Q103: Valor | R103: =IFERROR(R102*$O101,0) -> 0 | S103: =IFERROR(S102*$O101,0) -> 0 | T103: =IFERROR(T102*$O101,0) -> 0 | U103: =IFERROR(U102*$O101,0) -> 0 | V103: =IFERROR(V102*$O101,0) -> 0 | W103: =IFERROR(W102*$O101,0) -> 0 | X103: =IFERROR(X102*$O101,0) -> 0 | Y103: =IFERROR(Y102*$O101,0) -> 0 | ... AK103: =IFERROR(AK102*$O101,0) -> 0
